Workbook

Sheet Start
B1: Pacifica: the financial model, 1846-1932
B2: Rebuilt from the master storyline of 18 October 2026: every canon event with a cost, the approved oil, turbine and electrical programmes, a real fleet, Japan's own budget and a world comparison.
B4: Case in use | C4: =Levers!F4 -> Story case | E4: Change it on Levers, cell E4 (1 = Story, 2 = Stress).
B5: Problems found by Checks, all years | C5: =SUM(Checks!S6:S92) -> 0 | E5: Zero means every year passes the arithmetic, the canon ceilings and the story checks.
B7: Key results | C7: 1850 | D7: 1865 | E7: 1880 | F7: 1895 | G7: 1905 | H7: 1913 | I7: 1918 | J7: 1922 | K7: 1929 | L7: 1932
B8: People and economy
B9: Residents (millions) | C9: =INDEX(People!$W$6:$W$92,MATCH(C$7,People!$A$6:$A$92,0))/1000000 -> 0.35280293 | D9: =INDEX(People!$W$6:$W$92,MATCH(D$7,People!$A$6:$A$92,0))/1000000 -> 1.9005936 | E9: =INDEX(People!$W$6:$W$92,MATCH(E$7,People!$A$6:$A$92,0))/1000000 -> 4.3604186 | F9: =INDEX(People!$W$6:$W$92,MATCH(F$7,People!$A$6:$A$92,0))/1000000 -> 8.3296699 | G9: =INDEX(People!$W$6:$W$92,MATCH(G$7,People!$A$6:$A$92,0))/1000000 -> 13.195122 | H9: =INDEX(People!$W$6:$W$92,MATCH(H$7,People!$A$6:$A$92,0))/1000000 -> 19.227664 | I9: =INDEX(People!$W$6:$W$92,MATCH(I$7,People!$A$6:$A$92,0))/1000000 -> 22.891194 | J9: =INDEX(People!$W$6:$W$92,MATCH(J$7,People!$A$6:$A$92,0))/1000000 -> 26.402898 | ... L9: =INDEX(People!$W$6:$W$92,MATCH(L$7,People!$A$6:$A$92,0))/1000000 -> 36.181178
B10: Asian-origin share of residents | C10: =INDEX(People!$S$6:$S$92,MATCH(C$7,People!$A$6:$A$92,0)) -> 0.018436588 | D10: =INDEX(People!$S$6:$S$92,MATCH(D$7,People!$A$6:$A$92,0)) -> 0.10370891 | E10: =INDEX(People!$S$6:$S$92,MATCH(E$7,People!$A$6:$A$92,0)) -> 0.14290257 | F10: =INDEX(People!$S$6:$S$92,MATCH(F$7,People!$A$6:$A$92,0)) -> 0.18528421 | G10: =INDEX(People!$S$6:$S$92,MATCH(G$7,People!$A$6:$A$92,0)) -> 0.2161103 | H10: =INDEX(People!$S$6:$S$92,MATCH(H$7,People!$A$6:$A$92,0)) -> 0.23557319 | I10: =INDEX(People!$S$6:$S$92,MATCH(I$7,People!$A$6:$A$92,0)) -> 0.25247851 | J10: =INDEX(People!$S$6:$S$92,MATCH(J$7,People!$A$6:$A$92,0)) -> 0.26668688 | ... L10: =INDEX(People!$S$6:$S$92,MATCH(L$7,People!$A$6:$A$92,0)) -> 0.29441177
B11: Guest workers present (thousands) | C11: =INDEX(Labour!$L$6:$L$92,MATCH(C$7,Labour!$A$6:$A$92,0))/1000 -> 0 | D11: =INDEX(Labour!$L$6:$L$92,MATCH(D$7,Labour!$A$6:$A$92,0))/1000 -> 0 | E11: =INDEX(Labour!$L$6:$L$92,MATCH(E$7,Labour!$A$6:$A$92,0))/1000 -> 0 | F11: =INDEX(Labour!$L$6:$L$92,MATCH(F$7,Labour!$A$6:$A$92,0))/1000 -> 251.60759 | G11: =INDEX(Labour!$L$6:$L$92,MATCH(G$7,Labour!$A$6:$A$92,0))/1000 -> 477.17542 | H11: =INDEX(Labour!$L$6:$L$92,MATCH(H$7,Labour!$A$6:$A$92,0))/1000 -> 695.21043 | I11: =INDEX(Labour!$L$6:$L$92,MATCH(I$7,Labour!$A$6:$A$92,0))/1000 -> 912.4506 | J11: =INDEX(Labour!$L$6:$L$92,MATCH(J$7,Labour!$A$6:$A$92,0))/1000 -> 892.35618 | ... L11: =INDEX(Labour!$L$6:$L$92,MATCH(L$7,Labour!$A$6:$A$92,0))/1000 -> 1010.6804
B12: Core GDP ($bn) | C12: =INDEX(Economy!$O$6:$O$92,MATCH(C$7,Economy!$A$6:$A$92,0))/1000 -> 0.089459911 | D12: =INDEX(Economy!$O$6:$O$92,MATCH(D$7,Economy!$A$6:$A$92,0))/1000 -> 0.53072279 | E12: =INDEX(Economy!$O$6:$O$92,MATCH(E$7,Economy!$A$6:$A$92,0))/1000 -> 1.4038748 | F12: =INDEX(Economy!$O$6:$O$92,MATCH(F$7,Economy!$A$6:$A$92,0))/1000 -> 3.4856786 | G12: =INDEX(Economy!$O$6:$O$92,MATCH(G$7,Economy!$A$6:$A$92,0))/1000 -> 8.4921785 | H12: =INDEX(Economy!$O$6:$O$92,MATCH(H$7,Economy!$A$6:$A$92,0))/1000 -> 17.784832 | I12: =INDEX(Economy!$O$6:$O$92,MATCH(I$7,Economy!$A$6:$A$92,0))/1000 -> 38.05454 | J12: =INDEX(Economy!$O$6:$O$92,MATCH(J$7,Economy!$A$6:$A$92,0))/1000 -> 43.385375 | ... L12: =INDEX(Economy!$O$6:$O$92,MATCH(L$7,Economy!$A$6:$A$92,0))/1000 -> 54.846119
B13: GDP per resident vs the US | C13: =INDEX(Economy!$R$6:$R$92,MATCH(C$7,Economy!$A$6:$A$92,0)) -> 2.7066951 | D13: =INDEX(Economy!$R$6:$R$92,MATCH(D$7,Economy!$A$6:$A$92,0)) -> 1.9047716 | E13: =INDEX(Economy!$R$6:$R$92,MATCH(E$7,Economy!$A$6:$A$92,0)) -> 1.5841317 | F13: =INDEX(Economy!$R$6:$R$92,MATCH(F$7,Economy!$A$6:$A$92,0)) -> 2.0732207 | G13: =INDEX(Economy!$R$6:$R$92,MATCH(G$7,Economy!$A$6:$A$92,0)) -> 2.195255 | H13: =INDEX(Economy!$R$6:$R$92,MATCH(H$7,Economy!$A$6:$A$92,0)) -> 2.2644002 | I13: =INDEX(Economy!$R$6:$R$92,MATCH(I$7,Economy!$A$6:$A$92,0)) -> 2.1970691 | J13: =INDEX(Economy!$R$6:$R$92,MATCH(J$7,Economy!$A$6:$A$92,0)) -> 2.3779239 | ... L13: =INDEX(Economy!$R$6:$R$92,MATCH(L$7,Economy!$A$6:$A$92,0)) -> 3.1374743
B14: Development Fund investment ($m) | C14: =INDEX('Debt & cash'!$N$6:$N$92,MATCH(C$7,'Debt & cash'!$A$6:$A$92,0)) -> 0 | D14: =INDEX('Debt & cash'!$N$6:$N$92,MATCH(D$7,'Debt & cash'!$A$6:$A$92,0)) -> 0 | E14: =INDEX('Debt & cash'!$N$6:$N$92,MATCH(E$7,'Debt & cash'!$A$6:$A$92,0)) -> 446.02902 | F14: =INDEX('Debt & cash'!$N$6:$N$92,MATCH(F$7,'Debt & cash'!$A$6:$A$92,0)) -> 20.817736 | G14: =INDEX('Debt & cash'!$N$6:$N$92,MATCH(G$7,'Debt & cash'!$A$6:$A$92,0)) -> 183.68426 | H14: =INDEX('Debt & cash'!$N$6:$N$92,MATCH(H$7,'Debt & cash'!$A$6:$A$92,0)) -> 376.91517 | I14: =INDEX('Debt & cash'!$N$6:$N$92,MATCH(I$7,'Debt & cash'!$A$6:$A$92,0)) -> 721.07514 | J14: =INDEX('Debt & cash'!$N$6:$N$92,MATCH(J$7,'Debt & cash'!$A$6:$A$92,0)) -> 787.44796 | ... L14: =INDEX('Debt & cash'!$N$6:$N$92,MATCH(L$7,'Debt & cash'!$A$6:$A$92,0)) -> 218.61235
B15: Oil output (m barrels) | C15: =INDEX(Resources!$K$6:$K$92,MATCH(C$7,Resources!$A$6:$A$92,0)) -> 0 | D15: =INDEX(Resources!$K$6:$K$92,MATCH(D$7,Resources!$A$6:$A$92,0)) -> 0 | E15: =INDEX(Resources!$K$6:$K$92,MATCH(E$7,Resources!$A$6:$A$92,0)) -> 0.05 | F15: =INDEX(Resources!$K$6:$K$92,MATCH(F$7,Resources!$A$6:$A$92,0)) -> 10 | G15: =INDEX(Resources!$K$6:$K$92,MATCH(G$7,Resources!$A$6:$A$92,0)) -> 50 | H15: =INDEX(Resources!$K$6:$K$92,MATCH(H$7,Resources!$A$6:$A$92,0)) -> 100 | I15: =INDEX(Resources!$K$6:$K$92,MATCH(I$7,Resources!$A$6:$A$92,0)) -> 105 | J15: =INDEX(Resources!$K$6:$K$92,MATCH(J$7,Resources!$A$6:$A$92,0)) -> 150 | ... L15: =INDEX(Resources!$K$6:$K$92,MATCH(L$7,Resources!$A$6:$A$92,0)) -> 153
B16: National champions at home ($m) | C16: =INDEX(Champions!$AP$6:$AP$92,MATCH(C$7,Champions!$A$6:$A$92,0)) -> 0 | D16: =INDEX(Champions!$AP$6:$AP$92,MATCH(D$7,Champions!$A$6:$A$92,0)) -> 2.1188156 | E16: =INDEX(Champions!$AP$6:$AP$92,MATCH(E$7,Champions!$A$6:$A$92,0)) -> 25.726157 | F16: =INDEX(Champions!$AP$6:$AP$92,MATCH(F$7,Champions!$A$6:$A$92,0)) -> 134.12356 | G16: =INDEX(Champions!$AP$6:$AP$92,MATCH(G$7,Champions!$A$6:$A$92,0)) -> 372.65973 | H16: =INDEX(Champions!$AP$6:$AP$92,MATCH(H$7,Champions!$A$6:$A$92,0)) -> 751.60124 | I16: =INDEX(Champions!$AP$6:$AP$92,MATCH(I$7,Champions!$A$6:$A$92,0)) -> 1820.283 | J16: =INDEX(Champions!$AP$6:$AP$92,MATCH(J$7,Champions!$A$6:$A$92,0)) -> 2169.6299 | ... L16: =INDEX(Champions!$AP$6:$AP$92,MATCH(L$7,Champions!$A$6:$A$92,0)) -> 2580.9661
B17: Champions' assets abroad ($m) | C17: =INDEX(Champions!$AY$6:$AY$92,MATCH(C$7,Champions!$A$6:$A$92,0)) -> 0 | D17: =INDEX(Champions!$AY$6:$AY$92,MATCH(D$7,Champions!$A$6:$A$92,0)) -> 0 | E17: =INDEX(Champions!$AY$6:$AY$92,MATCH(E$7,Champions!$A$6:$A$92,0)) -> 52.121125 | F17: =INDEX(Champions!$AY$6:$AY$92,MATCH(F$7,Champions!$A$6:$A$92,0)) -> 348.39172 | G17: =INDEX(Champions!$AY$6:$AY$92,MATCH(G$7,Champions!$A$6:$A$92,0)) -> 1850.0567 | H17: =INDEX(Champions!$AY$6:$AY$92,MATCH(H$7,Champions!$A$6:$A$92,0)) -> 3158.3206 | I17: =INDEX(Champions!$AY$6:$AY$92,MATCH(I$7,Champions!$A$6:$A$92,0)) -> 4601.5182 | J17: =INDEX(Champions!$AY$6:$AY$92,MATCH(J$7,Champions!$A$6:$A$92,0)) -> 6566.4413 | ... L17: =INDEX(Champions!$AY$6:$AY$92,MATCH(L$7,Champions!$A$6:$A$92,0)) -> 9716.7072
B18: Patents per resident vs the US | C18: =INDEX(Champions!$I$6:$I$92,MATCH(C$7,Champions!$A$6:$A$92,0)) -> 0 | D18: =INDEX(Champions!$I$6:$I$92,MATCH(D$7,Champions!$A$6:$A$92,0)) -> 0.29500056 | E18: =INDEX(Champions!$I$6:$I$92,MATCH(E$7,Champions!$A$6:$A$92,0)) -> 1.0490154 | F18: =INDEX(Champions!$I$6:$I$92,MATCH(F$7,Champions!$A$6:$A$92,0)) -> 1.4538065 | G18: =INDEX(Champions!$I$6:$I$92,MATCH(G$7,Champions!$A$6:$A$92,0)) -> 1.7892297 | H18: =INDEX(Champions!$I$6:$I$92,MATCH(H$7,Champions!$A$6:$A$92,0)) -> 1.6276533 | I18: =INDEX(Champions!$I$6:$I$92,MATCH(I$7,Champions!$A$6:$A$92,0)) -> 1.6302071 | J18: =INDEX(Champions!$I$6:$I$92,MATCH(J$7,Champions!$A$6:$A$92,0)) -> 1.6642104 | ... L18: =INDEX(Champions!$I$6:$I$92,MATCH(L$7,Champions!$A$6:$A$92,0)) -> 1.2513167
B19: Extra arrivals drawn by the lead | C19: =INDEX(Labour!$AL$6:$AL$92,MATCH(C$7,Labour!$A$6:$A$92,0)) -> 0 | D19: =INDEX(Labour!$AL$6:$AL$92,MATCH(D$7,Labour!$A$6:$A$92,0)) -> 10729.839 | E19: =INDEX(Labour!$AL$6:$AL$92,MATCH(E$7,Labour!$A$6:$A$92,0)) -> 33751.353 | F19: =INDEX(Labour!$AL$6:$AL$92,MATCH(F$7,Labour!$A$6:$A$92,0)) -> 128663.33 | G19: =INDEX(Labour!$AL$6:$AL$92,MATCH(G$7,Labour!$A$6:$A$92,0)) -> 311422.17 | H19: =INDEX(Labour!$AL$6:$AL$92,MATCH(H$7,Labour!$A$6:$A$92,0)) -> 332155.67 | I19: =INDEX(Labour!$AL$6:$AL$92,MATCH(I$7,Labour!$A$6:$A$92,0)) -> 165282.01 | J19: =INDEX(Labour!$AL$6:$AL$92,MATCH(J$7,Labour!$A$6:$A$92,0)) -> 328439.07 | ... L19: =INDEX(Labour!$AL$6:$AL$92,MATCH(L$7,Labour!$A$6:$A$92,0)) -> 304486.38
B20: Champion-related jobs / labour force | C20: =INDEX(Labour!$G$6:$G$92,MATCH(C$7,Labour!$A$6:$A$92,0)) -> 0 | D20: =INDEX(Labour!$G$6:$G$92,MATCH(D$7,Labour!$A$6:$A$92,0)) -> 0.0037705251 | E20: =INDEX(Labour!$G$6:$G$92,MATCH(E$7,Labour!$A$6:$A$92,0)) -> 0.017307046 | F20: =INDEX(Labour!$G$6:$G$92,MATCH(F$7,Labour!$A$6:$A$92,0)) -> 0.039010417 | G20: =INDEX(Labour!$G$6:$G$92,MATCH(G$7,Labour!$A$6:$A$92,0)) -> 0.045105629 | H20: =INDEX(Labour!$G$6:$G$92,MATCH(H$7,Labour!$A$6:$A$92,0)) -> 0.043428298 | I20: =INDEX(Labour!$G$6:$G$92,MATCH(I$7,Labour!$A$6:$A$92,0)) -> 0.049527061 | J20: =INDEX(Labour!$G$6:$G$92,MATCH(J$7,Labour!$A$6:$A$92,0)) -> 0.051098745 | ... L20: =INDEX(Labour!$G$6:$G$92,MATCH(L$7,Labour!$A$6:$A$92,0)) -> 0.047438561
B21: Union output lost to Pacifica | C21: =INDEX(Labour!$BL$6:$BL$92,MATCH(C$7,Labour!$A$6:$A$92,0)) -> 0.000239162 | D21: =INDEX(Labour!$BL$6:$BL$92,MATCH(D$7,Labour!$A$6:$A$92,0)) -> 0.012776027 | E21: =INDEX(Labour!$BL$6:$BL$92,MATCH(E$7,Labour!$A$6:$A$92,0)) -> 0.041271792 | F21: =INDEX(Labour!$BL$6:$BL$92,MATCH(F$7,Labour!$A$6:$A$92,0)) -> 0.086575049 | G21: =INDEX(Labour!$BL$6:$BL$92,MATCH(G$7,Labour!$A$6:$A$92,0)) -> 0.13733836 | H21: =INDEX(Labour!$BL$6:$BL$92,MATCH(H$7,Labour!$A$6:$A$92,0)) -> 0.17093966 | I21: =INDEX(Labour!$BL$6:$BL$92,MATCH(I$7,Labour!$A$6:$A$92,0)) -> 0.19017257 | J21: =INDEX(Labour!$BL$6:$BL$92,MATCH(J$7,Labour!$A$6:$A$92,0)) -> 0.20659515 | ... L21: =INDEX(Labour!$BL$6:$BL$92,MATCH(L$7,Labour!$A$6:$A$92,0)) -> 0.31652374
B22: Union population (m) | C22: =INDEX(Labour!$AX$6:$AX$92,MATCH(C$7,Labour!$A$6:$A$92,0)) -> 16.87 | D22: =INDEX(Labour!$AX$6:$AX$92,MATCH(D$7,Labour!$A$6:$A$92,0)) -> 24.933288 | E22: =INDEX(Labour!$AX$6:$AX$92,MATCH(E$7,Labour!$A$6:$A$92,0)) -> 39.727081 | F22: =INDEX(Labour!$AX$6:$AX$92,MATCH(F$7,Labour!$A$6:$A$92,0)) -> 53.621174 | G22: =INDEX(Labour!$AX$6:$AX$92,MATCH(G$7,Labour!$A$6:$A$92,0)) -> 63.281477 | H22: =INDEX(Labour!$AX$6:$AX$92,MATCH(H$7,Labour!$A$6:$A$92,0)) -> 71.893629 | I22: =INDEX(Labour!$AX$6:$AX$92,MATCH(I$7,Labour!$A$6:$A$92,0)) -> 75.401657 | J22: =INDEX(Labour!$AX$6:$AX$92,MATCH(J$7,Labour!$A$6:$A$92,0)) -> 78.407832 | ... L22: =INDEX(Labour!$AX$6:$AX$92,MATCH(L$7,Labour!$A$6:$A$92,0)) -> 85.850319
B23: Income from abroad ($m) | C23: =INDEX(Abroad!$M$6:$M$92,MATCH(C$7,Abroad!$A$6:$A$92,0)) -> 0.016660753 | D23: =INDEX(Abroad!$M$6:$M$92,MATCH(D$7,Abroad!$A$6:$A$92,0)) -> 0.38852724 | E23: =INDEX(Abroad!$M$6:$M$92,MATCH(E$7,Abroad!$A$6:$A$92,0)) -> 7.7105338 | F23: =INDEX(Abroad!$M$6:$M$92,MATCH(F$7,Abroad!$A$6:$A$92,0)) -> 39.600522 | G23: =INDEX(Abroad!$M$6:$M$92,MATCH(G$7,Abroad!$A$6:$A$92,0)) -> 203.38308 | H23: =INDEX(Abroad!$M$6:$M$92,MATCH(H$7,Abroad!$A$6:$A$92,0)) -> 401.58639 | I23: =INDEX(Abroad!$M$6:$M$92,MATCH(I$7,Abroad!$A$6:$A$92,0)) -> 733.46391 | J23: =INDEX(Abroad!$M$6:$M$92,MATCH(J$7,Abroad!$A$6:$A$92,0)) -> 1234.8877 | ... L23: =INDEX(Abroad!$M$6:$M$92,MATCH(L$7,Abroad!$A$6:$A$92,0)) -> 1499.7244
B24: National income ($bn) | C24: =INDEX(Abroad!$P$6:$P$92,MATCH(C$7,Abroad!$A$6:$A$92,0))/1000 -> 0.089476572 | D24: =INDEX(Abroad!$P$6:$P$92,MATCH(D$7,Abroad!$A$6:$A$92,0))/1000 -> 0.53111132 | E24: =INDEX(Abroad!$P$6:$P$92,MATCH(E$7,Abroad!$A$6:$A$92,0))/1000 -> 1.410797 | F24: =INDEX(Abroad!$P$6:$P$92,MATCH(F$7,Abroad!$A$6:$A$92,0))/1000 -> 3.4924339 | G24: =INDEX(Abroad!$P$6:$P$92,MATCH(G$7,Abroad!$A$6:$A$92,0))/1000 -> 8.5629107 | H24: =INDEX(Abroad!$P$6:$P$92,MATCH(H$7,Abroad!$A$6:$A$92,0))/1000 -> 17.952344 | I24: =INDEX(Abroad!$P$6:$P$92,MATCH(I$7,Abroad!$A$6:$A$92,0))/1000 -> 38.344649 | J24: =INDEX(Abroad!$P$6:$P$92,MATCH(J$7,Abroad!$A$6:$A$92,0))/1000 -> 44.142542 | ... L24: =INDEX(Abroad!$P$6:$P$92,MATCH(L$7,Abroad!$A$6:$A$92,0))/1000 -> 55.773407
B25: Treasury
B26: Receipts ($m) | C26: =INDEX(Budget!$M$6:$M$92,MATCH(C$7,Budget!$A$6:$A$92,0)) -> 7.7742456 | D26: =INDEX(Budget!$M$6:$M$92,MATCH(D$7,Budget!$A$6:$A$92,0)) -> 68.560763 | E26: =INDEX(Budget!$M$6:$M$92,MATCH(E$7,Budget!$A$6:$A$92,0)) -> 187.92018 | F26: =INDEX(Budget!$M$6:$M$92,MATCH(F$7,Budget!$A$6:$A$92,0)) -> 380.65575 | G26: =INDEX(Budget!$M$6:$M$92,MATCH(G$7,Budget!$A$6:$A$92,0)) -> 857.87667 | H26: =INDEX(Budget!$M$6:$M$92,MATCH(H$7,Budget!$A$6:$A$92,0)) -> 1753.8047 | I26: =INDEX(Budget!$M$6:$M$92,MATCH(I$7,Budget!$A$6:$A$92,0)) -> 4435.0423 | J26: =INDEX(Budget!$M$6:$M$92,MATCH(J$7,Budget!$A$6:$A$92,0)) -> 4544.4058 | ... L26: =INDEX(Budget!$M$6:$M$92,MATCH(L$7,Budget!$A$6:$A$92,0)) -> 5330.0415
B27: Crown share dividends ($m) | C27: =INDEX(Budget!$K$6:$K$92,MATCH(C$7,Budget!$A$6:$A$92,0)) -> 0 | D27: =INDEX(Budget!$K$6:$K$92,MATCH(D$7,Budget!$A$6:$A$92,0)) -> 0 | E27: =INDEX(Budget!$K$6:$K$92,MATCH(E$7,Budget!$A$6:$A$92,0)) -> 0.97533384 | F27: =INDEX(Budget!$K$6:$K$92,MATCH(F$7,Budget!$A$6:$A$92,0)) -> 5.2882159 | G27: =INDEX(Budget!$K$6:$K$92,MATCH(G$7,Budget!$A$6:$A$92,0)) -> 18.682667 | H27: =INDEX(Budget!$K$6:$K$92,MATCH(H$7,Budget!$A$6:$A$92,0)) -> 35.727657 | I27: =INDEX(Budget!$K$6:$K$92,MATCH(I$7,Budget!$A$6:$A$92,0)) -> 67.896409 | J27: =INDEX(Budget!$K$6:$K$92,MATCH(J$7,Budget!$A$6:$A$92,0)) -> 95.257938 | ... L27: =INDEX(Budget!$K$6:$K$92,MATCH(L$7,Budget!$A$6:$A$92,0)) -> 104.66775
B28: Guest-worker levy ($m) | C28: =INDEX(Budget!$J$6:$J$92,MATCH(C$7,Budget!$A$6:$A$92,0)) -> 0 | D28: =INDEX(Budget!$J$6:$J$92,MATCH(D$7,Budget!$A$6:$A$92,0)) -> 0 | E28: =INDEX(Budget!$J$6:$J$92,MATCH(E$7,Budget!$A$6:$A$92,0)) -> 0 | F28: =INDEX(Budget!$J$6:$J$92,MATCH(F$7,Budget!$A$6:$A$92,0)) -> 22.903459 | G28: =INDEX(Budget!$J$6:$J$92,MATCH(G$7,Budget!$A$6:$A$92,0)) -> 66.323025 | H28: =INDEX(Budget!$J$6:$J$92,MATCH(H$7,Budget!$A$6:$A$92,0)) -> 139.32065 | I28: =INDEX(Budget!$J$6:$J$92,MATCH(I$7,Budget!$A$6:$A$92,0)) -> 323.38067 | J28: =INDEX(Budget!$J$6:$J$92,MATCH(J$7,Budget!$A$6:$A$92,0)) -> 316.79547 | ... L28: =INDEX(Budget!$J$6:$J$92,MATCH(L$7,Budget!$A$6:$A$92,0)) -> 334.03131
B29: Spending ($m) | C29: =INDEX(Budget!$Y$6:$Y$92,MATCH(C$7,Budget!$A$6:$A$92,0)) -> 7.515048 | D29: =INDEX(Budget!$Y$6:$Y$92,MATCH(D$7,Budget!$A$6:$A$92,0)) -> 58.074635 | E29: =INDEX(Budget!$Y$6:$Y$92,MATCH(E$7,Budget!$A$6:$A$92,0)) -> 119.94803 | F29: =INDEX(Budget!$Y$6:$Y$92,MATCH(F$7,Budget!$A$6:$A$92,0)) -> 292.62049 | G29: =INDEX(Budget!$Y$6:$Y$92,MATCH(G$7,Budget!$A$6:$A$92,0)) -> 656.90278 | H29: =INDEX(Budget!$Y$6:$Y$92,MATCH(H$7,Budget!$A$6:$A$92,0)) -> 1398.709 | I29: =INDEX(Budget!$Y$6:$Y$92,MATCH(I$7,Budget!$A$6:$A$92,0)) -> 3294.7738 | J29: =INDEX(Budget!$Y$6:$Y$92,MATCH(J$7,Budget!$A$6:$A$92,0)) -> 3507.0311 | ... L29: =INDEX(Budget!$Y$6:$Y$92,MATCH(L$7,Budget!$A$6:$A$92,0)) -> 5001.3762
B30: Defence & overseas / GDP | C30: =INDEX(Budget!$AC$6:$AC$92,MATCH(C$7,Budget!$A$6:$A$92,0)) -> 0.013648572 | D30: =INDEX(Budget!$AC$6:$AC$92,MATCH(D$7,Budget!$A$6:$A$92,0)) -> 0.050429886 | E30: =INDEX(Budget!$AC$6:$AC$92,MATCH(E$7,Budget!$A$6:$A$92,0)) -> 0.014531666 | F30: =INDEX(Budget!$AC$6:$AC$92,MATCH(F$7,Budget!$A$6:$A$92,0)) -> 0.0069343391 | G30: =INDEX(Budget!$AC$6:$AC$92,MATCH(G$7,Budget!$A$6:$A$92,0)) -> 0.0061317934 | H30: =INDEX(Budget!$AC$6:$AC$92,MATCH(H$7,Budget!$A$6:$A$92,0)) -> 0.0057507348 | I30: =INDEX(Budget!$AC$6:$AC$92,MATCH(I$7,Budget!$A$6:$A$92,0)) -> 0.011053752 | J30: =INDEX(Budget!$AC$6:$AC$92,MATCH(J$7,Budget!$A$6:$A$92,0)) -> 0.0055404538 | ... L30: =INDEX(Budget!$AC$6:$AC$92,MATCH(L$7,Budget!$A$6:$A$92,0)) -> 0.0039313037
B31: Public debt ($m) | C31: =INDEX('Debt & cash'!$R$6:$R$92,MATCH(C$7,'Debt & cash'!$A$6:$A$92,0)) -> 17.018376 | D31: =INDEX('Debt & cash'!$R$6:$R$92,MATCH(D$7,'Debt & cash'!$A$6:$A$92,0)) -> 13.277584 | E31: =INDEX('Debt & cash'!$R$6:$R$92,MATCH(E$7,'Debt & cash'!$A$6:$A$92,0)) -> 0 | F31: =INDEX('Debt & cash'!$R$6:$R$92,MATCH(F$7,'Debt & cash'!$A$6:$A$92,0)) -> 174.28393 | G31: =INDEX('Debt & cash'!$R$6:$R$92,MATCH(G$7,'Debt & cash'!$A$6:$A$92,0)) -> 424.60892 | H31: =INDEX('Debt & cash'!$R$6:$R$92,MATCH(H$7,'Debt & cash'!$A$6:$A$92,0)) -> 889.24158 | I31: =INDEX('Debt & cash'!$R$6:$R$92,MATCH(I$7,'Debt & cash'!$A$6:$A$92,0)) -> 1902.727 | J31: =INDEX('Debt & cash'!$R$6:$R$92,MATCH(J$7,'Debt & cash'!$A$6:$A$92,0)) -> 2169.2688 | ... L31: =INDEX('Debt & cash'!$R$6:$R$92,MATCH(L$7,'Debt & cash'!$A$6:$A$92,0)) -> 2920.4904
B32: Debt / GDP | C32: =INDEX('Debt & cash'!$V$6:$V$92,MATCH(C$7,'Debt & cash'!$A$6:$A$92,0)) -> 0.19023467 | D32: =INDEX('Debt & cash'!$V$6:$V$92,MATCH(D$7,'Debt & cash'!$A$6:$A$92,0)) -> 0.025017926 | E32: =INDEX('Debt & cash'!$V$6:$V$92,MATCH(E$7,'Debt & cash'!$A$6:$A$92,0)) -> 0 | F32: =INDEX('Debt & cash'!$V$6:$V$92,MATCH(F$7,'Debt & cash'!$A$6:$A$92,0)) -> 0.05 | G32: =INDEX('Debt & cash'!$V$6:$V$92,MATCH(G$7,'Debt & cash'!$A$6:$A$92,0)) -> 0.05 | H32: =INDEX('Debt & cash'!$V$6:$V$92,MATCH(H$7,'Debt & cash'!$A$6:$A$92,0)) -> 0.05 | I32: =INDEX('Debt & cash'!$V$6:$V$92,MATCH(I$7,'Debt & cash'!$A$6:$A$92,0)) -> 0.05 | J32: =INDEX('Debt & cash'!$V$6:$V$92,MATCH(J$7,'Debt & cash'!$A$6:$A$92,0)) -> 0.05 | ... L32: =INDEX('Debt & cash'!$V$6:$V$92,MATCH(L$7,'Debt & cash'!$A$6:$A$92,0)) -> 0.053248808
B33: Treasury Reserve Fund ($m) | C33: =INDEX('Debt & cash'!$S$6:$S$92,MATCH(C$7,'Debt & cash'!$A$6:$A$92,0)) -> 0 | D33: =INDEX('Debt & cash'!$S$6:$S$92,MATCH(D$7,'Debt & cash'!$A$6:$A$92,0)) -> 1.7243131 | E33: =INDEX('Debt & cash'!$S$6:$S$92,MATCH(E$7,'Debt & cash'!$A$6:$A$92,0)) -> 62.025853 | F33: =INDEX('Debt & cash'!$S$6:$S$92,MATCH(F$7,'Debt & cash'!$A$6:$A$92,0)) -> 87.864949 | G33: =INDEX('Debt & cash'!$S$6:$S$92,MATCH(G$7,'Debt & cash'!$A$6:$A$92,0)) -> 148.03386 | H33: =INDEX('Debt & cash'!$S$6:$S$92,MATCH(H$7,'Debt & cash'!$A$6:$A$92,0)) -> 267.52047 | I33: =INDEX('Debt & cash'!$S$6:$S$92,MATCH(I$7,'Debt & cash'!$A$6:$A$92,0)) -> 361.88634 | J33: =INDEX('Debt & cash'!$S$6:$S$92,MATCH(J$7,'Debt & cash'!$A$6:$A$92,0)) -> 610.82105 | ... L33: =INDEX('Debt & cash'!$S$6:$S$92,MATCH(L$7,'Debt & cash'!$A$6:$A$92,0)) -> 1344.0797
B34: Loans abroad outstanding ($m) | C34: =INDEX(Loans!$X$6:$X$92,MATCH(C$7,Loans!$A$6:$A$92,0)) -> 0 | D34: =INDEX(Loans!$X$6:$X$92,MATCH(D$7,Loans!$A$6:$A$92,0)) -> 0 | E34: =INDEX(Loans!$X$6:$X$92,MATCH(E$7,Loans!$A$6:$A$92,0)) -> 29.765514 | F34: =INDEX(Loans!$X$6:$X$92,MATCH(F$7,Loans!$A$6:$A$92,0)) -> 113.35301 | G34: =INDEX(Loans!$X$6:$X$92,MATCH(G$7,Loans!$A$6:$A$92,0)) -> 189.84116 | H34: =INDEX(Loans!$X$6:$X$92,MATCH(H$7,Loans!$A$6:$A$92,0)) -> 137.06972 | I34: =INDEX(Loans!$X$6:$X$92,MATCH(I$7,Loans!$A$6:$A$92,0)) -> 1654.8606 | J34: =INDEX(Loans!$X$6:$X$92,MATCH(J$7,Loans!$A$6:$A$92,0)) -> 2380.0908 | ... L34: =INDEX(Loans!$X$6:$X$92,MATCH(L$7,Loans!$A$6:$A$92,0)) -> 2651.9826
B35: Monetary gold ($m) | C35: =INDEX('Gold & money'!$F$6:$F$92,MATCH(C$7,'Gold & money'!$A$6:$A$92,0)) -> 18.37892 | D35: =INDEX('Gold & money'!$F$6:$F$92,MATCH(D$7,'Gold & money'!$A$6:$A$92,0)) -> 190.37822 | E35: =INDEX('Gold & money'!$F$6:$F$92,MATCH(E$7,'Gold & money'!$A$6:$A$92,0)) -> 303.86467 | F35: =INDEX('Gold & money'!$F$6:$F$92,MATCH(F$7,'Gold & money'!$A$6:$A$92,0)) -> 389.62172 | G35: =INDEX('Gold & money'!$F$6:$F$92,MATCH(G$7,'Gold & money'!$A$6:$A$92,0)) -> 598.10071 | H35: =INDEX('Gold & money'!$F$6:$F$92,MATCH(H$7,'Gold & money'!$A$6:$A$92,0)) -> 951.94144 | I35: =INDEX('Gold & money'!$F$6:$F$92,MATCH(I$7,'Gold & money'!$A$6:$A$92,0)) -> 1299.5056 | J35: =INDEX('Gold & money'!$F$6:$F$92,MATCH(J$7,'Gold & money'!$A$6:$A$92,0)) -> 1707.6315 | ... L35: =INDEX('Gold & money'!$F$6:$F$92,MATCH(L$7,'Gold & money'!$A$6:$A$92,0)) -> 2363.0908
B36: Navy
B37: Pacifica's navy bill ($m) | C37: =INDEX(Navy!$Y$6:$Y$92,MATCH(C$7,Navy!$A$6:$A$92,0)) -> 0 | D37: =INDEX(Navy!$Y$6:$Y$92,MATCH(D$7,Navy!$A$6:$A$92,0)) -> 3.77429 | E37: =INDEX(Navy!$Y$6:$Y$92,MATCH(E$7,Navy!$A$6:$A$92,0)) -> 7.76064 | F37: =INDEX(Navy!$Y$6:$Y$92,MATCH(F$7,Navy!$A$6:$A$92,0)) -> 8.8141188 | G37: =INDEX(Navy!$Y$6:$Y$92,MATCH(G$7,Navy!$A$6:$A$92,0)) -> 28.711684 | H37: =INDEX(Navy!$Y$6:$Y$92,MATCH(H$7,Navy!$A$6:$A$92,0)) -> 74.37585 | I37: =INDEX(Navy!$Y$6:$Y$92,MATCH(I$7,Navy!$A$6:$A$92,0)) -> 152.38039 | J37: =INDEX(Navy!$Y$6:$Y$92,MATCH(J$7,Navy!$A$6:$A$92,0)) -> 145.28468 | ... L37: =INDEX(Navy!$Y$6:$Y$92,MATCH(L$7,Navy!$A$6:$A$92,0)) -> 163.22577
B38: Ships in service | C38: =INDEX(Navy!$K$6:$K$92,MATCH(C$7,Navy!$A$6:$A$92,0)) -> 0 | D38: =INDEX(Navy!$K$6:$K$92,MATCH(D$7,Navy!$A$6:$A$92,0)) -> 12 | E38: =INDEX(Navy!$K$6:$K$92,MATCH(E$7,Navy!$A$6:$A$92,0)) -> 25 | F38: =INDEX(Navy!$K$6:$K$92,MATCH(F$7,Navy!$A$6:$A$92,0)) -> 49 | G38: =INDEX(Navy!$K$6:$K$92,MATCH(G$7,Navy!$A$6:$A$92,0)) -> 68 | H38: =INDEX(Navy!$K$6:$K$92,MATCH(H$7,Navy!$A$6:$A$92,0)) -> 115 | I38: =INDEX(Navy!$K$6:$K$92,MATCH(I$7,Navy!$A$6:$A$92,0)) -> 183 | J38: =INDEX(Navy!$K$6:$K$92,MATCH(J$7,Navy!$A$6:$A$92,0)) -> 180 | ... L38: =INDEX(Navy!$K$6:$K$92,MATCH(L$7,Navy!$A$6:$A$92,0)) -> 162
B39: Capital ships: Pacifica | C39: =INDEX(Navy!$AA$6:$AA$92,MATCH(C$7,Navy!$A$6:$A$92,0)) -> 0 | D39: =INDEX(Navy!$AA$6:$AA$92,MATCH(D$7,Navy!$A$6:$A$92,0)) -> 0 | E39: =INDEX(Navy!$AA$6:$AA$92,MATCH(E$7,Navy!$A$6:$A$92,0)) -> 0 | F39: =INDEX(Navy!$AA$6:$AA$92,MATCH(F$7,Navy!$A$6:$A$92,0)) -> 0 | G39: =INDEX(Navy!$AA$6:$AA$92,MATCH(G$7,Navy!$A$6:$A$92,0)) -> 2 | H39: =INDEX(Navy!$AA$6:$AA$92,MATCH(H$7,Navy!$A$6:$A$92,0)) -> 9 | I39: =INDEX(Navy!$AA$6:$AA$92,MATCH(I$7,Navy!$A$6:$A$92,0)) -> 14 | J39: =INDEX(Navy!$AA$6:$AA$92,MATCH(J$7,Navy!$A$6:$A$92,0)) -> 14 | ... L39: =INDEX(Navy!$AA$6:$AA$92,MATCH(L$7,Navy!$A$6:$A$92,0)) -> 14
B40: Capital ships: Pacifica + Japan / Britain | C40: =INDEX(Navy!$AE$6:$AE$92,MATCH(C$7,Navy!$A$6:$A$92,0)) -> 0 | D40: =INDEX(Navy!$AE$6:$AE$92,MATCH(D$7,Navy!$A$6:$A$92,0)) -> 0 | E40: =INDEX(Navy!$AE$6:$AE$92,MATCH(E$7,Navy!$A$6:$A$92,0)) -> 0 | F40: =INDEX(Navy!$AE$6:$AE$92,MATCH(F$7,Navy!$A$6:$A$92,0)) -> 0 | G40: =INDEX(Navy!$AE$6:$AE$92,MATCH(G$7,Navy!$A$6:$A$92,0)) -> 0 | H40: =INDEX(Navy!$AE$6:$AE$92,MATCH(H$7,Navy!$A$6:$A$92,0)) -> 0.59090909 | I40: =INDEX(Navy!$AE$6:$AE$92,MATCH(I$7,Navy!$A$6:$A$92,0)) -> 0.52380952 | J40: =INDEX(Navy!$AE$6:$AE$92,MATCH(J$7,Navy!$A$6:$A$92,0)) -> 1 | ... L40: =INDEX(Navy!$AE$6:$AE$92,MATCH(L$7,Navy!$A$6:$A$92,0)) -> 1
B41: Sailors saved by oil firing | C41: =INDEX(Navy!$O$6:$O$92,MATCH(C$7,Navy!$A$6:$A$92,0)) -> 0 | D41: =INDEX(Navy!$O$6:$O$92,MATCH(D$7,Navy!$A$6:$A$92,0)) -> 0 | E41: =INDEX(Navy!$O$6:$O$92,MATCH(E$7,Navy!$A$6:$A$92,0)) -> 0 | F41: =INDEX(Navy!$O$6:$O$92,MATCH(F$7,Navy!$A$6:$A$92,0)) -> 747.4359 | G41: =INDEX(Navy!$O$6:$O$92,MATCH(G$7,Navy!$A$6:$A$92,0)) -> 3111.0256 | H41: =INDEX(Navy!$O$6:$O$92,MATCH(H$7,Navy!$A$6:$A$92,0)) -> 6611.2821 | I41: =INDEX(Navy!$O$6:$O$92,MATCH(I$7,Navy!$A$6:$A$92,0)) -> 9632.0513 | J41: =INDEX(Navy!$O$6:$O$92,MATCH(J$7,Navy!$A$6:$A$92,0)) -> 9691.2821 | ... L41: =INDEX(Navy!$O$6:$O$92,MATCH(L$7,Navy!$A$6:$A$92,0)) -> 10438.718
B42: Japan
B43: Japan GDP ($bn) | C43: =INDEX(Japan!$D$6:$D$92,MATCH(C$7,Japan!$A$6:$A$92,0))/1000 -> 0 | D43: =INDEX(Japan!$D$6:$D$92,MATCH(D$7,Japan!$A$6:$A$92,0))/1000 -> 0 | E43: =INDEX(Japan!$D$6:$D$92,MATCH(E$7,Japan!$A$6:$A$92,0))/1000 -> 0.68259556 | F43: =INDEX(Japan!$D$6:$D$92,MATCH(F$7,Japan!$A$6:$A$92,0))/1000 -> 1.1694425 | G43: =INDEX(Japan!$D$6:$D$92,MATCH(G$7,Japan!$A$6:$A$92,0))/1000 -> 2.6348526 | H43: =INDEX(Japan!$D$6:$D$92,MATCH(H$7,Japan!$A$6:$A$92,0))/1000 -> 4.9179306 | I43: =INDEX(Japan!$D$6:$D$92,MATCH(I$7,Japan!$A$6:$A$92,0))/1000 -> 12.934733 | J43: =INDEX(Japan!$D$6:$D$92,MATCH(J$7,Japan!$A$6:$A$92,0))/1000 -> 17.654799 | ... L43: =INDEX(Japan!$D$6:$D$92,MATCH(L$7,Japan!$A$6:$A$92,0))/1000 -> 17.654926
B44: Japan output per person vs the US | C44: =INDEX(Partners!$J$6:$J$92,MATCH(C$7,Partners!$A$6:$A$92,0)) -> 0 | D44: =INDEX(Partners!$J$6:$J$92,MATCH(D$7,Partners!$A$6:$A$92,0)) -> 0 | E44: =INDEX(Partners!$J$6:$J$92,MATCH(E$7,Partners!$A$6:$A$92,0)) -> 0.089664191 | F44: =INDEX(Partners!$J$6:$J$92,MATCH(F$7,Partners!$A$6:$A$92,0)) -> 0.13921935 | G44: =INDEX(Partners!$J$6:$J$92,MATCH(G$7,Partners!$A$6:$A$92,0)) -> 0.19409738 | H44: =INDEX(Partners!$J$6:$J$92,MATCH(H$7,Partners!$A$6:$A$92,0)) -> 0.23788113 | I44: =INDEX(Partners!$J$6:$J$92,MATCH(I$7,Partners!$A$6:$A$92,0)) -> 0.32065017 | J44: =INDEX(Partners!$J$6:$J$92,MATCH(J$7,Partners!$A$6:$A$92,0)) -> 0.45019835 | ... L44: =INDEX(Partners!$J$6:$J$92,MATCH(L$7,Partners!$A$6:$A$92,0)) -> 0.55858706
B45: Partners' output vs history | C45: =INDEX(Partners!$CA$6:$CA$92,MATCH(C$7,Partners!$A$6:$A$92,0)) -> 0 | D45: =INDEX(Partners!$CA$6:$CA$92,MATCH(D$7,Partners!$A$6:$A$92,0)) -> 0 | E45: =INDEX(Partners!$CA$6:$CA$92,MATCH(E$7,Partners!$A$6:$A$92,0)) -> 1.1226765 | F45: =INDEX(Partners!$CA$6:$CA$92,MATCH(F$7,Partners!$A$6:$A$92,0)) -> 1.3898307 | G45: =INDEX(Partners!$CA$6:$CA$92,MATCH(G$7,Partners!$A$6:$A$92,0)) -> 1.4085475 | H45: =INDEX(Partners!$CA$6:$CA$92,MATCH(H$7,Partners!$A$6:$A$92,0)) -> 1.5726635 | I45: =INDEX(Partners!$CA$6:$CA$92,MATCH(I$7,Partners!$A$6:$A$92,0)) -> 1.7240063 | J45: =INDEX(Partners!$CA$6:$CA$92,MATCH(J$7,Partners!$A$6:$A$92,0)) -> 1.8199185 | ... L45: =INDEX(Partners!$CA$6:$CA$92,MATCH(L$7,Partners!$A$6:$A$92,0)) -> 2.1351967
B46: Champions' markets abroad vs history | C46: =INDEX(Partners!$BW$6:$BW$92,MATCH(C$7,Partners!$A$6:$A$92,0)) -> 1 | D46: =INDEX(Partners!$BW$6:$BW$92,MATCH(D$7,Partners!$A$6:$A$92,0)) -> 1.0008626 | E46: =INDEX(Partners!$BW$6:$BW$92,MATCH(E$7,Partners!$A$6:$A$92,0)) -> 1.0470688 | F46: =INDEX(Partners!$BW$6:$BW$92,MATCH(F$7,Partners!$A$6:$A$92,0)) -> 1.1569725 | G46: =INDEX(Partners!$BW$6:$BW$92,MATCH(G$7,Partners!$A$6:$A$92,0)) -> 1.2670239 | H46: =INDEX(Partners!$BW$6:$BW$92,MATCH(H$7,Partners!$A$6:$A$92,0)) -> 1.3822301 | I46: =INDEX(Partners!$BW$6:$BW$92,MATCH(I$7,Partners!$A$6:$A$92,0)) -> 1.4663242 | J46: =INDEX(Partners!$BW$6:$BW$92,MATCH(J$7,Partners!$A$6:$A$92,0)) -> 1.5391554 | ... L46: =INDEX(Partners!$BW$6:$BW$92,MATCH(L$7,Partners!$A$6:$A$92,0)) -> 1.7624804
B47: Japan debt / GDP | C47: =INDEX(Japan!$AA$6:$AA$92,MATCH(C$7,Japan!$A$6:$A$92,0)) -> 0 | D47: =INDEX(Japan!$AA$6:$AA$92,MATCH(D$7,Japan!$A$6:$A$92,0)) -> 0 | E47: =INDEX(Japan!$AA$6:$AA$92,MATCH(E$7,Japan!$A$6:$A$92,0)) -> 0.16986669 | F47: =INDEX(Japan!$AA$6:$AA$92,MATCH(F$7,Japan!$A$6:$A$92,0)) -> 0.13953478 | G47: =INDEX(Japan!$AA$6:$AA$92,MATCH(G$7,Japan!$A$6:$A$92,0)) -> 0.42547104 | H47: =INDEX(Japan!$AA$6:$AA$92,MATCH(H$7,Japan!$A$6:$A$92,0)) -> 0.10449305 | I47: =INDEX(Japan!$AA$6:$AA$92,MATCH(I$7,Japan!$A$6:$A$92,0)) -> 0.023058951 | J47: =INDEX(Japan!$AA$6:$AA$92,MATCH(J$7,Japan!$A$6:$A$92,0)) -> 0.014956197 | ... L47: =INDEX(Japan!$AA$6:$AA$92,MATCH(L$7,Japan!$A$6:$A$92,0)) -> 0.031697841
B48: Checks
B49: Problems that year | C49: =INDEX(Checks!$S$6:$S$92,MATCH(C$7,Checks!$A$6:$A$92,0)) -> 0 | D49: =INDEX(Checks!$S$6:$S$92,MATCH(D$7,Checks!$A$6:$A$92,0)) -> 0 | E49: =INDEX(Checks!$S$6:$S$92,MATCH(E$7,Checks!$A$6:$A$92,0)) -> 0 | F49: =INDEX(Checks!$S$6:$S$92,MATCH(F$7,Checks!$A$6:$A$92,0)) -> 0 | G49: =INDEX(Checks!$S$6:$S$92,MATCH(G$7,Checks!$A$6:$A$92,0)) -> 0 | H49: =INDEX(Checks!$S$6:$S$92,MATCH(H$7,Checks!$A$6:$A$92,0)) -> 0 | I49: =INDEX(Checks!$S$6:$S$92,MATCH(I$7,Checks!$A$6:$A$92,0)) -> 0 | J49: =INDEX(Checks!$S$6:$S$92,MATCH(J$7,Checks!$A$6:$A$92,0)) -> 0 | ... L49: =INDEX(Checks!$S$6:$S$92,MATCH(L$7,Checks!$A$6:$A$92,0)) -> 0
B51: World in 1929 and 1932 ($bn)
C52: 1913 | D52: 1929 | E52: 1932
B53: Pacifica | C53: =World!E6 -> 17.784832 | D53: =World!F6 -> 69.472342 | E53: =World!G6 -> 54.846119
B54: Pacifica + Japan | C54: =World!E8 -> 22.702762 | D54: =World!F8 -> 90.458408 | E54: =World!G8 -> 72.501045
B55: The Pacific order | C55: =World!E12 -> 25.696547 | D55: =World!F12 -> 102.43452 | E55: =World!G12 -> 80.299369
B56: The Union | C56: =World!E13 -> 26.722591 | D56: =World!F13 -> 63.282135 | E56: =World!G13 -> 32.460139
B57: Britain | C57: =World!E15 -> 12.2 | D57: =World!F15 -> 22.9 | E57: =World!G15 -> 15.3
B58: Germany | C58: =World!E16 -> 12.4 | D58: =World!F16 -> 23.3 | E58: =World!G16 -> 15.2
B60: How to read the workbook
B61: Levers | C61: Every scalar assumption, story and stress values side by side, with canon status.
B62: Events | C62: The story ledger: each dated commitment with its cost, category, canon status and section.
B63: Paths | C63: Year-by-year inputs: prices, migration, growth, tax rates, army size, loan terms.
B64: People | C64: Residents: births, territory and four migration streams; Asian-origin residents.
B65: Economy | C65: GDP from residents, productivity, slumps, prices, mining and oil; benchmark against the US.
B66: Resources | C66: Gold, metals and oil, and the royalties the state takes.
B67: Budget | C67: Treasury receipts and spending.
B68: Debt & cash | C68: How each year is financed: cash, Reserve Fund, bonds.
B69: Loans | C69: Public loans to the Union, the Confederacy, Japan, China and the Entente.
B70: Gold & money | C70: Monetary gold against the 40% cover rule.
B71: Navy plan | C71: Ships completed each year and their unit costs: edit these to change the fleet.
B72: Navy | C72: Fleet in service, cost, sailors and fuel saved by oil, capital-ship parity.
... B81: Changes | C81: What differs from Sol's model and why.
B82: Colours: blue = input you can change · black = formula · green = link to another sheet · yellow = the main levers. Years shaded red are war years.
B84: Japan's 1927 rescue | C84: See Japan rescue: bank capital, monthly FX, actual public/private funding and repayment through 1933.

Sheet Changes
A1: What changed from Sol's model
A2: Sol's CR-018/CR-019 workbook (working case) against this model, with the reason for each difference.
A3: Sol's values are typed in from Pacifica_CR018_CR019_financial_model_1846-1932.xlsx; this model's values are live.
B5: Measure | C5: Year | D5: Sol's model | E5: This model | F5: Ratio | G5: Why it differs
B6: Core residents (m) | C6: 1895 | D6: 6.01 | E6: =INDEX(People!$L$6:$L$92,MATCH(C6,People!$A$6:$A$92,0))/1000000 -> 8.3296699 | F6: =IF(D6<>0,E6/D6,0) -> 1.3859684 | G6: Similar until 1895.
B7: Core residents (m) | C7: 1913 | D7: 9.44 | E7: =INDEX(People!$L$6:$L$92,MATCH(C7,People!$A$6:$A$92,0))/1000000 -> 19.227664 | F7: =IF(D7<>0,E7/D7,0) -> 2.0368288 | G7: No exclusion act, family programmes and skilled entry keep migration higher after 1888.
B8: Core residents (m) | C8: 1929 | D8: 12.92 | E8: =INDEX(People!$L$6:$L$92,MATCH(C8,People!$A$6:$A$92,0))/1000000 -> 33.396639 | F8: =IF(D8<>0,E8/D8,0) -> 2.5848792 | G8: Baseline arrivals, plus people drawn by Pacifica's lead: skilled migrants and families (B10), settled guest workers (B11), and Europeans who would have gone to the Union (B12).
B9: Core GDP ($bn) | C9: 1895 | D9: 2.24 | E9: =INDEX(Economy!$O$6:$O$92,MATCH(C9,Economy!$A$6:$A$92,0))/1000 -> 3.4856786 | F9: =IF(D9<>0,E9/D9,0) -> 1.5561065 | G9: Sol's per-resident output was higher early, lower late.
B10: Core GDP ($bn) | C10: 1913 | D10: 5.62 | E10: =INDEX(Economy!$O$6:$O$92,MATCH(C10,Economy!$A$6:$A$92,0))/1000 -> 17.784832 | F10: =IF(D10<>0,E10/D10,0) -> 3.1645608
B11: Core GDP ($bn) | C11: 1929 | D11: 12.15 | E11: =INDEX(Economy!$O$6:$O$92,MATCH(C11,Economy!$A$6:$A$92,0))/1000 -> 69.472342 | F11: =IF(D11<>0,E11/D11,0) -> 5.7178882 | G11: Sol's 1929 economy was the historical American West (about 1.1x US output per person). This one is about 2x: the trend path near historical California, the national champions (B9), the extra talent (B10) and the Development Fund. Total GDP is also larger because there are more people.
B12: Core GDP ($bn) | C12: 1932 | D12: 7.11 | E12: =INDEX(Economy!$O$6:$O$92,MATCH(C12,Economy!$A$6:$A$92,0))/1000 -> 54.846119 | F12: =IF(D12<>0,E12/D12,0) -> 7.7139408 | G12: Sol's slump was -41% in money terms, worse than the Union's. Here about -24%: Pacifica keeps its market open, lends its gold and its central bank acts (§34, CR-020).
B13: Treasury receipts ($m) | C13: 1929 | D13: 1255 | E13: =INDEX(Budget!$M$6:$M$92,MATCH(C13,Budget!$A$6:$A$92,0)) -> 7577.4189 | F13: =IF(D13<>0,E13/D13,0) -> 6.037784
B14: Navy ($m) | C14: 1913 | D14: 114.5 | E14: =INDEX(Navy!$Y$6:$Y$92,MATCH(C14,Navy!$A$6:$A$92,0)) -> 74.37585 | F14: =IF(D14<>0,E14/D14,0) -> 0.64957074 | G14: Sol's navy kept 24 seagoing hulls fixed from 1905 and added a flat allowance. Here the fleet is built ship by ship.
B15: Navy ($m) | C15: 1929 | D15: 195 | E15: =INDEX(Navy!$Y$6:$Y$92,MATCH(C15,Navy!$A$6:$A$92,0)) -> 183.35254 | F15: =IF(D15<>0,E15/D15,0) -> 0.94026942 | G15: Includes Pacifica's 65% of the common navy from 1927.
B16: Public debt ($m) | C16: 1932 | D16: 119.8 | E16: =INDEX('Debt & cash'!$R$6:$R$92,MATCH(C16,'Debt & cash'!$A$6:$A$92,0)) -> 2920.4904 | F16: =IF(D16<>0,E16/D16,0) -> 24.37805 | G16: Here a standing debt of about 5% of GDP is kept for the Reserve Bank (OPEN-020-06), and the rescue is paid from the Reserve Fund.
B17: Treasury cash ($m) | C17: 1929 | D17: 2326.7 | E17: =INDEX('Debt & cash'!$M$6:$M$92,MATCH(C17,'Debt & cash'!$A$6:$A$92,0)) -> 1894.3547 | F17: =IF(D17<>0,E17/D17,0) -> 0.81418091 | G17: Sol's surpluses piled up as $2.3bn of idle cash. Here surpluses repay debt or go to the Reserve Fund.
B18: Monetary gold ($m) | C18: 1932 | D18: 1355.5 | E18: =INDEX('Gold & money'!$F$6:$F$92,MATCH(C18,'Gold & money'!$A$6:$A$92,0)) -> 2363.0908 | F18: =IF(D18<>0,E18/D18,0) -> 1.7433352
B20: Structural changes
B21: Fleet | C21: Nine ship classes with the canon technology dates: oil-fired torpedo boats in the 1880s, oil cruisers in the early 1890s, turbine destroyers 1893-95, turbine cruisers 1898, all-big-gun turbine capital ships from 1903 (proposed). HMS Dreadnought changes nothing for Pacifica's budget: there is no 1906 jump.
B22: Oil | C22: Sol's model counted oil inside 'other minerals' with no royalty and no navy effect. Here the state takes a 1/8 royalty, the navy burns its own oil, and the sheets show sailors and fuel saved by oil firing.
B23: Technology | C23: The approved oil (1876) and turbine (1885) programmes and the proposed electrical institute (1886) are costed Events, on top of a standing technical budget.
B24: Japan | C24: Japan has a conserved Treasury cash account. The 1927 panic combines bank losses, domestic withdrawals and a tested foreign-settlement shortage.
B25: Events | C25: One ledger lists every dated commitment with its canon status and section, so a story change is one row to edit.
B26: Canal | C26: Owned by the state, as the regency's achievement (Sol's model: 20% public). Tolls from 1901.
B27: World | C27: A new sheet sets Pacifica, Japan and the order against the Union, Britain and Germany.
B28: Layout | C28: Years run down the page; inputs, events and results are separate; every heading has a definition.
B29: CR-020 | C29: Income from private investment abroad (national income), named export sectors, the Gulf admission switch, Pacifica's milder price fall in 1930-32, an oil compact with the Gulf, a standing public debt for the Reserve Bank, the Thalassia and islands programme as Events, a drag on the Union's output, and a Development Fund that invests most surpluses in productivity (B8). Each has a lever.
B30: Champions | C30: CR-020 B9: a Champions sheet built bottom-up from world markets and Pacifica's share of each: the oil trust (Gulf refining and the Asian trade), steel, the assembly-line car industry, chemicals and drugs, electrical equipment on the Pacifican standard, telecom, shipping, San Francisco underwriting, film and aircraft. It adds to GDP, to income from abroad (concessions, plants, royalties) and to the Treasury (the Crown share), and takes a slice off the Union.
B31: Labour | C31: CR-020 B10: migration answers Pacifica's lead. Skilled workers come from the Union, Europe and Asia up to a ceiling of entry places, with their families and later their relatives; workers come for new champion jobs and leave in a slump. The extra talent raises output per resident and the champions; the Union loses what its emigrants would have produced. Only the champions' productivity premium now adds to GDP, since their workers are residents.
B32: The Union | C32: CR-020 B12: the Union is modelled year by year. Its historical output is reduced by the people who are not there (diverted immigrants, talent emigrants and their children), a compounding brain-drain drag, a compounding loss of Pacific trade and gold that grows with Pacifica, the champions' markets, Union citizens away as guest workers, and the 1930-32 German loan crash. This replaces the old fixed drag.
... B38: Not carried over | C38: Sol's bank-by-bank balance sheets, Siberian rail and shipping tonnage tests and foreign settlement deposits. The Siberian campaign keeps Sol's $808m cost and the permanent front keeps his $80m a year.
A40: CR-025: wartime lending, Japanese expansion and capital funding | B40: CR-024: Japan's 1927 rescue | C40: Treasury cash retained, bank capital and yen liquidity separated, monthly FX tested after all liquid reserves, and syndicate matched to actual drawings.
A41: Standing debt now supplies cash at the common issue price. Entente public/private/foreign claims share one repayment convention. | B41: Loan terms | C41: Fixed facility ceiling, 1/3 public and 2/3 private, monthly first-year interest, equal principal 1929-1933; private money reroutes the existing overseas budget.
A42: Sources & uses, War credit, Japan expansion and Capital accounts distinguish cash, claims, valuation and unverified subscribers. | B42: FX and gold | C42: Japanese import buffer is distinct from Pacifica's gold-cover rule. Pacifica records bullion calls and remaining callable settlement balances separately.
A44: 20 Oct: gaps closed | B44: Private capital | C44: Home investment allowance falls to 13% of GDP in 1861-65 and 1870-71, and to 12.4% in 1862; the Baja purchase is paid in five instalments, 1867-71.
B45: Champions | C45: Champion funding sheet: retained cash, Carnegie paid in Pacifica Steel paper ($480m, 1901), local partners' equity (25%), champion bonds sold in Europe (1880-1913) and to the Union and Japan (1919-29). Oil assets abroad are priced at four years' earnings.
B46: Foreign claims | C46: Coupons, the Carnegie yield and partners' earnings are paid out of national income; redemptions are a use of home saving.
B47: Entente | C47: Entente subscribers sheet names the foreign subscribers by source and year, checked against the sources: $3.95bn abroad (none in 1914), $2.85bn from Pacifican savers, $1.7bn from the Treasury.
B48: Japan creditors | C48: The $800m outside Pacifican portfolios is named: London houses $400m, Union banks $250m, continental $100m, regional $50m. Japan's short foreign bank debt is re-timed (21 Oct): $600m in wartime, mostly Pacifican; $1bn in 1919-26 as London and the Union banks return. Japan's Entente subscriptions move to 1917-18.
B49: Numbering | C49: Japan's 1927 rescue is CR-024 and the wartime credit CR-025 (CR-022 and CR-023 are taken).
A51: 22 Oct: CR-029 | B51: Philippines | C51: CR-029: the Manila station (1873-76); the 1874 loan cancelled against a $20m price, so only $14.3m leaves in gold; the inherited Sulu war and the Moro stipends; Subic and Olongapo; the friar-estate, waterworks and peso-reserve credits to the Philippines; quarantine; New Calamba; the 1896 rising and the 1897 interception; Micronesia, Samoa, Midway and Wake; the 1914 plebiscites and Ka Lokahi; the Philippine budget support ends in 1914 and a defence contribution starts in 1915. On Partners the Philippine crown integrates faster (+0.04 from the 1886 peso, +0.03 from the 1915 customs union), and its population keeps the people the 1888-89 and 1902-04 cholera epidemics killed historically.
B52: Islands pay their way | C52: CR-029 A46-A49: the $20m purchase, the friar-estate bonds ($7m) and the waterworks bonds ($4m) are Philippine debt guaranteed by the Confederation (the Redemption Loan), serviced from Philippine customs under a fairness covenant: debt service never exceeds the measured gain, which binds only in 1877. The Realm takes over the $9.5m left in 1914 (E145). Seigniorage on the token peso (E146), the sale of the tobacco monopoly and the Crown's dividends from the tobacco company and the cordage champion (E147-E151). No Treasury gold is lent for the peso.
A53: 22 Oct: CR-028 | B53: Founding, 1846-60 | C53: CR-028: the royalty runs only from the October 1848 decree; the 1848 claims commission, the whalers' allowance under the Buchanan-Vallejo Convention and the Sausalito storehouse rent (E114-E117).
A54: 22 Oct: CR-030 | B54: Siberian transport | C54: A Siberia sheet carries the campaign quarter by quarter (1918-22) and the standing front year by year (1923-32): troops, daily tonnage, four railway sections, train paths, locomotives, wagons, Vladivostok, ships, depots and the Kara Sea route. Costs are built up from it and replace Sol's flat $808m and $80m a year (E76, E81, E152-E164; Japan column L). Checks gains column AI, 'Siberian line carries the army'. This restores the rail and shipping tests that were not carried over. Revision 2: five sections (the Manzhouli branch split from the double track), the Amur summer route via Sretensk, Pacifican-built engines and cars inherited in 1918, coal-strike and dry-year levers, stress works at 60%, provisions for railwaymen and miners.
A55: 23 Oct: CR-031 | B55: The Treaty of Harbin: the North | C55: CR-031 revision 4: relief ships to Chukotka and the Okhotsk coast (1919-20), the Northern Trade Commission's write-down, the Commander Islands' price and seal receipts, and the Pacifican stake in the Kamchatka Company (E165-E169). Kamchatka is a Japanese protectorate and costs Pacifica nothing to garrison; Kolyma gold ships through Nagaevo on the Siberian side, with the road built from 1928.
A56: 27 Oct: CR-033 | B56: Population and the Land Fund | C56: Population change list P1-P6 (population/workbook_change_list.md): Paths C from the population model; DEM-01 early arrivals (dem01_mult); extra arrivals split by origin into People N-P (xo_*), Q and R folded in; memo columns for Native Hawaiians and Native Californians; two checks. Land Fund sheet (CR-033 draft) feeding Budget G. Events table widened to row 400.
A57: 28 Oct: CR-034 | B57: Skilled entry from the 1850s | C57: Levers 'First year of the skilled-entry programme' 1856 (was 1880), CR-034 A24.
A58: 30 Oct: CR-041 | B58: The Russian war re-planned | C58: CR-041 Plan C and CR-040 Stages 3-4: the Siberia schedule rebuilt (50,000-man corps at the Urals, Russian armies on the line, a new railway section (section 5) to Chelyabinsk, a guarantee reserve from 1923 instead of a standing front); new Events for the Directory's credit, Cossack pay, the Kazan gold, the Black Sea, White Sea and Baltic operations, Yudenich and Estonia, the reconstruction credit and the oil concessions; federal Russia recognises part of the 1918 write-off. Paths C from 1918 includes the corps' war deaths.

Sheet Levers
A1: Story levers
A2: Every scalar assumption in one place. Pick the case in E4; the Active column feeds the model.
A3: Blue = input · yellow = the main levers · Status says whether the idea is canon; the amount is almost always a model estimate.
B4: Case in use (1 = Story case, 2 = Stress case) | E4: 1 | F4: =IF(E4=1,"Story case","Stress case") -> Story case
B6: Lever | C6: Story case | D6: Stress case | E6: Active | F6: Unit | G6: Status | H6: Basis and notes
B7: — Economy and people —
B8: Residents of California in 1846 | C8: 170000 | D8: 170000 | E8: =IF(case_sel=1,C8,D8) -> 170000 | F8: persons | G8: Model estimate | H8: Californios, Indigenous communities and foreigners; old model used the same figure.
B9: Real non-mining output per resident, 1846 | C9: 150 | D9: 150 | E9: =IF(case_sel=1,C9,D9) -> 150 | F9: 1913 $ | G9: Model estimate | H9: Pastoral Californio economy, a little above the US level of about $125 in 1913 dollars.
B10: Productivity growth after 1895 (× story path) | C10: 1 | D10: 0.75 | E10: =IF(case_sel=1,C10,D10) -> 1 | F10: × | G10: Model estimate | H10: Stress case cuts growth after 1895 by a quarter, like Sol's 25% lower-productivity case.
B11: Immigration after 1895 (× story path) | C11: 1 | D11: 0.8 | E11: =IF(case_sel=1,C11,D11) -> 1 | F11: × | G11: Model estimate | H11: Selective-entry era. Stress case admits a fifth fewer people.
B12: Depression severity 1930-32 (× story slump) | C12: 1 | D12: 1.6 | E12: =IF(case_sel=1,C12,D12) -> 1 | F12: × | G12: Model estimate | H12: Stress case: the 1932 slump is 22% below trend instead of 14%.
B13: Return migration, Asian streams | C13: 0.28 | D13: 0.28 | E13: =IF(case_sel=1,C13,D13) -> 0.28 | F13: share | G13: Model estimate | H13: Share of Chinese, Japanese and Filipino arrivals who later leave. Family migration keeps it lower than the historical 40-50%.
B14: Assisted passage and reception per person | C14: 60 | D14: 60 | E14: =IF(case_sel=1,C14,D14) -> 60 | F14: 1913 $ | G14: Model estimate | H14: Kaiulani's programme: fare, reception and training. Old model: $75 + $12 in 1860 dollars.
B15: Mining value added / gross output | C15: 0.7 | D15: 0.7 | E15: =IF(case_sel=1,C15,D15) -> 0.7 | F15: share | G15: Model estimate | H15: Old model used 0.8.
B16: — Revenue —
B17: Customs collection | C17: 0.9 | D17: 0.9 | E17: =IF(case_sel=1,C17,D17) -> 0.9 | F17: share | G17: Model estimate | H17: Old model value.
B18: Royalty on gold, silver and copper | C18: 0.05 | D18: 0.05 | E18: =IF(case_sel=1,C18,D18) -> 0.05 | F18: share | G18: Canon | H18: Mining Law of 1849: 5% public royalty at the mint and choke points (§5). Applied to all metals here.
B19: State royalty on oil | C19: 0.125 | D19: 0.125 | E19: =IF(case_sel=1,C19,D19) -> 0.125 | F19: share | G19: Model estimate | H19: The state survey found the fields (approved oil programme), so the state keeps a landowner's 1/8 royalty.
B20: State ownership of the Panama canal | C20: 1 | D20: 1 | E20: =IF(case_sel=1,C20,D20) -> 1 | F20: share | G20: Model estimate | H20: Canon: the regency buys the French works in 1889 and completes the canal. Old model assumed 20% public.
B21: Canal operating cost / tolls | C21: 0.4 | D21: 0.4 | E21: =IF(case_sel=1,C21,D21) -> 0.4 | F21: share | G21: Model estimate | H21: Historical Panama: about $10m costs on $25-27m tolls in the late 1920s.
B22: Yield on the Treasury Reserve Fund | C22: 0.04 | D22: 0.04 | E22: =IF(case_sel=1,C22,D22) -> 0.04 | F22: share | G22: Model estimate | H22: Fund holds gold-dollar bonds of partners and the Union.
B23: — Spending —
B24: Cost per active soldier | C24: 700 | D24: 700 | E24: =IF(case_sel=1,C24,D24) -> 700 | F24: 1913 $ | G24: Model estimate | H24: Pay, food, equipment. US Army 1913 ran about $1,100 per soldier; conscript army is cheaper.
B25: Training cost per reservist | C25: 15 | D25: 15 | E25: =IF(case_sel=1,C25,D25) -> 15 | F25: 1913 $ | G25: Model estimate | H25: Defense Law of 1855 reserve liability (§8).
B26: Cost per sailor | C26: 900 | D26: 900 | E26: =IF(case_sel=1,C26,D26) -> 900 | F26: 1913 $ | G26: Model estimate | H26: Pay and keep, at Pacifican wage levels.
B27: Ship maintenance / replacement cost | C27: 0.05 | D27: 0.05 | E27: =IF(case_sel=1,C27,D27) -> 0.05 | F27: share | G27: Model estimate
B28: Bases, yards, training / running costs | C28: 0.15 | D28: 0.15 | E28: =IF(case_sel=1,C28,D28) -> 0.15 | F28: share | G28: Model estimate
B29: Crew of an oil-fired ship vs coal-fired | C29: 0.78 | D29: 0.78 | E29: =IF(case_sel=1,C29,D29) -> 0.78 | F29: × | G29: Model estimate | H29: Oil removes most stokers and coal trimmers, about a fifth of a coal ship's crew.
B30: Fuel cost of own oil vs bought coal | C30: 0.7 | D30: 0.7 | E30: =IF(case_sel=1,C30,D30) -> 0.7 | F30: × | G30: Model estimate | H30: Domestic oil, no colliers or foreign coaling stations.
B31: Pacifica's share of common costs from 1927 | C31: 0.65 | D31: 0.65 | E31: =IF(case_sel=1,C31,D31) -> 0.65 | F31: share | G31: Proposed | H31: Old model working convention (OPEN FIN-13). Japan pays the rest.
B32: — Financing —
B33: Treasury cash at the 1846 founding | C33: 0.05 | D33: 0.05 | E33: =IF(case_sel=1,C33,D33) -> 0.05 | F33: $m | G33: Model estimate | H33: Old model value.
B34: Cash kept / annual receipts | C34: 0.25 | D34: 0.25 | E34: =IF(case_sel=1,C34,D34) -> 0.25 | F34: share | G34: Model estimate | H34: Old model value.
B35: Bond issue price / face | C35: 0.97 | D35: 0.97 | E35: =IF(case_sel=1,C35,D35) -> 0.97 | F35: share | G35: Model estimate
B36: Scheduled debt repayment per year | C36: 0.02 | D36: 0.02 | E36: =IF(case_sel=1,C36,D36) -> 0.02 | F36: share | G36: Model estimate
B37: Share of surplus used to repay debt | C37: 0.8 | D37: 0.8 | E37: =IF(case_sel=1,C37,D37) -> 0.8 | F37: share | G37: Model estimate | H37: The rest of a surplus goes to the Treasury Reserve Fund.
B38: Most new bonds the home market can take / GDP | C38: 0.06 | D38: 0.06 | E38: =IF(case_sel=1,C38,D38) -> 0.06 | F38: share | G38: Model estimate | H38: Old model's market cash commitment limit. Used only in Checks.
B39: Bonds London and other markets will take per year | C39: 10 | D39: 10 | E39: =IF(case_sel=1,C39,D39) -> 10 | F39: $m | G39: Model estimate | H39: Early Pacifica depends on foreign credit (§8-9). Used only in Checks.
B40: — Foreign lending —
B41: Coupon: continental loans (Union, Confederacy, Cuba) | C41: 0.05 | D41: 0.05 | E41: =IF(case_sel=1,C41,D41) -> 0.05 | F41: share | G41: Model estimate
B42: Repayment: continental loans | C42: 0.04 | D42: 0.04 | E42: =IF(case_sel=1,C42,D42) -> 0.04 | F42: share | G42: Model estimate
B43: Coupon: Asian partner loans | C43: 0.055 | D43: 0.055 | E43: =IF(case_sel=1,C43,D43) -> 0.055 | F43: share | G43: Model estimate
B44: Repayment: Asian partner loans | C44: 0.04 | D44: 0.04 | E44: =IF(case_sel=1,C44,D44) -> 0.04 | F44: share | G44: Model estimate
B45: Coupon: 1931-32 rescue loans | C45: 0.04 | D45: 0.04 | E45: =IF(case_sel=1,C45,D45) -> 0.04 | F45: share | G45: Model estimate | H45: Repayment starts after 1932.
B46: Entente credit organized 1914-18 | C46: 8500 | D46: 8500 | E46: =IF(case_sel=1,C46,D46) -> 8500 | F46: $m | G46: Proposed | H46: Sol's proposal tested $3bn and $8.5bn. Union investors buy most of it through San Francisco.
B47: Treasury's own share of Entente credit | C47: 0.2 | D47: 0.3 | E47: =IF(case_sel=1,C47,D47) -> 0.2 | F47: share | G47: Model estimate | H47: Sol's proposal used 10%. A bigger economy can carry 20%; stress case assumes fewer outside buyers.
B48: Entente credit written off when Russia defaults (1918) | C48: 0.12 | D48: 0.15 | E48: =IF(case_sel=1,C48,D48) -> 0.12 | F48: share | G48: Model estimate
B49: Western cession vendor credit to the Union | C49: 40 | D49: 40 | E49: =IF(case_sel=1,C49,D49) -> 40 | F49: $m | G49: Proposed | H49: §12: $40m gold in instalments through 1872.
B50: — Wars and crises —
B51: Siberian campaign, Pacifican spending 1918-22 (old estimate, now built up on the Siberia sheet) | C51: 808 | D51: 1212 | E51: =IF(case_sel=1,C51,D51) -> 808 | F51: $m | G51: Model estimate | H51: Old model $807.9m; stress case +50% (Sol's adverse procurement case).
B52: Permanent Siberian front, all partners, per year (old estimate, now built up on the Siberia sheet) | C52: 80 | D52: 112 | E52: =IF(case_sel=1,C52,D52) -> 80 | F52: $m | G52: Model estimate | H52: Old model working / adverse values.
B53: Second gold rescue of the Union, 1931-32 | C53: 400 | D53: 700 | E53: =IF(case_sel=1,C53,D53) -> 400 | F53: $m | G53: Proposed | H53: Old model $400m; §34 says the scale needs audit.
B54: Recapitalisation of Pacifican banks 1931-32 | C54: 150 | D54: 300 | E54: =IF(case_sel=1,C54,D54) -> 150 | F54: $m | G54: Model estimate
B55: Reserve Bank purchases of Treasury bonds 1931-32 | C55: 0 | D55: 400 | E55: =IF(case_sel=1,C55,D55) -> 0 | F55: $m | G55: Proposed | H55: Sol's proposal needed $400m. The story case does not need it; the stress case does.
B56: — Money and gold —
B57: New gold kept as monetary metal | C57: 0.2 | D57: 0.2 | E57: =IF(case_sel=1,C57,D57) -> 0.2 | F57: share | G57: Model estimate | H57: Old model 0.6. Most private bullion is exported (§8), so 20% here.
B58: Concession gold (Korea, Kolyma) sold to the Reserve Bank | C58: 0.6 | D58: 0.4 | E58: =IF(case_sel=1,C58,D58) -> 0.6 | F58: share | G58: Proposed | H58: CR-021 H: Pacifican concession companies sell most of their gold in San Francisco against credit.
B59: Gold inflow from the external surplus / GDP | C59: 0.002 | D59: 0.0012 | E59: =IF(case_sel=1,C59,D59) -> 0.002 | F59: share | G59: Model estimate | H59: Creditor and exporter of oil, wheat, copper and shipping services.
B60: Notes and bank reserves / GDP | C60: 0.07 | D60: 0.07 | E60: =IF(case_sel=1,C60,D60) -> 0.07 | F60: share | G60: Model estimate | H60: US monetary base was about 6% of GDP in 1929.
B61: Gold cover required | C61: 0.4 | D61: 0.4 | E61: =IF(case_sel=1,C61,D61) -> 0.4 | F61: share | G61: Proposed | H61: Sol's proposal and old model: 40%.
B62: — Gulf Republic —
B63: Gulf Republic joins Pacifica (1 = yes, 0 = no) | C63: 0 | D63: 0 | E63: =IF(case_sel=1,C63,D63) -> 0 | F63: switch | G63: Proposed | H63: §25 admission test. Off keeps the Gulf an allied republic, as the master storyline has it.
B64: Years every measure must be held before admission | C64: 25 | D64: 25 | E64: =IF(case_sel=1,C64,D64) -> 25 | F64: years | G64: Approved | H64: OPEN-020-04: a generation; Pacifica reserves the right to ask for a second. It is in no hurry.
B65: Year the Gulf joins (test only) | C65: 1960 | D65: 1960 | E65: =IF(case_sel=1,C65,D65) -> 1960 | F65: year | G65: Approved | H65: 1929 is the earliest the six indicators allow (three passing years 1926-28; see the Gulf sheet). A year after 1932 delays admission past the Depression and beyond this model.
B66: — CR-020: Depression, oil compact, standing debt, investment abroad —
B67: Share of the US price fall Pacifica suffers, 1930-32 | C67: 0.6 | D67: 1 | E67: =IF(case_sel=1,C67,D67) -> 0.6 | F67: × | G67: Proposed | H67: CR-020 B6: Pacifica lends its gold out instead of hoarding it, so its prices fall less than America's. 1 = the full US fall.
B68: Oil compact with the Gulf (1 = yes; from the year below) | C68: 1 | D68: 0 | E68: =IF(case_sel=1,C68,D68) -> 1 | F68: switch | G68: Proposed | H68: CR-020 B6: limits output after the East Texas glut and holds the price. Keeps the Gulf's wage indicator from failing in 1931-33.
B69: Oil price the compact holds ($ per barrel) | C69: 0.95 | D69: 0.95 | E69: =IF(case_sel=1,C69,D69) -> 0.95 | F69: $ | G69: Proposed | H69: Historical California crude fell to about $0.70; East Texas to about $0.10.
B70: Output cut under the compact | C70: 0.15 | D70: 0.15 | E70: =IF(case_sel=1,C70,D70) -> 0.15 | F70: share | G70: Proposed
B71: First year of the oil compact | C71: 1932 | D71: 1932 | E71: =IF(case_sel=1,C71,D71) -> 1932 | F71: year | G71: Proposed | H71: OPEN-020-04 decided: the compact comes a year late, after a year of 10-cent East Texas oil, so 1931 narrowly breaks the Gulf's streak.
B72: Fall in the Gulf's real wage, 1931-33, without a compact | C72: 0.09 | D72: 0.12 | E72: =IF(case_sel=1,C72,D72) -> 0.09 | F72: share | G72: Model estimate | H72: Enough to break the Gulf's admission streak (CR-020 B5).
B73: Fall in Gulf output, 1931-32, without a compact | C73: 0.05 | D73: 0.05 | E73: =IF(case_sel=1,C73,D73) -> 0.05 | F73: share | G73: Model estimate
B74: Standing public debt kept from 1887 / GDP | C74: 0.05 | D74: 0.05 | E74: =IF(case_sel=1,C74,D74) -> 0.05 | F74: share | G74: Proposed | H74: OPEN-020-06: bonds kept in issue for the Reserve Bank's operations; the proceeds go to the Reserve Fund. Set 0 to repay everything.
B75: Pacifican private investors' share of the Entente credit | C75: 0.3 | D75: 0.2 | E75: =IF(case_sel=1,C75,D75) -> 0.3 | F75: share | G75: Proposed | H75: CR-020 B4.
B76: Return on private investment abroad | C76: 0.06 | D76: 0.05 | E76: =IF(case_sel=1,C76,D76) -> 0.06 | F76: share | G76: Model estimate | H76: Britain earned 8-9% of national income from abroad in 1913.
B77: Investment abroad repaid or sold each year | C77: 0.03 | D77: 0.03 | E77: =IF(case_sel=1,C77,D77) -> 0.03 | F77: share | G77: Model estimate
B78: Losses on investment abroad, 1931-32 | C78: 0.08 | D78: 0.15 | E78: =IF(case_sel=1,C78,D78) -> 0.08 | F78: share | G78: Model estimate | H78: Defaults and write-downs in the crash.
B79: Income from abroad in 1931-32 (× normal) | C79: 0.7 | D79: 0.6 | E79: =IF(case_sel=1,C79,D79) -> 0.7 | F79: × | G79: Model estimate | H79: Moratorium and defaults.
B80: Tax on income from abroad | C80: 0.1 | D80: 0.1 | E80: =IF(case_sel=1,C80,D80) -> 0.1 | F80: share | G80: Model estimate
B81: — CR-020: Development Fund —
B82: Share of each surplus invested by the Development Fund | C82: 0.7 | D82: 0.7 | E82: =IF(case_sel=1,C82,D82) -> 0.7 | F82: share | G82: Proposed | H82: CR-020 B8: instead of piling up in the Reserve Fund, most of a surplus goes into productive public investment: the Polytechnic and research institutes, the power grid, ports and rail, technical schools, credit for new industries.
B83: Lasting rise in output per $1 invested (social return) | C83: 0.3 | D83: 0.15 | E83: =IF(case_sel=1,C83,D83) -> 0.3 | F83: share | G83: Model estimate | H83: Each $1 invested raises the next year's output growth by this much per $1 of GDP. Estimates for infrastructure, research and technical education mostly fall between 10% and 40%.
B84: First year of the Development Fund | C84: 1880 | D84: 1880 | E84: =IF(case_sel=1,C84,D84) -> 1880 | F84: year | G84: Proposed | H84: Before the regency: Elias's oil and turbine programmes.
B85: Standing-debt bonds finance development (1 = yes, 0 = Reserve Fund) | C85: 1 | D85: 1 | E85: =IF(case_sel=1,C85,D85) -> 1 | F85: switch | G85: Proposed | H85: Development bonds, as in a state-capitalist economy: the bonds kept in issue for the Reserve Bank pay for investment instead of sitting in the Reserve Fund.
B86: Reserve Fund kept as a crisis buffer / GDP | C86: 0.03 | D86: 0.03 | E86: =IF(case_sel=1,C86,D86) -> 0.03 | F86: share | G86: Proposed | H86: Anything above this is invested by the Development Fund each year.
B87: Largest yearly growth boost from the fund | C87: 0.012 | D87: 0.012 | E87: =IF(case_sel=1,C87,D87) -> 0.012 | F87: share | G87: Model estimate | H87: A ceiling for diminishing returns; even the fastest frontier economies rarely beat rivals by more than about 1 point a year for decades.
B88: Yearly wear-out of the development stock | C88: 0.03 | D88: 0.03 | E88: =IF(case_sel=1,C88,D88) -> 0.03 | F88: share | G88: Model estimate | H88: Only for the memo stock column.
B89: — CR-020 B9: national champions —
B90: Scale of the champions (× story paths) | C90: 1 | D90: 0.6 | E90: =IF(case_sel=1,C90,D90) -> 1 | F90: × | G90: Proposed | H90: CR-020 B9: oil, steel, motor vehicles, chemicals, electrical, telecom, shipping, finance, film and aircraft. The stress case keeps 60% of what the story claims.
B91: Champions' output per worker vs the average job | C91: 1.8 | D91: 1.6 | E91: =IF(case_sel=1,C91,D91) -> 1.8 | F91: × | G91: Model estimate | H91: Only this premium adds to GDP: the champions' workers are residents whose average output is already counted (CR-020 B10).
B92: Supplier and city spillovers (× champions' value added) | C92: 0.25 | D92: 0.1 | E92: =IF(case_sel=1,C92,D92) -> 0.25 | F92: × | G92: Model estimate | H92: Parts makers, machine shops, engineering offices, the service economy of the new industrial cities.
B93: Value added / sales: chemicals and drugs | C93: 0.45 | D93: 0.45 | E93: =IF(case_sel=1,C93,D93) -> 0.45 | F93: share | G93: Model estimate
B94: Value added / sales: electrical equipment | C94: 0.45 | D94: 0.45 | E94: =IF(case_sel=1,C94,D94) -> 0.45 | F94: share | G94: Model estimate
B95: Royalty or licence fee on sales | C95: 0.03 | D95: 0.02 | E95: =IF(case_sel=1,C95,D95) -> 0.03 | F95: share | G95: Model estimate | H95: Typical patent licences ran 2-5% of sales.
B96: Underwriting and banking fees on bonds floated | C96: 0.025 | D96: 0.02 | E96: =IF(case_sel=1,C96,D96) -> 0.025 | F96: share | G96: Model estimate
B97: Book value of oil assets abroad (years of earnings) | C97: 7 | D97: 7 | E97: =IF(case_sel=1,C97,D97) -> 7 | F97: years | G97: Model estimate
B98: Yield: rail, ports and canals abroad | C98: 0.05 | D98: 0.04 | E98: =IF(case_sel=1,C98,D98) -> 0.05 | F98: share | G98: Model estimate | H98: British overseas railways paid 4-6%.
B99: Yield: cables and telegraphs abroad | C99: 0.1 | D99: 0.08 | E99: =IF(case_sel=1,C99,D99) -> 0.1 | F99: share | G99: Model estimate | H99: Cable companies paid 8-12% on monopoly routes.
B100: Yield: power companies abroad | C100: 0.07 | D100: 0.06 | E100: =IF(case_sel=1,C100,D100) -> 0.07 | F100: share | G100: Model estimate
B101: Yield: assembly plants abroad | C101: 0.12 | D101: 0.08 | E101: =IF(case_sel=1,C101,D101) -> 0.12 | F101: share | G101: Model estimate
...

Sheet Events
A1: Story events ledger
A2: Every dated commitment from the master storyline that costs or brings in money. One row per event; the annual amount applies in each year from Start to End.
A3: Category decides where the money lands: Purchase, War & operations, Programme, Investment, Subsidy & guarantee, Relief, Bank rescue & capital and Receipt go to the Budget; Loan goes to Loans; Debt assumed adds debt without cash. Investment is spent like a Programme but also counts as development investment, so it raises later output (CR-021 B6). Amounts are Treasury cash in $m; shared or syndicated totals are in the notes.
A4: Rows 6-400 are read by the model (widened from 174 on 27 Oct 2026). Add new events in the first empty row.
A5: ID | B5: Start | C5: End | D5: Event | E5: Category | F5: Loan group | G5: Party | H5: Per year ($m) | I5: Total ($m) | J5: Paid in gold | K5: Story status | L5: Section | M5: Basis of the amount
A6: E01 | B6: 1848 | C6: 1848 | D6: London bondholders' Mexican debt assumed (£3m) | E6: Debt assumed | G6: Britain | H6: 14.6 | I6: =IF(H6="","",H6*(C6-B6+1)) -> 14.6 | J6: No | K6: Canon | L6: §4 | M6: £3m at $4.87
A7: E02 | B7: 1850 | C7: 1851 | D7: San Francisco mint and assay office | E7: Programme | H7: 0.5 | I7: =IF(H7="","",H7*(C7-B7+1)) -> 1 | J7: No | K7: Canon | L7: §5 | M7: Model estimate
A8: E03 | B8: 1853 | C8: 1854 | D8: Walker filibusters: naval supply cut-off | E8: War & operations | H8: 0.3 | I8: =IF(H8="","",H8*(C8-B8+1)) -> 0.6 | J8: No | K8: Canon | L8: §6 | M8: Model estimate
A9: E04 | B9: 1855 | C9: 1861 | D9: Ericsson experimental workshop and turret trials | E9: Programme | H9: 0.4 | I9: =IF(H9="","",H9*(C9-B9+1)) -> 2.8 | J9: No | K9: Canon | L9: §8 | M9: Hulls are in the navy plan
A10: E05 | B10: 1857 | C10: 1858 | D10: Utah War border readiness | E10: War & operations | H10: 0.3 | I10: =IF(H10="","",H10*(C10-B10+1)) -> 0.6 | J10: No | K10: Canon | L10: §8 | M10: Model estimate
A11: E06 | B11: 1860 | C11: 1860 | D11: Pyramid Lake relief force and Washoe crisis | E11: War & operations | H11: 1 | I11: =IF(H11="","",H11*(C11-B11+1)) -> 1 | J11: No | K11: Canon | L11: §8 | M11: Model estimate
A12: E07 | B12: 1861 | C12: 1861 | D12: Northwestern campaign: sea transport and occupation | E12: War & operations | H12: 6 | I12: =IF(H12="","",H12*(C12-B12+1)) -> 6 | J12: No | K12: Canon | L12: §10 | M12: On top of the wartime army in Paths
A13: E08 | B13: 1862 | C13: 1864 | D13: Occupation, interior columns and garrisons | E13: War & operations | H13: 5 | I13: =IF(H13="","",H13*(C13-B13+1)) -> 15 | J13: No | K13: Canon | L13: §10-11 | M13: Model estimate
A14: E09 | B14: 1862 | C14: 1864 | D14: Eastern technical mission and Confederate aid | E14: Subsidy & guarantee | G14: Confederacy | H14: 0.8 | I14: =IF(H14="","",H14*(C14-B14+1)) -> 2.4 | J14: No | K14: Canon | L14: §11 | M14: Logan's mission, Louisiana repairs, Mobile mines
A15: E10 | B15: 1865 | C15: 1865 | D15: Navajo and Apache treaties, peonage compensation | E15: Subsidy & guarantee | H15: 2 | I15: =IF(H15="","",H15*(C15-B15+1)) -> 2 | J15: No | K15: Proposed | L15: §10 | M15: Model estimate
A16: E11 | B16: 1866 | C16: 1872 | D16: Western cession: vendor credit to the Union | E16: Purchase | G16: Union | H16: =union_vendor/7 -> 5.7142857 | I16: =IF(H16="","",H16*(C16-B16+1)) -> 40 | J16: Yes | K16: Proposed | L16: §12 | M16: $40m gold in instalments through 1872
A17: E12 | B17: 1867 | C17: 1867 | D17: Alaska purchase | E17: Purchase | G17: Russia | H17: 7.2 | I17: =IF(H17="","",H17*(C17-B17+1)) -> 7.2 | J17: Yes | K17: Canon | L17: §14 | M17: Historical US price as comparator
A18: E13 | B18: 1867 | C18: 1871 | D18: Baja purchase | E18: Purchase | G18: Mexico | H18: 1 | I18: =IF(H18="","",H18*(C18-B18+1)) -> 5 | J18: Yes | K18: Proposed | L18: §13 | M18: Old model working price ($5m), paid in five annual instalments of $1m, 1867-71 (author's decision, 20 Oct)
A19: E14 | B19: 1867 | C19: 1867 | D19: Treasury loan to the Union | E19: Loan | F19: Continental | G19: Union | H19: 10 | I19: =IF(H19="","",H19*(C19-B19+1)) -> 10 | J19: Yes | K19: Proposed | L19: §12 | M19: Old model L01: $10m syndicate
A20: E15 | B20: 1867 | C20: 1900 | D20: Ocean mail line subsidy (SF-Honolulu-Yokohama-Hong Kong) | E20: Subsidy & guarantee | H20: 1 | I20: =IF(H20="","",H20*(C20-B20+1)) -> 34 | J20: No | K20: Proposed | L20: §14 | M20: Model estimate
A21: E16 | B21: 1868 | C21: 1869 | D21: Fleet guarantee for the Edo transition | E21: War & operations | G21: Japan | H21: 0.5 | I21: =IF(H21="","",H21*(C21-B21+1)) -> 1 | J21: No | K21: Proposed | L21: §14 | M21: Model estimate
A22: E17 | B22: 1870 | C22: 1871 | D22: Gulf squadron, turret ships and mines in Grant's war | E22: War & operations | G22: Confederacy | H22: 6 | I22: =IF(H22="","",H22*(C22-B22+1)) -> 12 | J22: No | K22: Canon | L22: §13 | M22: No field army sent
A23: E18 | B23: 1870 | C23: 1870 | D23: Japan alliance credit (Yokosuka, Takashima) | E23: Loan | F23: Asia | G23: Japan | H23: 5 | I23: =IF(H23="","",H23*(C23-B23+1)) -> 5 | J23: No | K23: Canon | L23: §14 | M23: Old model L02
A24: E19 | B24: 1871 | C24: 1872 | D24: Confederate debt refinanced on customs security | E24: Loan | F24: Continental | G24: Confederacy | H24: 12.5 | I24: =IF(H24="","",H24*(C24-B24+1)) -> 25 | J24: No | K24: Canon | L24: §13 | M24: Old model L03 + L04
A25: E20 | B25: 1871 | C25: 1888 | D25: Replacement of Richmond's Mississippi tolls | E25: Subsidy & guarantee | G25: Confederacy | H25: 1 | I25: =IF(H25="","",H25*(C25-B25+1)) -> 18 | J25: No | K25: Canon | L25: §13 | M25: Model estimate
A26: E21 | B26: 1872 | C26: 1872 | D26: Chinese industrial loans (arsenals, steamships, Kaiping) | E26: Loan | F26: Asia | G26: China | H26: 4 | I26: =IF(H26="","",H26*(C26-B26+1)) -> 4 | J26: No | K26: Proposed | L26: §14 | M26: Public share of a $20m syndicate
A27: E22 | B27: 1873 | C27: 1873 | D27: One-day naval action at Manila Bay | E27: War & operations | G27: Spain | H27: 1.5 | I27: =IF(H27="","",H27*(C27-B27+1)) -> 1.5 | J27: No | K27: Canon | L27: §15 | M27: Model estimate
A28: E23 | B28: 1874 | C28: 1874 | D28: Hawaiian crisis and the Honolulu suppression | E28: War & operations | G28: Hawaii | H28: 1 | I28: =IF(H28="","",H28*(C28-B28+1)) -> 1 | J28: No | K28: Canon | L28: §17 | M28: Model estimate
A29: E24 | B29: 1874 | C29: 1874 | D29: Supplies for Japan's Formosa expedition | E29: War & operations | G29: Japan | H29: 0.5 | I29: =IF(H29="","",H29*(C29-B29+1)) -> 0.5 | J29: No | K29: Proposed | L29: §15 | M29: Model estimate
A30: E25 | B30: 1874 | C30: 1875 | D30: Loan of 1874 to Serrano's Republic, secured on Philippine customs and tobacco | E30: Loan | F30: Europe | G30: Spain | H30: 3 | I30: =IF(H30="","",H30*(C30-B30+1)) -> 6 | J30: No | K30: Approved | L30: §15; CR-029 A7 | M30: Old model L09: $6m; cancelled against the 1876 price (E119)
A31: E26 | B31: 1876 | C31: 1876 | D31: Purchase of the Philippines, Marianas, Carolines and Palau: $20m, paid from the Philippine Redemption Loan | E31: Purchase | G31: Spain | H31: 0 | I31: =IF(H31="","",H31*(C31-B31+1)) -> 0 | J31: Yes | K31: Canon | L31: §15; CR-029 A8 | M31: Off-budget: a Philippine 4% loan of 1876, guaranteed by the Confederation and serviced from Philippine customs; $5.73m of it repays the 1874 loan (E119). The US paid $20m in 1898
A32: E27 | B32: 1876 | C32: 1890 | D32: State oil programme: survey, burner trials, oil locomotives | E32: Programme | H32: 0.3 | I32: =IF(H32="","",H32*(C32-B32+1)) -> 4.5 | J32: No | K32: Approved | L32: §21 | M32: Pico Canyon find; LA and Kern fields found 1885-88
A33: E28 | B33: 1876 | C33: 1879 | D33: North China famine relief | E33: Relief | G33: China | H33: 0.5 | I33: =IF(H33="","",H33*(C33-B33+1)) -> 2 | J33: No | K33: Proposed | L33: §14 | M33: Model estimate
A34: E29 | B34: 1877 | C34: 1914 | D34: Support to the Philippine budget (until the crown of 1914) | E34: Subsidy & guarantee | G34: Philippines | H34: 0.5 | I34: =IF(H34="","",H34*(C34-B34+1)) -> 19 | J34: No | K34: Proposed | L34: §15; CR-029 A10-A11 | M34: Old model transfer; from 1915 the Philippine crown pays a defence contribution (E143-E144)
A35: E30 | B35: 1877 | C35: 1877 | D35: Support for the Meiji government against Satsuma | E35: War & operations | G35: Japan | H35: 0.5 | I35: =IF(H35="","",H35*(C35-B35+1)) -> 0.5 | J35: No | K35: Proposed | L35: §15 | M35: Model estimate
A36: E31 | B36: 1878 | C36: 1878 | D36: Vladivostok maritime action | E36: War & operations | G36: Russia | H36: 6 | I36: =IF(H36="","",H36*(C36-B36+1)) -> 6 | J36: No | K36: Canon | L36: §16 | M36: Model estimate
A37: E32 | B37: 1880 | C37: 1880 | D37: Panama Railroad control and Colombian transit treaty | E37: Purchase | G37: Colombia | H37: 10 | I37: =IF(H37="","",H37*(C37-B37+1)) -> 10 | J37: Yes | K37: Canon | L37: §19 | M37: Old model $10m
A38: E33 | B38: 1880 | C38: 1887 | D38: Korean treaty and neutrality advisers | E38: Programme | G38: Korea | H38: 0.2 | I38: =IF(H38="","",H38*(C38-B38+1)) -> 1.6 | J38: No | K38: Proposed | L38: §14 | M38: Model estimate
A39: E34 | B39: 1884 | C39: 1885 | D39: Keelung squadron protecting the coal trade | E39: War & operations | G39: China | H39: 1 | I39: =IF(H39="","",H39*(C39-B39+1)) -> 2 | J39: No | K39: Proposed | L39: §16 | M39: Model estimate
A40: E35 | B40: 1885 | C40: 1885 | D40: Keelung coal and local rail (public stake) | E40: Loan | F40: Asia | G40: China | H40: 0.6 | I40: =IF(H40="","",H40*(C40-B40+1)) -> 0.6 | J40: No | K40: Proposed | L40: §16 | M40: Old model Q03
A41: E36 | B41: 1885 | C41: 1900 | D41: Steam-turbine programme | E41: Programme | H41: 0.6 | I41: =IF(H41="","",H41*(C41-B41+1)) -> 9.6 | J41: No | K41: Approved | L41: §21 | M41: Turbo-generators 1885, marine prototype 1890
A42: E37 | B42: 1886 | C42: 1900 | D42: Electrical institute, Tesla, one AC standard | E42: Programme | H42: 0.5 | I42: =IF(H42="","",H42*(C42-B42+1)) -> 7.5 | J42: No | K42: Proposed | L42: §21 | M42: Model estimate
A43: E38 | B43: 1885 | C43: 1887 | D43: Port Hamilton near-war readiness | E43: War & operations | G43: Britain | H43: 1 | I43: =IF(H43="","",H43*(C43-B43+1)) -> 3 | J43: No | K43: Proposed | L43: §16 | M43: Model estimate
A44: E39 | B44: 1887 | C44: 1889 | D44: Managed succession, Truce of Thalassia, Donner standoff | E44: War & operations | H44: 0.5 | I44: =IF(H44="","",H44*(C44-B44+1)) -> 1.5 | J44: No | K44: Canon | L44: §22 | M44: Old model $1.5m
A45: E40 | B45: 1888 | C45: 1932 | D45: Statistics bureau, multilingual weekly and newsreels | E45: Programme | H45: 0.4 | I45: =IF(H45="","",H45*(C45-B45+1)) -> 18 | J45: No | K45: Canon | L45: §25 | M45: Kaiulani's life project; model estimate
A46: E41 | B46: 1888 | C46: 1889 | D46: Abolition compensation bonds (public participation) | E46: Loan | F46: Continental | G46: Confederacy | H46: 3 | I46: =IF(H46="","",H46*(C46-B46+1)) -> 6 | J46: No | K46: Canon | L46: §25 | M46: Old model L06
A47: E42 | B47: 1889 | C47: 1889 | D47: Purchase of the French Panama works | E47: Purchase | G47: France | H47: =30*canal_share -> 30 | I47: =IF(H47="","",H47*(C47-B47+1)) -> 30 | J47: Yes | K47: Canon | L47: §19, §25 | M47: US paid $40m in 1904
A48: E43 | B48: 1890 | C48: 1901 | D48: Canal construction, lock-and-lake design | E48: Purchase | H48: =225/12*canal_share -> 18.75 | I48: =IF(H48="","",H48*(C48-B48+1)) -> 225 | J48: No | K48: Canon | L48: §25 | M48: Old model $225m
A49: E44 | B49: 1890 | C49: 1891 | D49: Baring-crisis gold loans | E49: Loan | F49: Europe | G49: Britain | H49: 1.5 | I49: =IF(H49="","",H49*(C49-B49+1)) -> 3 | J49: Yes | K49: Proposed | L49: §25 | M49: Public share of $15m
A50: E45 | B50: 1890 | C50: 1902 | D50: Galapagos coaling station lease | E50: Subsidy & guarantee | G50: Ecuador | H50: 0.2 | I50: =IF(H50="","",H50*(C50-B50+1)) -> 2.6 | J50: No | K50: Proposed | L50: §25 | M50: Model estimate
A51: E46 | B51: 1893 | C51: 1895 | D51: Guarantee pays Richmond's missed coupons | E51: Subsidy & guarantee | G51: Confederacy | H51: 2 | I51: =IF(H51="","",H51*(C51-B51+1)) -> 6 | J51: No | K51: Canon | L51: §25 | M51: Model estimate
A52: E47 | B52: 1894 | C52: 1894 | D52: Coal, equipment and credit for Japan (Korean war) | E52: Loan | F52: Asia | G52: Japan | H52: 10 | I52: =IF(H52="","",H52*(C52-B52+1)) -> 10 | J52: No | K52: Canon | L52: §25 | M52: Model estimate
A53: E48 | B53: 1894 | C53: 1895 | D53: Bread March: border defence, detention, filmed trials | E53: War & operations | H53: 0.4 | I53: =IF(H53="","",H53*(C53-B53+1)) -> 0.8 | J53: No | K53: Canon | L53: §25 | M53: Model estimate
A54: E49 | B54: 1894 | C54: 1900 | D54: Pacific cable onward from Oahu via Midway and Guam to Manila | E54: Investment | H54: 3 | I54: =IF(H54="","",H54*(C54-B54+1)) -> 21 | J54: No | K54: Proposed | L54: §25 | M54: Old model $20m gross; the San Francisco-Oahu leg is E101
A55: E50 | B55: 1895 | C55: 1895 | D55: Rescue of the Union's gold reserve | E55: Loan | F55: Continental | G55: Union | H55: 65 | I55: =IF(H55="","",H55*(C55-B55+1)) -> 65 | J55: Yes | K55: Canon | L55: §25 | M55: Size of the historical 1895 Morgan-Belmont syndicate
A56: E51 | B56: 1895 | C56: 1895 | D56: Chinese indemnity facility (public share) | E56: Loan | F56: Asia | G56: China | H56: 15 | I56: =IF(H56="","",H56*(C56-B56+1)) -> 15 | J56: No | K56: Proposed | L56: §25 | M56: Public share of a $75m facility
A57: E52 | B57: 1895 | C57: 1895 | D57: Formosan revenue administration set-up | E57: Programme | G57: China | H57: 0.5 | I57: =IF(H57="","",H57*(C57-B57+1)) -> 0.5 | J57: No | K57: Canon | L57: §25 | M57: Old model value
A58: E53 | B58: 1896 | C58: 1897 | D58: Manchurian and Hankow-Canton railway credits | E58: Loan | F58: Asia | G58: China | H58: 3 | I58: =IF(H58="","",H58*(C58-B58+1)) -> 6 | J58: No | K58: Proposed | L58: §25 | M58: Public share of $20m
A59: E54 | B59: 1897 | C59: 1897 | D59: Gold loan for Japan's move to gold | E59: Loan | F59: Asia | G59: Japan | H59: 20 | I59: =IF(H59="","",H59*(C59-B59+1)) -> 20 | J59: Yes | K59: Proposed | L59: §25 | M59: Old model L11
A60: E55 | B60: 1898 | C60: 1899 | D60: Primorye war: holding the sea | E60: War & operations | G60: Russia | H60: 6 | I60: =IF(H60="","",H60*(C60-B60+1)) -> 12 | J60: No | K60: Canon | L60: §25 | M60: Old model $6m a year
A61: E56 | B61: 1898 | C61: 1899 | D61: Primorye war credit for Japan | E61: Loan | F61: Asia | G61: Japan | H61: 15 | I61: =IF(H61="","",H61*(C61-B61+1)) -> 30 | J61: No | K61: Canon | L61: §25 | M61: Old model L13: $30m
A62: E57 | B62: 1898 | C62: 1899 | D62: Cuban colonial debt bought on customs security | E62: Loan | F62: Continental | G62: Cuba | H62: 9 | I62: =IF(H62="","",H62*(C62-B62+1)) -> 18 | J62: No | K62: Proposed | L62: §25 | M62: Old model $18m
A63: E58 | B63: 1899 | C63: 1899 | D63: Exclusive Nicaraguan canal rights | E63: Purchase | G63: Nicaragua | H63: 3 | I63: =IF(H63="","",H63*(C63-B63+1)) -> 3 | J63: No | K63: Proposed | L63: §25 | M63: Old model value
A64: E59 | B64: 1899 | C64: 1900 | D64: Finlay's yellow-fever work | E64: Relief | G64: Cuba | H64: 0.1 | I64: =IF(H64="","",H64*(C64-B64+1)) -> 0.2 | J64: No | K64: Proposed | L64: §25 | M64: Model estimate
A65: E60 | B65: 1898 | C65: 1902 | D65: Pearl Harbor drydock and dockyard (second phase) | E65: Programme | H65: 3 | I65: =IF(H65="","",H65*(C65-B65+1)) -> 15 | J65: No | K65: Proposed | L65: §25 | M65: Model estimate; the dredging is E100
A66: E61 | B66: 1899 | C66: 1901 | D66: Skagway-Whitehorse railway, assay and banking (public share) | E66: Programme | G66: Canada | H66: 1 | I66: =IF(H66="","",H66*(C66-B66+1)) -> 3 | J66: No | K66: Approved | L66: §25 | M66: Klondike route income policy
A67: E62 | B67: 1900 | C67: 1900 | D67: Boxer relief contingent | E67: War & operations | G67: China | H67: 1 | I67: =IF(H67="","",H67*(C67-B67+1)) -> 1 | J67: No | K67: Proposed | L67: §25 | M67: Indemnity turned into scholarships
A68: E63 | B68: 1900 | C68: 1900 | D68: Reserve Bank of Pacifica: capital | E68: Bank rescue & capital | H68: 10 | I68: =IF(H68="","",H68*(C68-B68+1)) -> 10 | J68: No | K68: Model estimate | L68: §34 | M68: Needed for the canon lender-of-last-resort role in 1931
A69: E64 | B69: 1904 | C69: 1905 | D69: Takahashi's war loans in San Francisco (public share) | E69: Loan | F69: Asia | G69: Japan | H69: 30 | I69: =IF(H69="","",H69*(C69-B69+1)) -> 60 | J69: No | K69: Canon | L69: §26 | M69: 15% of a $400m syndicate
A70: E65 | B70: 1904 | C70: 1905 | D70: Neutral fleet readiness, Russo-Japanese war | E70: War & operations | H70: 3 | I70: =IF(H70="","",H70*(C70-B70+1)) -> 6 | J70: No | K70: Model estimate | L70: §26
A71: E66 | B71: 1911 | C71: 1913 | D71: Support for Sun Yat-sen's movement | E71: Subsidy & guarantee | G71: China | H71: 2 | I71: =IF(H71="","",H71*(C71-B71+1)) -> 6 | J71: No | K71: Proposed | L71: §27 | M71: Model estimate
A72: E67 | B72: 1914 | C72: 1914 | D72: Germany's Pacific islands and Tsingtao | E72: War & operations | G72: Germany | H72: 25 | I72: =IF(H72="","",H72*(C72-B72+1)) -> 25 | J72: No | K72: Proposed | L72: §28 | M72: Model estimate
A73: E68 | B73: 1915 | C73: 1918 | D73: Wartime naval operations and convoys | E73: War & operations | H73: 40 | I73: =IF(H73="","",H73*(C73-B73+1)) -> 160 | J73: No | K73: Proposed | L73: §30 | M73: On top of the navy plan
A74: E69 | B74: 1915 | C74: 1918 | D74: Belgian relief administration (public share) | E74: Relief | G74: Belgium | H74: 25 | I74: =IF(H74="","",H74*(C74-B74+1)) -> 100 | J74: No | K74: Proposed | L74: §30 | M74: Hoover's relief, model estimate
A75: E70 | B75: 1914 | C75: 1914 | D75: Entente credit, Treasury share (1914) | E75: Loan | F75: Europe | G75: Britain & France | H75: =entente_total*entente_public*0.05 -> 85 | I75: =IF(H75="","",H75*(C75-B75+1)) -> 85 | J75: No | K75: Proposed | L75: §30 | M75: Profile of the old model's lending by year
A76: E71 | B76: 1915 | C76: 1915 | D76: Entente credit, Treasury share (1915) | E76: Loan | F76: Europe | G76: Britain & France | H76: =entente_total*entente_public*0.1333 -> 226.61 | I76: =IF(H76="","",H76*(C76-B76+1)) -> 226.61 | J76: No | K76: Proposed | L76: §30 | M76: Profile of the old model's lending by year
A77: E72 | B77: 1916 | C77: 1916 | D77: Entente credit, Treasury share (1916) | E77: Loan | F77: Europe | G77: Britain & France | H77: =entente_total*entente_public*0.2333 -> 396.61 | I77: =IF(H77="","",H77*(C77-B77+1)) -> 396.61 | J77: No | K77: Proposed | L77: §30 | M77: Profile of the old model's lending by year
A78: E73 | B78: 1917 | C78: 1917 | D78: Entente credit, Treasury share (1917) | E78: Loan | F78: Europe | G78: Britain & France | H78: =entente_total*entente_public*0.3 -> 510 | I78: =IF(H78="","",H78*(C78-B78+1)) -> 510 | J78: No | K78: Proposed | L78: §30 | M78: Profile of the old model's lending by year
A79: E74 | B79: 1918 | C79: 1918 | D79: Entente credit, Treasury share (1918) | E79: Loan | F79: Europe | G79: Britain & France | H79: =entente_total*entente_public*0.2834 -> 481.78 | I79: =IF(H79="","",H79*(C79-B79+1)) -> 481.78 | J79: No | K79: Proposed | L79: §30 | M79: Profile of the old model's lending by year
A80: E75 | B80: 1918 | C80: 1919 | D80: Food for the Central Powers (the armistice lever) | E80: Relief | G80: Germany | H80: 60 | I80: =IF(H80="","",H80*(C80-B80+1)) -> 120 | J80: No | K80: Proposed | L80: §30 | M80: Model estimate
A81: E76 | B81: 1918 | C81: 1918 | D81: Russian war 1918: Pacifican spending on the line (Siberia sheet) | E81: War & operations | G81: Siberia | H81: =Siberia!B38 -> 171.19426 | I81: =IF(H81="","",H81*(C81-B81+1)) -> 171.19426 | J81: No | K81: Canon | L81: §31 | M81: Siberia sheet (CR-041 Plan C), built up from the operational schedule
A82: E77 | B82: 1918 | C82: 1922 | D82: Wartime loans to Chinese and Siberian partners | E82: Loan | F82: Asia | G82: China & Siberia | H82: 17 | I82: =IF(H82="","",H82*(C82-B82+1)) -> 85 | J82: No | K82: Proposed | L82: §31 | M82: Sol's proposal: $85m public
A83: E78 | B83: 1919 | C83: 1919 | D83: The Hague peace and the arbitration court | E83: Programme | H83: 1 | I83: =IF(H83="","",H83*(C83-B83+1)) -> 1 | J83: No | K83: Proposed | L83: §30 | M83: Model estimate
A84: E79 | B84: 1922 | C84: 1932 | D84: Lena gold concessions | E84: Receipt | G84: Siberia | H84: 3 | I84: =IF(H84="","",H84*(C84-B84+1)) -> 33 | J84: No | K84: Proposed | L84: §32 | M84: Model estimate
A85: E92 | B85: 1849 | C85: 1932 | D85: Miner licences ($2 residents, $4 foreigners a month) | E85: Receipt | H85: 1 | I85: =IF(H85="","",H85*(C85-B85+1)) -> 84 | J85: No | K85: Canon | L85: §5 | M85: Old model: $0.4-1.4m a year
A86: E80 | B86: 1885 | C86: 1928 | D86: Chinese customs agency fee | E86: Receipt | G86: China | H86: 0.05 | I86: =IF(H86="","",H86*(C86-B86+1)) -> 2.2 | J86: No | K86: Canon | L86: §16 | M86: Old model value
A87: E81 | B87: 1923 | C87: 1923 | D87: Guarantee of the federal compact 1923 (Pacifica's quota) | E87: War & operations | G87: Siberia | H87: =Siberia!B43 -> 10.240712 | I87: =IF(H87="","",H87*(C87-B87+1)) -> 10.240712 | J87: No | K87: Proposed | L87: §32 | M87: Siberia sheet: a railway and guarantee reserve instead of a standing front (CR-041); quota × the schedule's cost
A88: E82 | B88: 1923 | C88: 1923 | D88: Earthquake reconstruction credit for Japan (public share) | E88: Loan | F88: Asia | G88: Japan | H88: 50 | I88: =IF(H88="","",H88*(C88-B88+1)) -> 50 | J88: No | K88: Canon | L88: §33 | M88: Public third of $150m
A89: E83 | B89: 1924 | C89: 1928 | D89: Whampoa and Northern Expedition support | E89: Subsidy & guarantee | G89: China | H89: 2 | I89: =IF(H89="","",H89*(C89-B89+1)) -> 10 | J89: No | K89: Proposed | L89: §33 | M89: Model estimate
A90: E84 | B90: 1927 | C90: 1927 | D90: Japan foreign-settlement facility (public commitment) | E90: Commitment | F90: Asia | G90: Japan | H90: ='Japan rescue'!E46*'Japan rescue'!E47 -> 200 | I90: =IF(H90="","",H90*(C90-B90+1)) -> 200 | J90: No | K90: Canon | L90: §33 | M90: CR-024: commitment only. Actual public drawings feed Loans directly; private two-thirds reroutes Abroad investment.
A91: E85 | B91: 1927 | C91: 1932 | D91: Common ministries and overseas command (quota) | E91: Programme | G91: Japan | H91: =10*pac_quota -> 6.5 | I91: =IF(H91="","",H91*(C91-B91+1)) -> 39 | J91: No | K91: Proposed | L91: §33 | M91: Old model $10m a year shared
A92: E86 | B92: 1929 | C92: 1929 | D92: Soviet probe defeated | E92: War & operations | G92: USSR | H92: 10 | I92: =IF(H92="","",H92*(C92-B92+1)) -> 10 | J92: No | K92: Proposed | L92: §33 | M92: Model estimate
A93: E87 | B93: 1931 | C93: 1931 | D93: Manchurian plot: transport prohibition | E93: War & operations | G93: Japan | H93: 5 | I93: =IF(H93="","",H93*(C93-B93+1)) -> 5 | J93: No | K93: Canon | L93: §35 | M93: Model estimate
A94: E88 | B94: 1931 | C94: 1931 | D94: Second gold rescue of the Union, first tranche | E94: Loan | F94: Rescue | G94: Union | H94: =union_rescue*0.6 -> 240 | I94: =IF(H94="","",H94*(C94-B94+1)) -> 240 | J94: Yes | K94: Canon | L94: §34 | M94: Size proposed
A95: E89 | B95: 1932 | C95: 1932 | D95: Second gold rescue of the Union, second tranche | E95: Loan | F95: Rescue | G95: Union | H95: =union_rescue*0.4 -> 160 | I95: =IF(H95="","",H95*(C95-B95+1)) -> 160 | J95: Yes | K95: Canon | L95: §34 | M95: Size proposed
A96: E90 | B96: 1931 | C96: 1932 | D96: Recapitalisation of Pacifican banks | E96: Bank rescue & capital | H96: =bank_recap/2 -> 75 | I96: =IF(H96="","",H96*(C96-B96+1)) -> 150 | J96: No | K96: Proposed | L96: §34 | M96: Model estimate
A97: E91 | B97: 1932 | C97: 1932 | D97: Thalassia Conference | E97: Programme | H97: 1 | I97: =IF(H97="","",H97*(C97-B97+1)) -> 1 | J97: No | K97: Proposed | L97: §37 | M97: Model estimate
A98: E93 | B98: 1919 | C98: 1923 | D98: The Living Bay: sewage tunnel beyond Mokapu, slope forests, restored fishponds, marine reserve | E98: Programme | H98: 1.8 | I98: =IF(H98="","",H98*(C98-B98+1)) -> 9 | J98: No | K98: Approved | L98: CR-020 B7 | M98: Keawe's first scheme (1923 marine reserve); the restored fishponds feed the capital
A99: E113 | B99: 1876 | C99: 1882 | D99: Pali railway tunnel to Honolulu and Pearl Harbor, and Kaneohe Bay channel | E99: Investment | H99: 1 | I99: =IF(H99="","",H99*(C99-B99+1)) -> 7 | J99: No | K99: Proposed | L99: CR-021 B6 | M99: Model estimate, about $7m; the Waiahole water tunnel (1913-16) ran 2.7 miles through the same range
A100: E94 | B100: 1923 | C100: 1932 | D100: Watershed reserves, minimum stream flows, quarantine (all islands) | E100: Programme | H100: 1 | I100: =IF(H100="","",H100*(C100-B100+1)) -> 10 | J100: No | K100: Proposed | L100: CR-020 B7 | M100: Model estimate
...

Sheet Paths
A1: Year-by-year inputs
A2: Time paths behind the model: prices, migration, growth, tax rates, army size and loan terms.
A3: Years run down the page. Blue = input you can change · black = formula · green = link to another sheet. Hover a column heading for its definition.
B4: Prices & people | E4: Gross arrivals (story case) | K4: Prices & people | L4: Economy | N4: Taxes | T4: Spending | Y4: Financing
A5: Year | B5: Price level (1913 = 1) | C5: Natural increase | D5: Residents joining with territory | E5: Arrivals: Americas & Europe | F5: Arrivals: Chinese | G5: Arrivals: Japanese | H5: Arrivals: Filipino | I5: Return migration, Americas & Europe | J5: Share of arrivals assisted | K5: Philippine crown residents (separate) | L5: Real output growth per resident (story) | M5: Output vs trend (slumps) | N5: Dutiable imports / GDP | O5: Average tariff | P5: Domestic taxes / non-mining GDP | Q5: Tax collection | R5: State enterprises & concessions / GDP | S5: Panama canal tolls ($m) | T5: Civil services / GDP | U5: Public works / GDP | V5: Technical & industrial programmes / GDP | W5: Active army | X5: Trained reserves | Y5: Average coupon on public debt | Z5: Coupon on Entente / European loans | AA5: Repayment rate on European loans | AB5: European debtors paying (1/0) | AC5: War year (1/0) | AD5: World monetary gold ($m)
A6: 1846 | B6: 0.74 | C6: -0.008667 | D6: 0 | E6: 2000 | F6: 0 | G6: 0 | H6: 0 | I6: 0.2 | J6: 0.2 | K6: 0 | L6: 0 | M6: 1 | N6: 0.3 | O6: 0.08 | P6: 0.03 | Q6: 0.85 | R6: 0 | S6: 0 | T6: 0.018 | U6: 0.01 | V6: 0 | W6: 500 | X6: 0 | Y6: 0.06 | Z6: 0.05 | AA6: 0.03 | AB6: 1 | AC6: 0 | AD6: 1500
A7: 1847 | B7: 0.74 | C7: -0.008149 | D7: 0 | E7: 3000 | F7: 0 | G7: 0 | H7: 0 | I7: 0.2 | J7: 0.2 | K7: 0 | L7: 0.04 | M7: 1 | N7: 0.2967 | O7: 0.08 | P7: 0.03 | Q7: 0.85 | R7: 2e-05 | S7: 0 | T7: 0.0183 | U7: 0.0108 | V7: 0.0007 | W7: 1500 | X7: 1000 | Y7: 0.0603 | Z7: 0.05 | AA7: 0.03 | AB7: 1 | AC7: 0 | AD7: 1500
A8: 1848 | B8: 0.74 | C8: -0.007642 | D8: 0 | E8: 15000 | F8: 0 | G8: 0 | H8: 0 | I8: 0.2 | J8: 0.2 | K8: 0 | L8: 0.04 | M8: 1 | N8: 0.2933 | O8: 0.08 | P8: 0.03 | Q8: 0.85 | R8: 4e-05 | S8: 0 | T8: 0.0187 | U8: 0.0117 | V8: 0.0013 | W8: 1000 | X8: 2000 | Y8: 0.0605 | Z8: 0.05 | AA8: 0.03 | AB8: 1 | AC8: 0 | AD8: 1500
A9: 1849 | B9: 1.18 | C9: -0.003279 | D9: 0 | E9: 60000 | F9: 300 | G9: 0 | H9: 0 | I9: 0.35 | J9: 0.2 | K9: 0 | L9: 0.04 | M9: 1 | N9: 0.29 | O9: 0.08 | P9: 0.06 | Q9: 0.85 | R9: 6e-05 | S9: 0 | T9: 0.019 | U9: 0.0125 | V9: 0.002 | W9: 1200 | X9: 3000 | Y9: 0.0608 | Z9: 0.05 | AA9: 0.03 | AB9: 1 | AC9: 0 | AD9: 1500
A10: 1850 | B10: 1.1 | C10: 0.006354 | D10: 0 | E10: 50000 | F10: 4000 | G10: 0 | H10: 0 | I10: 0.35 | J10: 0.2 | K10: 0 | L10: 0.04 | M10: 1 | N10: 0.2867 | O10: 0.08 | P10: 0.06 | Q10: 0.85 | R10: 8e-05 | S10: 0 | T10: 0.0193 | U10: 0.0133 | V10: 0.0027 | W10: 1500 | X10: 4000 | Y10: 0.0611 | Z10: 0.05 | AA10: 0.03 | AB10: 1 | AC10: 0 | AD10: 1500
A11: 1851 | B11: 1.02 | C11: 0.010016 | D11: 0 | E11: 40000 | F11: 3000 | G11: 0 | H11: 0 | I11: 0.35 | J11: 0.2 | K11: 0 | L11: 0.04 | M11: 1 | N11: 0.2833 | O11: 0.08 | P11: 0.06 | Q11: 0.85 | R11: 0.0001 | S11: 0 | T11: 0.0197 | U11: 0.0142 | V11: 0.0033 | W11: 2200 | X11: 6000 | Y11: 0.0613 | Z11: 0.05 | AA11: 0.03 | AB11: 1 | AC11: 0 | AD11: 1535
A12: 1852 | B12: 1 | C12: 0.011695 | D12: 0 | E12: 55000 | F12: 20000 | G12: 0 | H12: 0 | I12: 0.35 | J12: 0.4 | K12: 0 | L12: 0.04 | M12: 1 | N12: 0.28 | O12: 0.12 | P12: 0.075 | Q12: 0.85 | R12: 0.00013 | S12: 0 | T12: 0.02 | U12: 0.015 | V12: 0.004 | W12: 3000 | X12: 7000 | Y12: 0.0616 | Z12: 0.05 | AA12: 0.03 | AB12: 1 | AC12: 0 | AD12: 1570
A13: 1853 | B13: 0.99 | C13: 0.018934 | D13: 0 | E13: 40000 | F13: 6000 | G13: 0 | H13: 0 | I13: 0.35 | J13: 0.4 | K13: 0 | L13: 0.04 | M13: 1 | N13: 0.2783 | O13: 0.12 | P13: 0.075 | Q13: 0.85 | R13: 0.00015 | S13: 0 | T13: 0.0202 | U13: 0.0158 | V13: 0.0045 | W13: 3700 | X13: 8000 | Y13: 0.0618 | Z13: 0.05 | AA13: 0.03 | AB13: 1 | AC13: 0 | AD13: 1605
A14: 1854 | B14: 0.97 | C14: 0.020507 | D14: 0 | E14: 35000 | F14: 6000 | G14: 0 | H14: 0 | I14: 0.35 | J14: 0.4 | K14: 0 | L14: 0.04 | M14: 1 | N14: 0.2767 | O14: 0.12 | P14: 0.075 | Q14: 0.85 | R14: 0.00017 | S14: 0 | T14: 0.0203 | U14: 0.0165 | V14: 0.005 | W14: 4300 | X14: 9000 | Y14: 0.0621 | Z14: 0.05 | AA14: 0.03 | AB14: 1 | AC14: 0 | AD14: 1640
A15: 1855 | B15: 0.95 | C15: 0.021664 | D15: 0 | E15: 30000 | F15: 6000 | G15: 0 | H15: 0 | I15: 0.35 | J15: 0.4 | K15: 0 | L15: 0.04 | M15: 1 | N15: 0.275 | O15: 0.12 | P15: 0.085 | Q15: 0.85 | R15: 0.00019 | S15: 0 | T15: 0.0205 | U15: 0.0172 | V15: 0.0055 | W15: 5000 | X15: 10000 | Y15: 0.0624 | Z15: 0.05 | AA15: 0.03 | AB15: 1 | AC15: 0 | AD15: 1675
A16: 1856 | B16: 0.935 | C16: 0.02084 | D16: 72000 | E16: 30000 | F16: 6000 | G16: 0 | H16: 0 | I16: 0.2 | J16: 0.4 | K16: 0 | L16: 0.025 | M16: 1 | N16: 0.2733 | O16: 0.12 | P16: 0.085 | Q16: 0.85 | R16: 0.00021 | S16: 0 | T16: 0.0206 | U16: 0.018 | V16: 0.006 | W16: 6300 | X16: 23000 | Y16: 0.0626 | Z16: 0.05 | AA16: 0.03 | AB16: 1 | AC16: 0 | AD16: 1710
A17: 1857 | B17: 0.92 | C17: 0.020876 | D17: 0 | E17: 30000 | F17: 6000 | G17: 0 | H17: 0 | I17: 0.2 | J17: 0.4 | K17: 0 | L17: 0.025 | M17: 0.97 | N17: 0.2717 | O17: 0.12 | P17: 0.085 | Q17: 0.85 | R17: 0.00023 | S17: 0 | T17: 0.0208 | U17: 0.0181 | V17: 0.0061 | W17: 7700 | X17: 37000 | Y17: 0.0629 | Z17: 0.05 | AA17: 0.03 | AB17: 1 | AC17: 0 | AD17: 1745
... A92: 1932 | B92: 1.22 | C92: 0.016532 | D92: 0 | E92: 30000 | F92: 12000 | G92: 12000 | H92: 8000 | I92: 0.2 | J92: 0.3 | K92: 13218388 | L92: 0 | M92: 0.86 | N92: 0.13 | O92: 0.12 | P92: 0.085 | Q92: 0.8 | R92: 0.002 | S92: 22 | T92: 0.047 | U92: 0.026 | V92: 0.008 | W92: 42000 | X92: 220000 | Y92: 0.05 | Z92: 0.033 | AA92: 0 | AB92: 0 | AC92: 0 | AD92: 11900

Sheet People
A1: Population
A2: Residents of core Pacifica: births, territory, and four migration streams.
A3: Years run down the page. Blue = input you can change · black = formula · green = link to another sheet. Hover a column heading for its definition.
B4: Residents | E4: Arrivals | L4: Residents | N4: Asian-origin residents | T4: Programme | V4: With the Gulf | Y4: Memo (not in totals)
A5: Year | B5: Residents at start of year | C5: Join with territory | D5: Natural increase | E5: Arrivals: Americas & Europe | F5: Arrivals: Chinese | G5: Arrivals: Japanese | H5: Arrivals: Filipino | I5: Leave again | J5: Extra arrivals drawn by Pacifica's lead | K5: Net migration | L5: Residents at end of year | M5: Growth | N5: Chinese-Pacificans | O5: Japanese-Pacificans | P5: Filipino-Pacificans | Q5: Settled guest workers of Asian origin (now in N-P) | R5: Asian talent migrants and families (now in N-P) | S5: Asian-origin share | T5: Assisted arrivals | U5: Philippine crown residents (separate) | V5: Gulf Republic residents (once a member) | W5: All residents incl. the Gulf | X5: Everyone present, incl. guest workers | Y5: Native Hawaiians (memo, population model) | Z5: Native Californians (memo, population model)
A6: 1846 | B6: =pop_1846 -> 170000 | C6: =Paths!D6 -> 0 | D6: =B6*Paths!C6 -> -1473.39 | E6: =Paths!E6*IF($A6>=1896,mig_scale,1)*IF(AND($A6>=1848,$A6<=1860),dem01_mult,1) -> 2000 | F6: =Paths!F6*IF($A6>=1896,mig_scale,1)*IF(AND($A6>=1848,$A6<=1860),dem01_mult,1) -> 0 | G6: =Paths!G6*IF($A6>=1896,mig_scale,1) -> 0 | H6: =Paths!H6*IF($A6>=1896,mig_scale,1) -> 0 | I6: =E6*Paths!I6+(F6+G6+H6)*dep_asia -> 400 | J6: =Labour!AL6 -> 0 | K6: =SUM(E6:H6)-I6+J6 -> 1600 | L6: =B6+C6+D6+K6 -> 170126.61 | M6: =IF(B6>0,L6/B6-1,0) -> 0.00074476471 | N6: =0 -> 0 | O6: =0 -> 0 | P6: =0 -> 0 | Q6: =0 -> 0 | R6: =0 -> 0 | S6: =(N6+O6+P6+Q6+R6)/L6 -> 0 | T6: =SUM(E6:H6)*Paths!J6 -> 400 | U6: =Paths!K6 -> 0 | V6: =IF(Gulf!E6=1,Gulf!B6,0) -> 0 | W6: =L6+V6 -> 170126.61 | X6: =W6+Labour!L6 -> 170126.61 | Y6: 0 | Z6: 148391
A7: 1847 | B7: =L6 -> 170126.61 | C7: =Paths!D7 -> 0 | D7: =B7*Paths!C7 -> -1386.3617 | E7: =Paths!E7*IF($A7>=1896,mig_scale,1)*IF(AND($A7>=1848,$A7<=1860),dem01_mult,1) -> 3000 | F7: =Paths!F7*IF($A7>=1896,mig_scale,1)*IF(AND($A7>=1848,$A7<=1860),dem01_mult,1) -> 0 | G7: =Paths!G7*IF($A7>=1896,mig_scale,1) -> 0 | H7: =Paths!H7*IF($A7>=1896,mig_scale,1) -> 0 | I7: =E7*Paths!I7+(F7+G7+H7)*dep_asia -> 600 | J7: =Labour!AL7 -> 0 | K7: =SUM(E7:H7)-I7+J7 -> 2400 | L7: =B7+C7+D7+K7 -> 171140.25 | M7: =IF(B7>0,L7/B7-1,0) -> 0.0059581406 | N7: =N6*(1+Paths!C7)+F7*(1-dep_asia)+Labour!AL7*IF($A7>=xo_year,xo_cn2,xo_cn1) -> 0 | O7: =O6*(1+Paths!C7)+G7*(1-dep_asia)+Labour!AL7*IF($A7>=xo_year,xo_jp2,xo_jp1) -> 0 | P7: =P6*(1+Paths!C7)+H7*(1-dep_asia)+Labour!AL7*IF($A7>=xo_year,xo_ph2,xo_ph1) -> 0 | Q7: =0 -> 0 | R7: =0 -> 0 | S7: =(N7+O7+P7+Q7+R7)/L7 -> 0 | T7: =SUM(E7:H7)*Paths!J7 -> 600 | U7: =Paths!K7 -> 0 | V7: =IF(Gulf!E7=1,Gulf!B7,0) -> 0 | W7: =L7+V7 -> 171140.25 | X7: =W7+Labour!L7 -> 171140.25 | Y7: 0 | Z7: 146799
A8: 1848 | B8: =L7 -> 171140.25 | C8: =Paths!D8 -> 0 | D8: =B8*Paths!C8 -> -1307.8538 | E8: =Paths!E8*IF($A8>=1896,mig_scale,1)*IF(AND($A8>=1848,$A8<=1860),dem01_mult,1) -> 31500 | F8: =Paths!F8*IF($A8>=1896,mig_scale,1)*IF(AND($A8>=1848,$A8<=1860),dem01_mult,1) -> 0 | G8: =Paths!G8*IF($A8>=1896,mig_scale,1) -> 0 | H8: =Paths!H8*IF($A8>=1896,mig_scale,1) -> 0 | I8: =E8*Paths!I8+(F8+G8+H8)*dep_asia -> 6300 | J8: =Labour!AL8 -> 0 | K8: =SUM(E8:H8)-I8+J8 -> 25200 | L8: =B8+C8+D8+K8 -> 195032.39 | M8: =IF(B8>0,L8/B8-1,0) -> 0.13960565 | N8: =N7*(1+Paths!C8)+F8*(1-dep_asia)+Labour!AL8*IF($A8>=xo_year,xo_cn2,xo_cn1) -> 0 | O8: =O7*(1+Paths!C8)+G8*(1-dep_asia)+Labour!AL8*IF($A8>=xo_year,xo_jp2,xo_jp1) -> 0 | P8: =P7*(1+Paths!C8)+H8*(1-dep_asia)+Labour!AL8*IF($A8>=xo_year,xo_ph2,xo_ph1) -> 0 | Q8: =0 -> 0 | R8: =0 -> 0 | S8: =(N8+O8+P8+Q8+R8)/L8 -> 0 | T8: =SUM(E8:H8)*Paths!J8 -> 6300 | U8: =Paths!K8 -> 0 | V8: =IF(Gulf!E8=1,Gulf!B8,0) -> 0 | W8: =L8+V8 -> 195032.39 | X8: =W8+Labour!L8 -> 195032.39 | Y8: 0 | Z8: 145225
A9: 1849 | B9: =L8 -> 195032.39 | C9: =Paths!D9 -> 0 | D9: =B9*Paths!C9 -> -639.51122 | E9: =Paths!E9*IF($A9>=1896,mig_scale,1)*IF(AND($A9>=1848,$A9<=1860),dem01_mult,1) -> 126000 | F9: =Paths!F9*IF($A9>=1896,mig_scale,1)*IF(AND($A9>=1848,$A9<=1860),dem01_mult,1) -> 630 | G9: =Paths!G9*IF($A9>=1896,mig_scale,1) -> 0 | H9: =Paths!H9*IF($A9>=1896,mig_scale,1) -> 0 | I9: =E9*Paths!I9+(F9+G9+H9)*dep_asia -> 44276.4 | J9: =Labour!AL9 -> 0 | K9: =SUM(E9:H9)-I9+J9 -> 82353.6 | L9: =B9+C9+D9+K9 -> 276746.48 | M9: =IF(B9>0,L9/B9-1,0) -> 0.41897701 | N9: =N8*(1+Paths!C9)+F9*(1-dep_asia)+Labour!AL9*IF($A9>=xo_year,xo_cn2,xo_cn1) -> 453.6 | O9: =O8*(1+Paths!C9)+G9*(1-dep_asia)+Labour!AL9*IF($A9>=xo_year,xo_jp2,xo_jp1) -> 0 | P9: =P8*(1+Paths!C9)+H9*(1-dep_asia)+Labour!AL9*IF($A9>=xo_year,xo_ph2,xo_ph1) -> 0 | Q9: =0 -> 0 | R9: =0 -> 0 | S9: =(N9+O9+P9+Q9+R9)/L9 -> 0.0016390452 | T9: =SUM(E9:H9)*Paths!J9 -> 25326 | U9: =Paths!K9 -> 0 | V9: =IF(Gulf!E9=1,Gulf!B9,0) -> 0 | W9: =L9+V9 -> 276746.48 | X9: =W9+Labour!L9 -> 276746.48 | Y9: 0 | Z9: 143667
A10: 1850 | B10: =L9 -> 276746.48 | C10: =Paths!D10 -> 0 | D10: =B10*Paths!C10 -> 1758.4472 | E10: =Paths!E10*IF($A10>=1896,mig_scale,1)*IF(AND($A10>=1848,$A10<=1860),dem01_mult,1) -> 105000 | F10: =Paths!F10*IF($A10>=1896,mig_scale,1)*IF(AND($A10>=1848,$A10<=1860),dem01_mult,1) -> 8400 | G10: =Paths!G10*IF($A10>=1896,mig_scale,1) -> 0 | H10: =Paths!H10*IF($A10>=1896,mig_scale,1) -> 0 | I10: =E10*Paths!I10+(F10+G10+H10)*dep_asia -> 39102 | J10: =Labour!AL10 -> 0 | K10: =SUM(E10:H10)-I10+J10 -> 74298 | L10: =B10+C10+D10+K10 -> 352802.93 | M10: =IF(B10>0,L10/B10-1,0) -> 0.27482354 | N10: =N9*(1+Paths!C10)+F10*(1-dep_asia)+Labour!AL10*IF($A10>=xo_year,xo_cn2,xo_cn1) -> 6504.4822 | O10: =O9*(1+Paths!C10)+G10*(1-dep_asia)+Labour!AL10*IF($A10>=xo_year,xo_jp2,xo_jp1) -> 0 | P10: =P9*(1+Paths!C10)+H10*(1-dep_asia)+Labour!AL10*IF($A10>=xo_year,xo_ph2,xo_ph1) -> 0 | Q10: =0 -> 0 | R10: =0 -> 0 | S10: =(N10+O10+P10+Q10+R10)/L10 -> 0.018436588 | T10: =SUM(E10:H10)*Paths!J10 -> 22680 | U10: =Paths!K10 -> 0 | V10: =IF(Gulf!E10=1,Gulf!B10,0) -> 0 | W10: =L10+V10 -> 352802.93 | X10: =W10+Labour!L10 -> 352802.93 | Y10: 0 | Z10: 142126
A11: 1851 | B11: =L10 -> 352802.93 | C11: =Paths!D11 -> 0 | D11: =B11*Paths!C11 -> 3533.6742 | E11: =Paths!E11*IF($A11>=1896,mig_scale,1)*IF(AND($A11>=1848,$A11<=1860),dem01_mult,1) -> 84000 | F11: =Paths!F11*IF($A11>=1896,mig_scale,1)*IF(AND($A11>=1848,$A11<=1860),dem01_mult,1) -> 6300 | G11: =Paths!G11*IF($A11>=1896,mig_scale,1) -> 0 | H11: =Paths!H11*IF($A11>=1896,mig_scale,1) -> 0 | I11: =E11*Paths!I11+(F11+G11+H11)*dep_asia -> 31164 | J11: =Labour!AL11 -> 0 | K11: =SUM(E11:H11)-I11+J11 -> 59136 | L11: =B11+C11+D11+K11 -> 415472.6 | M11: =IF(B11>0,L11/B11-1,0) -> 0.17763366 | N11: =N10*(1+Paths!C11)+F11*(1-dep_asia)+Labour!AL11*IF($A11>=xo_year,xo_cn2,xo_cn1) -> 11105.631 | O11: =O10*(1+Paths!C11)+G11*(1-dep_asia)+Labour!AL11*IF($A11>=xo_year,xo_jp2,xo_jp1) -> 0 | P11: =P10*(1+Paths!C11)+H11*(1-dep_asia)+Labour!AL11*IF($A11>=xo_year,xo_ph2,xo_ph1) -> 0 | Q11: =0 -> 0 | R11: =0 -> 0 | S11: =(N11+O11+P11+Q11+R11)/L11 -> 0.026730116 | T11: =SUM(E11:H11)*Paths!J11 -> 18060 | U11: =Paths!K11 -> 0 | V11: =IF(Gulf!E11=1,Gulf!B11,0) -> 0 | W11: =L11+V11 -> 415472.6 | X11: =W11+Labour!L11 -> 415472.6 | Y11: 0 | Z11: 140601
A12: 1852 | B12: =L11 -> 415472.6 | C12: =Paths!D12 -> 0 | D12: =B12*Paths!C12 -> 4858.9521 | E12: =Paths!E12*IF($A12>=1896,mig_scale,1)*IF(AND($A12>=1848,$A12<=1860),dem01_mult,1) -> 115500 | F12: =Paths!F12*IF($A12>=1896,mig_scale,1)*IF(AND($A12>=1848,$A12<=1860),dem01_mult,1) -> 42000 | G12: =Paths!G12*IF($A12>=1896,mig_scale,1) -> 0 | H12: =Paths!H12*IF($A12>=1896,mig_scale,1) -> 0 | I12: =E12*Paths!I12+(F12+G12+H12)*dep_asia -> 52185 | J12: =Labour!AL12 -> 0 | K12: =SUM(E12:H12)-I12+J12 -> 105315 | L12: =B12+C12+D12+K12 -> 525646.56 | M12: =IF(B12>0,L12/B12-1,0) -> 0.26517742 | N12: =N11*(1+Paths!C12)+F12*(1-dep_asia)+Labour!AL12*IF($A12>=xo_year,xo_cn2,xo_cn1) -> 41475.511 | O12: =O11*(1+Paths!C12)+G12*(1-dep_asia)+Labour!AL12*IF($A12>=xo_year,xo_jp2,xo_jp1) -> 0 | P12: =P11*(1+Paths!C12)+H12*(1-dep_asia)+Labour!AL12*IF($A12>=xo_year,xo_ph2,xo_ph1) -> 0 | Q12: =0 -> 0 | R12: =0 -> 0 | S12: =(N12+O12+P12+Q12+R12)/L12 -> 0.078903801 | T12: =SUM(E12:H12)*Paths!J12 -> 63000 | U12: =Paths!K12 -> 0 | V12: =IF(Gulf!E12=1,Gulf!B12,0) -> 0 | W12: =L12+V12 -> 525646.56 | X12: =W12+Labour!L12 -> 525646.56 | Y12: 0 | Z12: 139093
A13: 1853 | B13: =L12 -> 525646.56 | C13: =Paths!D13 -> 0 | D13: =B13*Paths!C13 -> 9952.5919 | E13: =Paths!E13*IF($A13>=1896,mig_scale,1)*IF(AND($A13>=1848,$A13<=1860),dem01_mult,1) -> 84000 | F13: =Paths!F13*IF($A13>=1896,mig_scale,1)*IF(AND($A13>=1848,$A13<=1860),dem01_mult,1) -> 12600 | G13: =Paths!G13*IF($A13>=1896,mig_scale,1) -> 0 | H13: =Paths!H13*IF($A13>=1896,mig_scale,1) -> 0 | I13: =E13*Paths!I13+(F13+G13+H13)*dep_asia -> 32928 | J13: =Labour!AL13 -> 0 | K13: =SUM(E13:H13)-I13+J13 -> 63672 | L13: =B13+C13+D13+K13 -> 599271.15 | M13: =IF(B13>0,L13/B13-1,0) -> 0.14006482 | N13: =N12*(1+Paths!C13)+F13*(1-dep_asia)+Labour!AL13*IF($A13>=xo_year,xo_cn2,xo_cn1) -> 51332.809 | O13: =O12*(1+Paths!C13)+G13*(1-dep_asia)+Labour!AL13*IF($A13>=xo_year,xo_jp2,xo_jp1) -> 0 | P13: =P12*(1+Paths!C13)+H13*(1-dep_asia)+Labour!AL13*IF($A13>=xo_year,xo_ph2,xo_ph1) -> 0 | Q13: =0 -> 0 | R13: =0 -> 0 | S13: =(N13+O13+P13+Q13+R13)/L13 -> 0.085658735 | T13: =SUM(E13:H13)*Paths!J13 -> 38640 | U13: =Paths!K13 -> 0 | V13: =IF(Gulf!E13=1,Gulf!B13,0) -> 0 | W13: =L13+V13 -> 599271.15 | X13: =W13+Labour!L13 -> 599271.15 | Y13: 0 | Z13: 137601
A14: 1854 | B14: =L13 -> 599271.15 | C14: =Paths!D14 -> 0 | D14: =B14*Paths!C14 -> 12289.253 | E14: =Paths!E14*IF($A14>=1896,mig_scale,1)*IF(AND($A14>=1848,$A14<=1860),dem01_mult,1) -> 73500 | F14: =Paths!F14*IF($A14>=1896,mig_scale,1)*IF(AND($A14>=1848,$A14<=1860),dem01_mult,1) -> 12600 | G14: =Paths!G14*IF($A14>=1896,mig_scale,1) -> 0 | H14: =Paths!H14*IF($A14>=1896,mig_scale,1) -> 0 | I14: =E14*Paths!I14+(F14+G14+H14)*dep_asia -> 29253 | J14: =Labour!AL14 -> 0 | K14: =SUM(E14:H14)-I14+J14 -> 56847 | L14: =B14+C14+D14+K14 -> 668407.4 | M14: =IF(B14>0,L14/B14-1,0) -> 0.11536723 | N14: =N13*(1+Paths!C14)+F14*(1-dep_asia)+Labour!AL14*IF($A14>=xo_year,xo_cn2,xo_cn1) -> 61457.491 | O14: =O13*(1+Paths!C14)+G14*(1-dep_asia)+Labour!AL14*IF($A14>=xo_year,xo_jp2,xo_jp1) -> 0 | P14: =P13*(1+Paths!C14)+H14*(1-dep_asia)+Labour!AL14*IF($A14>=xo_year,xo_ph2,xo_ph1) -> 0 | Q14: =0 -> 0 | R14: =0 -> 0 | S14: =(N14+O14+P14+Q14+R14)/L14 -> 0.091946155 | T14: =SUM(E14:H14)*Paths!J14 -> 34440 | U14: =Paths!K14 -> 0 | V14: =IF(Gulf!E14=1,Gulf!B14,0) -> 0 | W14: =L14+V14 -> 668407.4 | X14: =W14+Labour!L14 -> 668407.4 | Y14: 0 | Z14: 136125
A15: 1855 | B15: =L14 -> 668407.4 | C15: =Paths!D15 -> 0 | D15: =B15*Paths!C15 -> 14480.378 | E15: =Paths!E15*IF($A15>=1896,mig_scale,1)*IF(AND($A15>=1848,$A15<=1860),dem01_mult,1) -> 63000 | F15: =Paths!F15*IF($A15>=1896,mig_scale,1)*IF(AND($A15>=1848,$A15<=1860),dem01_mult,1) -> 12600 | G15: =Paths!G15*IF($A15>=1896,mig_scale,1) -> 0 | H15: =Paths!H15*IF($A15>=1896,mig_scale,1) -> 0 | I15: =E15*Paths!I15+(F15+G15+H15)*dep_asia -> 25578 | J15: =Labour!AL15 -> 0 | K15: =SUM(E15:H15)-I15+J15 -> 50022 | L15: =B15+C15+D15+K15 -> 732909.78 | M15: =IF(B15>0,L15/B15-1,0) -> 0.096501591 | N15: =N14*(1+Paths!C15)+F15*(1-dep_asia)+Labour!AL15*IF($A15>=xo_year,xo_cn2,xo_cn1) -> 71860.906 | O15: =O14*(1+Paths!C15)+G15*(1-dep_asia)+Labour!AL15*IF($A15>=xo_year,xo_jp2,xo_jp1) -> 0 | P15: =P14*(1+Paths!C15)+H15*(1-dep_asia)+Labour!AL15*IF($A15>=xo_year,xo_ph2,xo_ph1) -> 0 | Q15: =0 -> 0 | R15: =0 -> 0 | S15: =(N15+O15+P15+Q15+R15)/L15 -> 0.098048774 | T15: =SUM(E15:H15)*Paths!J15 -> 30240 | U15: =Paths!K15 -> 0 | V15: =IF(Gulf!E15=1,Gulf!B15,0) -> 0 | W15: =L15+V15 -> 732909.78 | X15: =W15+Labour!L15 -> 732909.78 | Y15: 0 | Z15: 134664
A16: 1856 | B16: =L15 -> 732909.78 | C16: =Paths!D16 -> 72000 | D16: =B16*Paths!C16 -> 15273.84 | E16: =Paths!E16*IF($A16>=1896,mig_scale,1)*IF(AND($A16>=1848,$A16<=1860),dem01_mult,1) -> 63000 | F16: =Paths!F16*IF($A16>=1896,mig_scale,1)*IF(AND($A16>=1848,$A16<=1860),dem01_mult,1) -> 12600 | G16: =Paths!G16*IF($A16>=1896,mig_scale,1) -> 0 | H16: =Paths!H16*IF($A16>=1896,mig_scale,1) -> 0 | I16: =E16*Paths!I16+(F16+G16+H16)*dep_asia -> 16128 | J16: =Labour!AL16 -> 4837.2045 | K16: =SUM(E16:H16)-I16+J16 -> 64309.205 | L16: =B16+C16+D16+K16 -> 884492.82 | M16: =IF(B16>0,L16/B16-1,0) -> 0.20682361 | N16: =N15*(1+Paths!C16)+F16*(1-dep_asia)+Labour!AL16*IF($A16>=xo_year,xo_cn2,xo_cn1) -> 82914.207 | O16: =O15*(1+Paths!C16)+G16*(1-dep_asia)+Labour!AL16*IF($A16>=xo_year,xo_jp2,xo_jp1) -> 967.44091 | P16: =P15*(1+Paths!C16)+H16*(1-dep_asia)+Labour!AL16*IF($A16>=xo_year,xo_ph2,xo_ph1) -> 0 | Q16: =0 -> 0 | R16: =0 -> 0 | S16: =(N16+O16+P16+Q16+R16)/L16 -> 0.094835872 | T16: =SUM(E16:H16)*Paths!J16 -> 30240 | U16: =Paths!K16 -> 0 | V16: =IF(Gulf!E16=1,Gulf!B16,0) -> 0 | W16: =L16+V16 -> 884492.82 | X16: =W16+Labour!L16 -> 884492.82 | Y16: 68279 | Z16: 133220
A17: 1857 | B17: =L16 -> 884492.82 | C17: =Paths!D17 -> 0 | D17: =B17*Paths!C17 -> 18464.672 | E17: =Paths!E17*IF($A17>=1896,mig_scale,1)*IF(AND($A17>=1848,$A17<=1860),dem01_mult,1) -> 63000 | F17: =Paths!F17*IF($A17>=1896,mig_scale,1)*IF(AND($A17>=1848,$A17<=1860),dem01_mult,1) -> 12600 | G17: =Paths!G17*IF($A17>=1896,mig_scale,1) -> 0 | H17: =Paths!H17*IF($A17>=1896,mig_scale,1) -> 0 | I17: =E17*Paths!I17+(F17+G17+H17)*dep_asia -> 16128 | J17: =Labour!AL17 -> 5910.2107 | K17: =SUM(E17:H17)-I17+J17 -> 65382.211 | L17: =B17+C17+D17+K17 -> 968339.71 | M17: =IF(B17>0,L17/B17-1,0) -> 0.094796567 | N17: =N16*(1+Paths!C17)+F17*(1-dep_asia)+Labour!AL17*IF($A17>=xo_year,xo_cn2,xo_cn1) -> 94308.146 | O17: =O16*(1+Paths!C17)+G17*(1-dep_asia)+Labour!AL17*IF($A17>=xo_year,xo_jp2,xo_jp1) -> 2169.6793 | P17: =P16*(1+Paths!C17)+H17*(1-dep_asia)+Labour!AL17*IF($A17>=xo_year,xo_ph2,xo_ph1) -> 0 | Q17: =0 -> 0 | R17: =0 -> 0 | S17: =(N17+O17+P17+Q17+R17)/L17 -> 0.09963221 | T17: =SUM(E17:H17)*Paths!J17 -> 30240 | U17: =Paths!K17 -> 0 | V17: =IF(Gulf!E17=1,Gulf!B17,0) -> 0 | W17: =L17+V17 -> 968339.71 | X17: =W17+Labour!L17 -> 968339.71 | Y17: 67283 | Z17: 131791
A18: 1858 | B18: =L17 -> 968339.71 | C18: =Paths!D18 -> 0 | D18: =B18*Paths!C18 -> 21376.099 | E18: =Paths!E18*IF($A18>=1896,mig_scale,1)*IF(AND($A18>=1848,$A18<=1860),dem01_mult,1) -> 63000 | F18: =Paths!F18*IF($A18>=1896,mig_scale,1)*IF(AND($A18>=1848,$A18<=1860),dem01_mult,1) -> 12600 | G18: =Paths!G18*IF($A18>=1896,mig_scale,1) -> 0 | H18: =Paths!H18*IF($A18>=1896,mig_scale,1) -> 0 | I18: =E18*Paths!I18+(F18+G18+H18)*dep_asia -> 16128 | J18: =Labour!AL18 -> 6552.6796 | K18: =SUM(E18:H18)-I18+J18 -> 66024.68 | L18: =B18+C18+D18+K18 -> 1055740.5 | M18: =IF(B18>0,L18/B18-1,0) -> 0.090258386 | N18: =N17*(1+Paths!C18)+F18*(1-dep_asia)+Labour!AL18*IF($A18>=xo_year,xo_cn2,xo_cn1) -> 106117.27 | O18: =O17*(1+Paths!C18)+G18*(1-dep_asia)+Labour!AL18*IF($A18>=xo_year,xo_jp2,xo_jp1) -> 3528.1109 | P18: =P17*(1+Paths!C18)+H18*(1-dep_asia)+Labour!AL18*IF($A18>=xo_year,xo_ph2,xo_ph1) -> 0 | Q18: =0 -> 0 | R18: =0 -> 0 | S18: =(N18+O18+P18+Q18+R18)/L18 -> 0.10385637 | T18: =SUM(E18:H18)*Paths!J18 -> 30240 | U18: =Paths!K18 -> 0 | V18: =IF(Gulf!E18=1,Gulf!B18,0) -> 0 | W18: =L18+V18 -> 1055740.5 | X18: =W18+Labour!L18 -> 1055740.5 | Y18: 66301 | Z18: 130377
... A92: 1932 | B92: =L91 -> 35246949 | C92: =Paths!D92 -> 0 | D92: =B92*Paths!C92 -> 582702.56 | E92: =Paths!E92*IF($A92>=1896,mig_scale,1)*IF(AND($A92>=1848,$A92<=1860),dem01_mult,1) -> 30000 | F92: =Paths!F92*IF($A92>=1896,mig_scale,1)*IF(AND($A92>=1848,$A92<=1860),dem01_mult,1) -> 12000 | G92: =Paths!G92*IF($A92>=1896,mig_scale,1) -> 12000 | H92: =Paths!H92*IF($A92>=1896,mig_scale,1) -> 8000 | I92: =E92*Paths!I92+(F92+G92+H92)*dep_asia -> 14960 | J92: =Labour!AL92 -> 304486.38 | K92: =SUM(E92:H92)-I92+J92 -> 351526.38 | L92: =B92+C92+D92+K92 -> 36181178 | M92: =IF(B92>0,L92/B92-1,0) -> 0.026505243 | N92: =N91*(1+Paths!C92)+F92*(1-dep_asia)+Labour!AL92*IF($A92>=xo_year,xo_cn2,xo_cn1) -> 4709703.9 | O92: =O91*(1+Paths!C92)+G92*(1-dep_asia)+Labour!AL92*IF($A92>=xo_year,xo_jp2,xo_jp1) -> 5139971.1 | P92: =P91*(1+Paths!C92)+H92*(1-dep_asia)+Labour!AL92*IF($A92>=xo_year,xo_ph2,xo_ph1) -> 802489.57 | Q92: =0 -> 0 | R92: =0 -> 0 | S92: =(N92+O92+P92+Q92+R92)/L92 -> 0.29441177 | T92: =SUM(E92:H92)*Paths!J92 -> 18600 | U92: =Paths!K92 -> 13218388 | V92: =IF(Gulf!E92=1,Gulf!B92,0) -> 0 | W92: =L92+V92 -> 36181178 | X92: =W92+Labour!L92 -> 37191858 | Y92: 68435 | Z92: 131392

Sheet Economy
A1: Economy
A2: GDP = residents × real output per resident × slump factor × prices, plus mining and oil and the national champions.
A3: Years run down the page. Blue = input you can change · black = formula · green = link to another sheet. Hover a column heading for its definition.
B4: Inputs | I4: GDP | Q4: Benchmark
A5: Year | B5: Average residents | C5: Real growth per resident, before the Development Fund | D5: Extra growth from the Development Fund | E5: Real growth per resident | F5: Real non-mining output per resident (1913 $) | G5: Output vs trend | H5: Price level | I5: Output raised by the extra talent | J5: Non-mining GDP ($m) | K5: Mining & oil ($m) | L5: Guest workers' output ($m) | M5: National champions, extra ($m) | N5: Gulf Republic ($m, once a member) | O5: Core GDP ($m) | P5: GDP per person present ($) | Q5: US GDP per person, historical ($) | R5: Pacifica / US per person | S5: Real GDP (1913 $m)
A6: 1846 | B6: =(People!B6+People!L6)/2 -> 170063.3 | C6: =Paths!L6*IF($A6>=1896,prod_factor,1) -> 0 | D6: =0 -> 0 | E6: =C6+D6 -> 0 | F6: =real_pc_1846 -> 150 | G6: =1-(1-Paths!M6)*IF($A6>=1930,dep_severity,1) -> 1 | H6: =IF($A6>=1930,Paths!B$89+(Paths!B6-Paths!B$89)*slump_price,Paths!B6) -> 0.74 | I6: =Labour!AO6 -> 0 | J6: =B6*F6*(1+I6)*G6*H6/1000000 -> 18.877027 | K6: =Resources!O6 -> 0 | L6: =Labour!L6*gw_rel*J6/Labour!B6 -> 0 | M6: =Champions!AQ6 -> 0 | N6: =IF(Gulf!E6=1,Gulf!D6,0) -> 0 | O6: =J6+K6+L6+M6+N6 -> 18.877027 | P6: =O6*1000000/(B6+People!V6+Labour!L6) -> 111 | Q6: 95 | R6: =P6/Q6 -> 1.1684211 | S6: =O6/H6 -> 25.509496
A7: 1847 | B7: =(People!B7+People!L7)/2 -> 170633.43 | C7: =Paths!L7*IF($A7>=1896,prod_factor,1) -> 0.04 | D7: =IF(O6>0,MIN(dev_cap,dev_return*'Debt & cash'!N6/O6),0) -> 0 | E7: =C7+D7 -> 0.04 | F7: =F6*(1+E7) -> 156 | G7: =1-(1-Paths!M7)*IF($A7>=1930,dep_severity,1) -> 1 | H7: =IF($A7>=1930,Paths!B$89+(Paths!B7-Paths!B$89)*slump_price,Paths!B7) -> 0.74 | I7: =Labour!AO7 -> 0 | J7: =B7*F7*(1+I7)*G7*H7/1000000 -> 19.697923 | K7: =Resources!O7 -> 0 | L7: =Labour!L7*gw_rel*J7/Labour!B7 -> 0 | M7: =Champions!AQ7 -> 0 | N7: =IF(Gulf!E7=1,Gulf!D7,0) -> 0 | O7: =J7+K7+L7+M7+N7 -> 19.697923 | P7: =O7*1000000/(B7+People!V7+Labour!L7) -> 115.44 | Q7: 98 | R7: =P7/Q7 -> 1.1779592 | S7: =O7/H7 -> 26.618815
A8: 1848 | B8: =(People!B8+People!L8)/2 -> 183086.32 | C8: =Paths!L8*IF($A8>=1896,prod_factor,1) -> 0.04 | D8: =IF(O7>0,MIN(dev_cap,dev_return*'Debt & cash'!N7/O7),0) -> 0 | E8: =C8+D8 -> 0.04 | F8: =F7*(1+E8) -> 162.24 | G8: =1-(1-Paths!M8)*IF($A8>=1930,dep_severity,1) -> 1 | H8: =IF($A8>=1930,Paths!B$89+(Paths!B8-Paths!B$89)*slump_price,Paths!B8) -> 0.74 | I8: =Labour!AO8 -> 0 | J8: =B8*F8*(1+I8)*G8*H8/1000000 -> 21.980904 | K8: =Resources!O8 -> 7 | L8: =Labour!L8*gw_rel*J8/Labour!B8 -> 0 | M8: =Champions!AQ8 -> 0 | N8: =IF(Gulf!E8=1,Gulf!D8,0) -> 0 | O8: =J8+K8+L8+M8+N8 -> 28.980904 | P8: =O8*1000000/(B8+People!V8+Labour!L8) -> 158.29093 | Q8: 100 | R8: =P8/Q8 -> 1.5829093 | S8: =O8/H8 -> 39.163384
A9: 1849 | B9: =(People!B9+People!L9)/2 -> 235889.44 | C9: =Paths!L9*IF($A9>=1896,prod_factor,1) -> 0.04 | D9: =IF(O8>0,MIN(dev_cap,dev_return*'Debt & cash'!N8/O8),0) -> 0 | E9: =C9+D9 -> 0.04 | F9: =F8*(1+E9) -> 168.7296 | G9: =1-(1-Paths!M9)*IF($A9>=1930,dep_severity,1) -> 1 | H9: =IF($A9>=1930,Paths!B$89+(Paths!B9-Paths!B$89)*slump_price,Paths!B9) -> 1.18 | I9: =Labour!AO9 -> 0 | J9: =B9*F9*(1+I9)*G9*H9/1000000 -> 46.965806 | K9: =Resources!O9 -> 28 | L9: =Labour!L9*gw_rel*J9/Labour!B9 -> 0 | M9: =Champions!AQ9 -> 0 | N9: =IF(Gulf!E9=1,Gulf!D9,0) -> 0 | O9: =J9+K9+L9+M9+N9 -> 74.965806 | P9: =O9*1000000/(B9+People!V9+Labour!L9) -> 317.8006 | Q9: 102 | R9: =P9/Q9 -> 3.1156922 | S9: =O9/H9 -> 63.530344
A10: 1850 | B10: =(People!B10+People!L10)/2 -> 314774.71 | C10: =Paths!L10*IF($A10>=1896,prod_factor,1) -> 0.04 | D10: =IF(O9>0,MIN(dev_cap,dev_return*'Debt & cash'!N9/O9),0) -> 0 | E10: =C10+D10 -> 0.04 | F10: =F9*(1+E10) -> 175.47878 | G10: =1-(1-Paths!M10)*IF($A10>=1930,dep_severity,1) -> 1 | H10: =IF($A10>=1930,Paths!B$89+(Paths!B10-Paths!B$89)*slump_price,Paths!B10) -> 1.1 | I10: =Labour!AO10 -> 0 | J10: =B10*F10*(1+I10)*G10*H10/1000000 -> 60.759911 | K10: =Resources!O10 -> 28.7 | L10: =Labour!L10*gw_rel*J10/Labour!B10 -> 0 | M10: =Champions!AQ10 -> 0 | N10: =IF(Gulf!E10=1,Gulf!D10,0) -> 0 | O10: =J10+K10+L10+M10+N10 -> 89.459911 | P10: =O10*1000000/(B10+People!V10+Labour!L10) -> 284.20298 | Q10: 105 | R10: =P10/Q10 -> 2.7066951 | S10: =O10/H10 -> 81.327192
A11: 1851 | B11: =(People!B11+People!L11)/2 -> 384137.77 | C11: =Paths!L11*IF($A11>=1896,prod_factor,1) -> 0.04 | D11: =IF(O10>0,MIN(dev_cap,dev_return*'Debt & cash'!N10/O10),0) -> 0 | E11: =C11+D11 -> 0.04 | F11: =F10*(1+E11) -> 182.49794 | G11: =1-(1-Paths!M11)*IF($A11>=1930,dep_severity,1) -> 1 | H11: =IF($A11>=1930,Paths!B$89+(Paths!B11-Paths!B$89)*slump_price,Paths!B11) -> 1.02 | I11: =Labour!AO11 -> 0 | J11: =B11*F11*(1+I11)*G11*H11/1000000 -> 71.506436 | K11: =Resources!O11 -> 52.5 | L11: =Labour!L11*gw_rel*J11/Labour!B11 -> 0 | M11: =Champions!AQ11 -> 0 | N11: =IF(Gulf!E11=1,Gulf!D11,0) -> 0 | O11: =J11+K11+L11+M11+N11 -> 124.00644 | P11: =O11*1000000/(B11+People!V11+Labour!L11) -> 322.81761 | Q11: 109 | R11: =P11/Q11 -> 2.9616295 | S11: =O11/H11 -> 121.57494
A12: 1852 | B12: =(People!B12+People!L12)/2 -> 470559.58 | C12: =Paths!L12*IF($A12>=1896,prod_factor,1) -> 0.04 | D12: =IF(O11>0,MIN(dev_cap,dev_return*'Debt & cash'!N11/O11),0) -> 0 | E12: =C12+D12 -> 0.04 | F12: =F11*(1+E12) -> 189.79785 | G12: =1-(1-Paths!M12)*IF($A12>=1930,dep_severity,1) -> 1 | H12: =IF($A12>=1930,Paths!B$89+(Paths!B12-Paths!B$89)*slump_price,Paths!B12) -> 1 | I12: =Labour!AO12 -> 0 | J12: =B12*F12*(1+I12)*G12*H12/1000000 -> 89.311198 | K12: =Resources!O12 -> 56.7 | L12: =Labour!L12*gw_rel*J12/Labour!B12 -> 0 | M12: =Champions!AQ12 -> 0 | N12: =IF(Gulf!E12=1,Gulf!D12,0) -> 0 | O12: =J12+K12+L12+M12+N12 -> 146.0112 | P12: =O12*1000000/(B12+People!V12+Labour!L12) -> 310.29269 | Q12: 113 | R12: =P12/Q12 -> 2.745953 | S12: =O12/H12 -> 146.0112
A13: 1853 | B13: =(People!B13+People!L13)/2 -> 562458.85 | C13: =Paths!L13*IF($A13>=1896,prod_factor,1) -> 0.04 | D13: =IF(O12>0,MIN(dev_cap,dev_return*'Debt & cash'!N12/O12),0) -> 0 | E13: =C13+D13 -> 0.04 | F13: =F12*(1+E13) -> 197.38977 | G13: =1-(1-Paths!M13)*IF($A13>=1930,dep_severity,1) -> 1 | H13: =IF($A13>=1930,Paths!B$89+(Paths!B13-Paths!B$89)*slump_price,Paths!B13) -> 0.99 | I13: =Labour!AO13 -> 0 | J13: =B13*F13*(1+I13)*G13*H13/1000000 -> 109.91339 | K13: =Resources!O13 -> 46.9 | L13: =Labour!L13*gw_rel*J13/Labour!B13 -> 0 | M13: =Champions!AQ13 -> 0 | N13: =IF(Gulf!E13=1,Gulf!D13,0) -> 0 | O13: =J13+K13+L13+M13+N13 -> 156.81339 | P13: =O13*1000000/(B13+People!V13+Labour!L13) -> 278.79975 | Q13: 117 | R13: =P13/Q13 -> 2.3829038 | S13: =O13/H13 -> 158.39736
A14: 1854 | B14: =(People!B14+People!L14)/2 -> 633839.28 | C14: =Paths!L14*IF($A14>=1896,prod_factor,1) -> 0.04 | D14: =IF(O13>0,MIN(dev_cap,dev_return*'Debt & cash'!N13/O13),0) -> 0 | E14: =C14+D14 -> 0.04 | F14: =F13*(1+E14) -> 205.28536 | G14: =1-(1-Paths!M14)*IF($A14>=1930,dep_severity,1) -> 1 | H14: =IF($A14>=1930,Paths!B$89+(Paths!B14-Paths!B$89)*slump_price,Paths!B14) -> 0.97 | I14: =Labour!AO14 -> 0 | J14: =B14*F14*(1+I14)*G14*H14/1000000 -> 126.21438 | K14: =Resources!O14 -> 48.3 | L14: =Labour!L14*gw_rel*J14/Labour!B14 -> 0 | M14: =Champions!AQ14 -> 0 | N14: =IF(Gulf!E14=1,Gulf!D14,0) -> 0 | O14: =J14+K14+L14+M14+N14 -> 174.51438 | P14: =O14*1000000/(B14+People!V14+Labour!L14) -> 275.32908 | Q14: 121 | R14: =P14/Q14 -> 2.2754469 | S14: =O14/H14 -> 179.91174
A15: 1855 | B15: =(People!B15+People!L15)/2 -> 700658.59 | C15: =Paths!L15*IF($A15>=1896,prod_factor,1) -> 0.04 | D15: =IF(O14>0,MIN(dev_cap,dev_return*'Debt & cash'!N14/O14),0) -> 0 | E15: =C15+D15 -> 0.04 | F15: =F14*(1+E15) -> 213.49677 | G15: =1-(1-Paths!M15)*IF($A15>=1930,dep_severity,1) -> 1 | H15: =IF($A15>=1930,Paths!B$89+(Paths!B15-Paths!B$89)*slump_price,Paths!B15) -> 0.95 | I15: =Labour!AO15 -> 0 | J15: =B15*F15*(1+I15)*G15*H15/1000000 -> 142.10893 | K15: =Resources!O15 -> 38.5 | L15: =Labour!L15*gw_rel*J15/Labour!B15 -> 0 | M15: =Champions!AQ15 -> 0 | N15: =IF(Gulf!E15=1,Gulf!D15,0) -> 0 | O15: =J15+K15+L15+M15+N15 -> 180.60893 | P15: =O15*1000000/(B15+People!V15+Labour!L15) -> 257.77024 | Q15: 125 | R15: =P15/Q15 -> 2.0621619 | S15: =O15/H15 -> 190.11466
A16: 1856 | B16: =(People!B16+People!L16)/2 -> 808701.3 | C16: =Paths!L16*IF($A16>=1896,prod_factor,1) -> 0.025 | D16: =IF(O15>0,MIN(dev_cap,dev_return*'Debt & cash'!N15/O15),0) -> 0 | E16: =C16+D16 -> 0.025 | F16: =F15*(1+E16) -> 218.83419 | G16: =1-(1-Paths!M16)*IF($A16>=1930,dep_severity,1) -> 1 | H16: =IF($A16>=1930,Paths!B$89+(Paths!B16-Paths!B$89)*slump_price,Paths!B16) -> 0.935 | I16: =Labour!AO16 -> 0 | J16: =B16*F16*(1+I16)*G16*H16/1000000 -> 165.46835 | K16: =Resources!O16 -> 39.9 | L16: =Labour!L16*gw_rel*J16/Labour!B16 -> 0 | M16: =Champions!AQ16 -> 0 | N16: =IF(Gulf!E16=1,Gulf!D16,0) -> 0 | O16: =J16+K16+L16+M16+N16 -> 205.36835 | P16: =O16*1000000/(B16+People!V16+Labour!L16) -> 253.94833 | Q16: 128 | R16: =P16/Q16 -> 1.9839714 | S16: =O16/H16 -> 219.64529
A17: 1857 | B17: =(People!B17+People!L17)/2 -> 926416.27 | C17: =Paths!L17*IF($A17>=1896,prod_factor,1) -> 0.025 | D17: =IF(O16>0,MIN(dev_cap,dev_return*'Debt & cash'!N16/O16),0) -> 0 | E17: =C17+D17 -> 0.025 | F17: =F16*(1+E17) -> 224.30505 | G17: =1-(1-Paths!M17)*IF($A17>=1930,dep_severity,1) -> 0.97 | H17: =IF($A17>=1930,Paths!B$89+(Paths!B17-Paths!B$89)*slump_price,Paths!B17) -> 0.92 | I17: =Labour!AO17 -> 0.0084154567 | J17: =B17*F17*(1+I17)*G17*H17/1000000 -> 187.00115 | K17: =Resources!O17 -> 30.1 | L17: =Labour!L17*gw_rel*J17/Labour!B17 -> 0 | M17: =Champions!AQ17 -> 0 | N17: =IF(Gulf!E17=1,Gulf!D17,0) -> 0 | O17: =J17+K17+L17+M17+N17 -> 217.10115 | P17: =O17*1000000/(B17+People!V17+Labour!L17) -> 234.34514 | Q17: 131 | R17: =P17/Q17 -> 1.7888942 | S17: =O17/H17 -> 235.97951
A18: 1858 | B18: =(People!B18+People!L18)/2 -> 1012040.1 | C18: =Paths!L18*IF($A18>=1896,prod_factor,1) -> 0.025 | D18: =IF(O17>0,MIN(dev_cap,dev_return*'Debt & cash'!N17/O17),0) -> 0 | E18: =C18+D18 -> 0.025 | F18: =F17*(1+E18) -> 229.91267 | G18: =1-(1-Paths!M18)*IF($A18>=1930,dep_severity,1) -> 0.98 | H18: =IF($A18>=1930,Paths!B$89+(Paths!B18-Paths!B$89)*slump_price,Paths!B18) -> 0.9067 | I18: =Labour!AO18 -> 0.016027999 | J18: =B18*F18*(1+I18)*G18*H18/1000000 -> 210.06611 | K18: =Resources!O18 -> 32.9 | L18: =Labour!L18*gw_rel*J18/Labour!B18 -> 0 | M18: =Champions!AQ18 -> 0 | N18: =IF(Gulf!E18=1,Gulf!D18,0) -> 0 | O18: =J18+K18+L18+M18+N18 -> 242.96611 | P18: =O18*1000000/(B18+People!V18+Labour!L18) -> 240.07558 | Q18: 134 | R18: =P18/Q18 -> 1.7916088 | S18: =O18/H18 -> 267.96748
... A92: 1932 | B92: =(People!B92+People!L92)/2 -> 35714064 | C92: =Paths!L92*IF($A92>=1896,prod_factor,1) -> 0 | D92: =IF(O91>0,MIN(dev_cap,dev_return*'Debt & cash'!N91/O91),0) -> 0.0021877239 | E92: =C92+D92 -> 0.0021877239 | F92: =F91*(1+E92) -> 1105.7859 | G92: =1-(1-Paths!M92)*IF($A92>=1930,dep_severity,1) -> 0.86 | H92: =IF($A92>=1930,Paths!B$89+(Paths!B92-Paths!B$89)*slump_price,Paths!B92) -> 1.372 | I92: =Labour!AO92 -> 0.09117505 | J92: =B92*F92*(1+I92)*G92*H92/1000000 -> 50846.059 | K92: =Resources!O92 -> 152.145 | L92: =Labour!L92*gw_rel*J92/Labour!B92 -> 2055.5773 | M92: =Champions!AQ92 -> 1792.3376 | N92: =IF(Gulf!E92=1,Gulf!D92,0) -> 0 | O92: =J92+K92+L92+M92+N92 -> 54846.119 | P92: =O92*1000000/(B92+People!V92+Labour!L92) -> 1493.4378 | Q92: 476 | R92: =P92/Q92 -> 3.1374743 | S92: =O92/H92 -> 39975.305

Sheet Resources
A1: Gold, metals and oil
A2: What comes out of the ground, and what the state takes from it.
A3: Years run down the page. Blue = input you can change · black = formula · green = link to another sheet. Hover a column heading for its definition.
B4: Gross output, $m | G4: Concessions abroad, $m | I4: Oil | N4: Totals | P4: To the Treasury
A5: Year | B5: California gold ($m) | C5: Interior gold & silver ($m) | D5: Nevada gold & silver: Goldfield and Tonopah ($m) | E5: Alaska gold ($m) | F5: Copper & other metals ($m) | G5: Korean concession gold ($m) | H5: Kolyma gold, Siberian Republic ($m) | I5: Oil output before any compact (m barrels) | J5: Oil price before any compact ($ per barrel) | K5: Oil output (m barrels) | L5: Oil price ($ per barrel) | M5: Oil value ($m) | N5: Gross mineral output ($m) | O5: Mining & oil value added ($m) | P5: Metal royalties ($m) | Q5: Oil royalties ($m) | R5: New gold kept as money ($m)
A6: 1846 | B6: 0 | C6: 0 | D6: 0 | E6: 0 | F6: 0 | G6: 0 | H6: 0 | I6: 0 | J6: 0 | K6: =I6*IF(AND(oil_compact=1,$A6>=compact_year),1-compact_cut,1) -> 0 | L6: =IF(AND(oil_compact=1,$A6>=compact_year),MAX(J6,compact_price),J6) -> 0 | M6: =K6*L6 -> 0 | N6: =SUM(B6:F6)+M6 -> 0 | O6: =N6*mining_va -> 0 | P6: =SUM(B6:F6)*roy_metal*0.9 -> 0 | Q6: =M6*roy_oil -> 0 | R6: =SUM(B6:E6)*gold_retained+(G6+H6)*conc_gold -> 0
A7: 1847 | B7: 0 | C7: 0 | D7: 0 | E7: 0 | F7: 0 | G7: 0 | H7: 0 | I7: 0 | J7: 0 | K7: =I7*IF(AND(oil_compact=1,$A7>=compact_year),1-compact_cut,1) -> 0 | L7: =IF(AND(oil_compact=1,$A7>=compact_year),MAX(J7,compact_price),J7) -> 0 | M7: =K7*L7 -> 0 | N7: =SUM(B7:F7)+M7 -> 0 | O7: =N7*mining_va -> 0 | P7: =SUM(B7:F7)*roy_metal*0.9 -> 0 | Q7: =M7*roy_oil -> 0 | R7: =SUM(B7:E7)*gold_retained+(G7+H7)*conc_gold -> 0
A8: 1848 | B8: 10 | C8: 0 | D8: 0 | E8: 0 | F8: 0 | G8: 0 | H8: 0 | I8: 0 | J8: 0 | K8: =I8*IF(AND(oil_compact=1,$A8>=compact_year),1-compact_cut,1) -> 0 | L8: =IF(AND(oil_compact=1,$A8>=compact_year),MAX(J8,compact_price),J8) -> 0 | M8: =K8*L8 -> 0 | N8: =SUM(B8:F8)+M8 -> 10 | O8: =N8*mining_va -> 7 | P8: =SUM(B8:F8)*roy_metal*0.9 -> 0.45 | Q8: =M8*roy_oil -> 0 | R8: =SUM(B8:E8)*gold_retained+(G8+H8)*conc_gold -> 2
A9: 1849 | B9: 40 | C9: 0 | D9: 0 | E9: 0 | F9: 0 | G9: 0 | H9: 0 | I9: 0 | J9: 0 | K9: =I9*IF(AND(oil_compact=1,$A9>=compact_year),1-compact_cut,1) -> 0 | L9: =IF(AND(oil_compact=1,$A9>=compact_year),MAX(J9,compact_price),J9) -> 0 | M9: =K9*L9 -> 0 | N9: =SUM(B9:F9)+M9 -> 40 | O9: =N9*mining_va -> 28 | P9: =SUM(B9:F9)*roy_metal*0.9 -> 1.8 | Q9: =M9*roy_oil -> 0 | R9: =SUM(B9:E9)*gold_retained+(G9+H9)*conc_gold -> 8
A10: 1850 | B10: 41 | C10: 0 | D10: 0 | E10: 0 | F10: 0 | G10: 0 | H10: 0 | I10: 0 | J10: 0 | K10: =I10*IF(AND(oil_compact=1,$A10>=compact_year),1-compact_cut,1) -> 0 | L10: =IF(AND(oil_compact=1,$A10>=compact_year),MAX(J10,compact_price),J10) -> 0 | M10: =K10*L10 -> 0 | N10: =SUM(B10:F10)+M10 -> 41 | O10: =N10*mining_va -> 28.7 | P10: =SUM(B10:F10)*roy_metal*0.9 -> 1.845 | Q10: =M10*roy_oil -> 0 | R10: =SUM(B10:E10)*gold_retained+(G10+H10)*conc_gold -> 8.2
A11: 1851 | B11: 75 | C11: 0 | D11: 0 | E11: 0 | F11: 0 | G11: 0 | H11: 0 | I11: 0 | J11: 0 | K11: =I11*IF(AND(oil_compact=1,$A11>=compact_year),1-compact_cut,1) -> 0 | L11: =IF(AND(oil_compact=1,$A11>=compact_year),MAX(J11,compact_price),J11) -> 0 | M11: =K11*L11 -> 0 | N11: =SUM(B11:F11)+M11 -> 75 | O11: =N11*mining_va -> 52.5 | P11: =SUM(B11:F11)*roy_metal*0.9 -> 3.375 | Q11: =M11*roy_oil -> 0 | R11: =SUM(B11:E11)*gold_retained+(G11+H11)*conc_gold -> 15
A12: 1852 | B12: 81 | C12: 0 | D12: 0 | E12: 0 | F12: 0 | G12: 0 | H12: 0 | I12: 0 | J12: 0 | K12: =I12*IF(AND(oil_compact=1,$A12>=compact_year),1-compact_cut,1) -> 0 | L12: =IF(AND(oil_compact=1,$A12>=compact_year),MAX(J12,compact_price),J12) -> 0 | M12: =K12*L12 -> 0 | N12: =SUM(B12:F12)+M12 -> 81 | O12: =N12*mining_va -> 56.7 | P12: =SUM(B12:F12)*roy_metal*0.9 -> 3.645 | Q12: =M12*roy_oil -> 0 | R12: =SUM(B12:E12)*gold_retained+(G12+H12)*conc_gold -> 16.2
A13: 1853 | B13: 67 | C13: 0 | D13: 0 | E13: 0 | F13: 0 | G13: 0 | H13: 0 | I13: 0 | J13: 0 | K13: =I13*IF(AND(oil_compact=1,$A13>=compact_year),1-compact_cut,1) -> 0 | L13: =IF(AND(oil_compact=1,$A13>=compact_year),MAX(J13,compact_price),J13) -> 0 | M13: =K13*L13 -> 0 | N13: =SUM(B13:F13)+M13 -> 67 | O13: =N13*mining_va -> 46.9 | P13: =SUM(B13:F13)*roy_metal*0.9 -> 3.015 | Q13: =M13*roy_oil -> 0 | R13: =SUM(B13:E13)*gold_retained+(G13+H13)*conc_gold -> 13.4
A14: 1854 | B14: 69 | C14: 0 | D14: 0 | E14: 0 | F14: 0 | G14: 0 | H14: 0 | I14: 0 | J14: 0 | K14: =I14*IF(AND(oil_compact=1,$A14>=compact_year),1-compact_cut,1) -> 0 | L14: =IF(AND(oil_compact=1,$A14>=compact_year),MAX(J14,compact_price),J14) -> 0 | M14: =K14*L14 -> 0 | N14: =SUM(B14:F14)+M14 -> 69 | O14: =N14*mining_va -> 48.3 | P14: =SUM(B14:F14)*roy_metal*0.9 -> 3.105 | Q14: =M14*roy_oil -> 0 | R14: =SUM(B14:E14)*gold_retained+(G14+H14)*conc_gold -> 13.8
A15: 1855 | B15: 55 | C15: 0 | D15: 0 | E15: 0 | F15: 0 | G15: 0 | H15: 0 | I15: 0 | J15: 0 | K15: =I15*IF(AND(oil_compact=1,$A15>=compact_year),1-compact_cut,1) -> 0 | L15: =IF(AND(oil_compact=1,$A15>=compact_year),MAX(J15,compact_price),J15) -> 0 | M15: =K15*L15 -> 0 | N15: =SUM(B15:F15)+M15 -> 55 | O15: =N15*mining_va -> 38.5 | P15: =SUM(B15:F15)*roy_metal*0.9 -> 2.475 | Q15: =M15*roy_oil -> 0 | R15: =SUM(B15:E15)*gold_retained+(G15+H15)*conc_gold -> 11
A16: 1856 | B16: 57 | C16: 0 | D16: 0 | E16: 0 | F16: 0 | G16: 0 | H16: 0 | I16: 0 | J16: 0 | K16: =I16*IF(AND(oil_compact=1,$A16>=compact_year),1-compact_cut,1) -> 0 | L16: =IF(AND(oil_compact=1,$A16>=compact_year),MAX(J16,compact_price),J16) -> 0 | M16: =K16*L16 -> 0 | N16: =SUM(B16:F16)+M16 -> 57 | O16: =N16*mining_va -> 39.9 | P16: =SUM(B16:F16)*roy_metal*0.9 -> 2.565 | Q16: =M16*roy_oil -> 0 | R16: =SUM(B16:E16)*gold_retained+(G16+H16)*conc_gold -> 11.4
A17: 1857 | B17: 43 | C17: 0 | D17: 0 | E17: 0 | F17: 0 | G17: 0 | H17: 0 | I17: 0 | J17: 0 | K17: =I17*IF(AND(oil_compact=1,$A17>=compact_year),1-compact_cut,1) -> 0 | L17: =IF(AND(oil_compact=1,$A17>=compact_year),MAX(J17,compact_price),J17) -> 0 | M17: =K17*L17 -> 0 | N17: =SUM(B17:F17)+M17 -> 43 | O17: =N17*mining_va -> 30.1 | P17: =SUM(B17:F17)*roy_metal*0.9 -> 1.935 | Q17: =M17*roy_oil -> 0 | R17: =SUM(B17:E17)*gold_retained+(G17+H17)*conc_gold -> 8.6
... A92: 1932 | B92: 11 | C92: 10 | D92: 1 | E92: 10 | F92: 40 | G92: 7 | H92: 14 | I92: 180 | J92: 0.7 | K92: =I92*IF(AND(oil_compact=1,$A92>=compact_year),1-compact_cut,1) -> 153 | L92: =IF(AND(oil_compact=1,$A92>=compact_year),MAX(J92,compact_price),J92) -> 0.95 | M92: =K92*L92 -> 145.35 | N92: =SUM(B92:F92)+M92 -> 217.35 | O92: =N92*mining_va -> 152.145 | P92: =SUM(B92:F92)*roy_metal*0.9 -> 3.24 | Q92: =M92*roy_oil -> 18.16875 | R92: =SUM(B92:E92)*gold_retained+(G92+H92)*conc_gold -> 19

Sheet Budget
A1: Budget
A2: Receipts and spending of the Pacifican Treasury (the confederal/imperial budget), $m.
A3: Years run down the page. Blue = input you can change · black = formula · green = link to another sheet. Hover a column heading for its definition.
B4: Receipts, $m | N4: Spending, $m | Z4: Result
A5: Year | B5: Customs | C5: Domestic taxes | D5: Mineral & oil royalties | E5: Canal net income | F5: State enterprises | G5: Other receipts (Events, Land Fund) | H5: Interest on loans abroad | I5: Reserve Fund income | J5: Guest-worker levy | K5: Crown share in the national champions | L5: Tax on income from abroad | M5: Total receipts | N5: Army | O5: Navy | P5: War & operations (Events) | Q5: Civil services | R5: Public works | S5: Technical programmes | T5: Settlement & immigration | U5: Purchases & canal (Events) | V5: Subsidies, guarantees & relief (Events) | W5: Bank rescues & capital (Events) | X5: Debt interest | Y5: Total spending | Z5: Budget balance | AA5: Receipts / GDP | AB5: Spending / GDP | AC5: Defence & overseas / GDP
A6: 1846 | B6: =Economy!O6*Paths!N6*Paths!O6*cust_coll -> 0.40774378 | C6: =(Economy!J6+Economy!L6+Economy!M6+Economy!N6)*Paths!P6*Paths!Q6 -> 0.48136418 | D6: =Resources!P6+Resources!Q6 -> 0 | E6: =Paths!S6*(1-canal_opcost)*canal_share -> 0 | F6: =Economy!O6*Paths!R6 -> 0 | G6: =SUMPRODUCT((Events!$B$6:$B$400<=$A6)*(Events!$C$6:$C$400>=$A6)*(Events!$E$6:$E$400="Receipt")*Events!$H$6:$H$400)+'Land Fund'!O6 -> 0 | H6: =Loans!Y6 -> 0 | I6: =0 -> 0 | J6: =Labour!Q6 -> 0 | K6: =Champions!BD6 -> 0 | L6: =Abroad!N6 -> 0 | M6: =SUM(B6:L6) -> 0.88910796 | N6: =(Paths!W6*army_cost+Paths!X6*res_cost)*Economy!H6/1000000 -> 0.259 | O6: =Navy!Y6 -> 0 | P6: =SUMPRODUCT((Events!$B$6:$B$400<=$A6)*(Events!$C$6:$C$400>=$A6)*(Events!$E$6:$E$400="War & operations")*Events!$H$6:$H$400) -> 0 | Q6: =Economy!O6*Paths!T6 -> 0.33978648 | R6: =Economy!O6*Paths!U6 -> 0.18877027 | S6: =Economy!O6*Paths!V6+SUMPRODUCT((Events!$B$6:$B$400<=$A6)*(Events!$C$6:$C$400>=$A6)*(Events!$E$6:$E$400="Programme")*Events!$H$6:$H$400)+SUMPRODUCT((Events!$B$6:$B$400<=$A6)*(Events!$C$6:$C$400>=$A6)*(Events!$E$6:$E$400="Investment")*Events!$H$6:$H$400) -> 0 | T6: =(People!T6*assist_cost+Labour!AD6*talent_cost+Labour!L6*gw_admin)*Economy!H6/1000000 -> 0.01776 | U6: =SUMPRODUCT((Events!$B$6:$B$400<=$A6)*(Events!$C$6:$C$400>=$A6)*(Events!$E$6:$E$400="Purchase")*Events!$H$6:$H$400) -> 0 | V6: =SUMPRODUCT((Events!$B$6:$B$400<=$A6)*(Events!$C$6:$C$400>=$A6)*(Events!$E$6:$E$400="Subsidy & guarantee")*Events!$H$6:$H$400)+SUMPRODUCT((Events!$B$6:$B$400<=$A6)*(Events!$C$6:$C$400>=$A6)*(Events!$E$6:$E$400="Relief")*Events!$H$6:$H$400) -> 0 | W6: =SUMPRODUCT((Events!$B$6:$B$400<=$A6)*(Events!$C$6:$C$400>=$A6)*(Events!$E$6:$E$400="Bank rescue & capital")*Events!$H$6:$H$400) -> 0 | X6: =0 -> 0 | Y6: =SUM(N6:X6) -> 0.80531675 | Z6: =M6-Y6 -> 0.083791213 | AA6: =M6/Economy!O6 -> 0.0471 | AB6: =Y6/Economy!O6 -> 0.042661207 | AC6: =(N6+O6+P6)/Economy!O6 -> 0.013720381
A7: 1847 | B7: =Economy!O7*Paths!N7*Paths!O7*cust_coll -> 0.42079491 | C7: =(Economy!J7+Economy!L7+Economy!M7+Economy!N7)*Paths!P7*Paths!Q7 -> 0.50229704 | D7: =Resources!P7+Resources!Q7 -> 0 | E7: =Paths!S7*(1-canal_opcost)*canal_share -> 0 | F7: =Economy!O7*Paths!R7 -> 0.00039395846 | G7: =SUMPRODUCT((Events!$B$6:$B$400<=$A7)*(Events!$C$6:$C$400>=$A7)*(Events!$E$6:$E$400="Receipt")*Events!$H$6:$H$400)+'Land Fund'!O7 -> 0 | H7: =Loans!Y7 -> 0 | I7: ='Debt & cash'!S6*fund_yield -> 0 | J7: =Labour!Q7 -> 0 | K7: =Champions!BD7 -> 0 | L7: =Abroad!N7 -> 0.00022652432 | M7: =SUM(B7:L7) -> 0.92371243 | N7: =(Paths!W7*army_cost+Paths!X7*res_cost)*Economy!H7/1000000 -> 0.7881 | O7: =Navy!Y7 -> 0 | P7: =SUMPRODUCT((Events!$B$6:$B$400<=$A7)*(Events!$C$6:$C$400>=$A7)*(Events!$E$6:$E$400="War & operations")*Events!$H$6:$H$400) -> 0 | Q7: =Economy!O7*Paths!T7 -> 0.36047199 | R7: =Economy!O7*Paths!U7 -> 0.21273757 | S7: =Economy!O7*Paths!V7+SUMPRODUCT((Events!$B$6:$B$400<=$A7)*(Events!$C$6:$C$400>=$A7)*(Events!$E$6:$E$400="Programme")*Events!$H$6:$H$400)+SUMPRODUCT((Events!$B$6:$B$400<=$A7)*(Events!$C$6:$C$400>=$A7)*(Events!$E$6:$E$400="Investment")*Events!$H$6:$H$400) -> 0.013788546 | T7: =(People!T7*assist_cost+Labour!AD7*talent_cost+Labour!L7*gw_admin)*Economy!H7/1000000 -> 0.02664 | U7: =SUMPRODUCT((Events!$B$6:$B$400<=$A7)*(Events!$C$6:$C$400>=$A7)*(Events!$E$6:$E$400="Purchase")*Events!$H$6:$H$400) -> 0 | V7: =SUMPRODUCT((Events!$B$6:$B$400<=$A7)*(Events!$C$6:$C$400>=$A7)*(Events!$E$6:$E$400="Subsidy & guarantee")*Events!$H$6:$H$400)+SUMPRODUCT((Events!$B$6:$B$400<=$A7)*(Events!$C$6:$C$400>=$A7)*(Events!$E$6:$E$400="Relief")*Events!$H$6:$H$400) -> 0 | W7: =SUMPRODUCT((Events!$B$6:$B$400<=$A7)*(Events!$C$6:$C$400>=$A7)*(Events!$E$6:$E$400="Bank rescue & capital")*Events!$H$6:$H$400) -> 0 | X7: ='Debt & cash'!R6*Paths!Y7 -> 0.0055007138 | Y7: =SUM(N7:X7) -> 1.4072388 | Z7: =M7-Y7 -> -0.48352639 | AA7: =M7/Economy!O7 -> 0.0468939 | AB7: =Y7/Economy!O7 -> 0.071440975 | AC7: =(N7+O7+P7)/Economy!O7 -> 0.040009294
A8: 1848 | B8: =Economy!O8*Paths!N8*Paths!O8*cust_coll -> 0.61200715 | C8: =(Economy!J8+Economy!L8+Economy!M8+Economy!N8)*Paths!P8*Paths!Q8 -> 0.56051306 | D8: =Resources!P8+Resources!Q8 -> 0.45 | E8: =Paths!S8*(1-canal_opcost)*canal_share -> 0 | F8: =Economy!O8*Paths!R8 -> 0.0011592362 | G8: =SUMPRODUCT((Events!$B$6:$B$400<=$A8)*(Events!$C$6:$C$400>=$A8)*(Events!$E$6:$E$400="Receipt")*Events!$H$6:$H$400)+'Land Fund'!O8 -> -0.365 | H8: =Loans!Y8 -> 0 | I8: ='Debt & cash'!S7*fund_yield -> 0 | J8: =Labour!Q8 -> 0 | K8: =Champions!BD8 -> 0 | L8: =Abroad!N8 -> 0.00045610367 | M8: =SUM(B8:L8) -> 1.2591355 | N8: =(Paths!W8*army_cost+Paths!X8*res_cost)*Economy!H8/1000000 -> 0.5402 | O8: =Navy!Y8 -> 0 | P8: =SUMPRODUCT((Events!$B$6:$B$400<=$A8)*(Events!$C$6:$C$400>=$A8)*(Events!$E$6:$E$400="War & operations")*Events!$H$6:$H$400) -> 0 | Q8: =Economy!O8*Paths!T8 -> 0.54194291 | R8: =Economy!O8*Paths!U8 -> 0.33907658 | S8: =Economy!O8*Paths!V8+SUMPRODUCT((Events!$B$6:$B$400<=$A8)*(Events!$C$6:$C$400>=$A8)*(Events!$E$6:$E$400="Programme")*Events!$H$6:$H$400)+SUMPRODUCT((Events!$B$6:$B$400<=$A8)*(Events!$C$6:$C$400>=$A8)*(Events!$E$6:$E$400="Investment")*Events!$H$6:$H$400) -> 0.037675176 | T8: =(People!T8*assist_cost+Labour!AD8*talent_cost+Labour!L8*gw_admin)*Economy!H8/1000000 -> 0.27972 | U8: =SUMPRODUCT((Events!$B$6:$B$400<=$A8)*(Events!$C$6:$C$400>=$A8)*(Events!$E$6:$E$400="Purchase")*Events!$H$6:$H$400) -> 0 | V8: =SUMPRODUCT((Events!$B$6:$B$400<=$A8)*(Events!$C$6:$C$400>=$A8)*(Events!$E$6:$E$400="Subsidy & guarantee")*Events!$H$6:$H$400)+SUMPRODUCT((Events!$B$6:$B$400<=$A8)*(Events!$C$6:$C$400>=$A8)*(Events!$E$6:$E$400="Relief")*Events!$H$6:$H$400) -> 0.1 | W8: =SUMPRODUCT((Events!$B$6:$B$400<=$A8)*(Events!$C$6:$C$400>=$A8)*(Events!$E$6:$E$400="Bank rescue & capital")*Events!$H$6:$H$400) -> 0 | X8: ='Debt & cash'!R7*Paths!Y8 -> 0.036220041 | Y8: =SUM(N8:X8) -> 1.8748347 | Z8: =M8-Y8 -> -0.61569916 | AA8: =M8/Economy!O8 -> 0.043447076 | AB8: =Y8/Economy!O8 -> 0.064692071 | AC8: =(N8+O8+P8)/Economy!O8 -> 0.01863986
A9: 1849 | B9: =Economy!O9*Paths!N9*Paths!O9*cust_coll -> 1.565286 | C9: =(Economy!J9+Economy!L9+Economy!M9+Economy!N9)*Paths!P9*Paths!Q9 -> 2.3952561 | D9: =Resources!P9+Resources!Q9 -> 1.8 | E9: =Paths!S9*(1-canal_opcost)*canal_share -> 0 | F9: =Economy!O9*Paths!R9 -> 0.0044979484 | G9: =SUMPRODUCT((Events!$B$6:$B$400<=$A9)*(Events!$C$6:$C$400>=$A9)*(Events!$E$6:$E$400="Receipt")*Events!$H$6:$H$400)+'Land Fund'!O9 -> 0.975 | H9: =Loans!Y9 -> 0 | I9: ='Debt & cash'!S8*fund_yield -> 0 | J9: =Labour!Q9 -> 0 | K9: =Champions!BD9 -> 0 | L9: =Abroad!N9 -> 0.00079019141 | M9: =SUM(B9:L9) -> 6.7408303 | N9: =(Paths!W9*army_cost+Paths!X9*res_cost)*Economy!H9/1000000 -> 1.0443 | O9: =Navy!Y9 -> 0 | P9: =SUMPRODUCT((Events!$B$6:$B$400<=$A9)*(Events!$C$6:$C$400>=$A9)*(Events!$E$6:$E$400="War & operations")*Events!$H$6:$H$400) -> 0 | Q9: =Economy!O9*Paths!T9 -> 1.4243503 | R9: =Economy!O9*Paths!U9 -> 0.93707258 | S9: =Economy!O9*Paths!V9+SUMPRODUCT((Events!$B$6:$B$400<=$A9)*(Events!$C$6:$C$400>=$A9)*(Events!$E$6:$E$400="Programme")*Events!$H$6:$H$400)+SUMPRODUCT((Events!$B$6:$B$400<=$A9)*(Events!$C$6:$C$400>=$A9)*(Events!$E$6:$E$400="Investment")*Events!$H$6:$H$400) -> 0.14993161 | T9: =(People!T9*assist_cost+Labour!AD9*talent_cost+Labour!L9*gw_admin)*Economy!H9/1000000 -> 1.7930808 | U9: =SUMPRODUCT((Events!$B$6:$B$400<=$A9)*(Events!$C$6:$C$400>=$A9)*(Events!$E$6:$E$400="Purchase")*Events!$H$6:$H$400) -> 0 | V9: =SUMPRODUCT((Events!$B$6:$B$400<=$A9)*(Events!$C$6:$C$400>=$A9)*(Events!$E$6:$E$400="Subsidy & guarantee")*Events!$H$6:$H$400)+SUMPRODUCT((Events!$B$6:$B$400<=$A9)*(Events!$C$6:$C$400>=$A9)*(Events!$E$6:$E$400="Relief")*Events!$H$6:$H$400) -> 0.1 | W9: =SUMPRODUCT((Events!$B$6:$B$400<=$A9)*(Events!$C$6:$C$400>=$A9)*(Events!$E$6:$E$400="Bank rescue & capital")*Events!$H$6:$H$400) -> 0 | X9: ='Debt & cash'!R8*Paths!Y9 -> 0.96795055 | Y9: =SUM(N9:X9) -> 6.4166859 | Z9: =M9-Y9 -> 0.32414443 | AA9: =M9/Economy!O9 -> 0.089918733 | AB9: =Y9/Economy!O9 -> 0.085594836 | AC9: =(N9+O9+P9)/Economy!O9 -> 0.013930351
A10: 1850 | B10: =Economy!O10*Paths!N10*Paths!O10*cust_coll -> 1.8466673 | C10: =(Economy!J10+Economy!L10+Economy!M10+Economy!N10)*Paths!P10*Paths!Q10 -> 3.0987555 | D10: =Resources!P10+Resources!Q10 -> 1.845 | E10: =Paths!S10*(1-canal_opcost)*canal_share -> 0 | F10: =Economy!O10*Paths!R10 -> 0.0071567929 | G10: =SUMPRODUCT((Events!$B$6:$B$400<=$A10)*(Events!$C$6:$C$400>=$A10)*(Events!$E$6:$E$400="Receipt")*Events!$H$6:$H$400)+'Land Fund'!O10 -> 0.975 | H10: =Loans!Y10 -> 0 | I10: ='Debt & cash'!S9*fund_yield -> 0 | J10: =Labour!Q10 -> 0 | K10: =Champions!BD10 -> 0 | L10: =Abroad!N10 -> 0.0016660753 | M10: =SUM(B10:L10) -> 7.7742456 | N10: =(Paths!W10*army_cost+Paths!X10*res_cost)*Economy!H10/1000000 -> 1.221 | O10: =Navy!Y10 -> 0 | P10: =SUMPRODUCT((Events!$B$6:$B$400<=$A10)*(Events!$C$6:$C$400>=$A10)*(Events!$E$6:$E$400="War & operations")*Events!$H$6:$H$400) -> 0 | Q10: =Economy!O10*Paths!T10 -> 1.7265763 | R10: =Economy!O10*Paths!U10 -> 1.1898168 | S10: =Economy!O10*Paths!V10+SUMPRODUCT((Events!$B$6:$B$400<=$A10)*(Events!$C$6:$C$400>=$A10)*(Events!$E$6:$E$400="Programme")*Events!$H$6:$H$400)+SUMPRODUCT((Events!$B$6:$B$400<=$A10)*(Events!$C$6:$C$400>=$A10)*(Events!$E$6:$E$400="Investment")*Events!$H$6:$H$400) -> 0.74154176 | T10: =(People!T10*assist_cost+Labour!AD10*talent_cost+Labour!L10*gw_admin)*Economy!H10/1000000 -> 1.49688 | U10: =SUMPRODUCT((Events!$B$6:$B$400<=$A10)*(Events!$C$6:$C$400>=$A10)*(Events!$E$6:$E$400="Purchase")*Events!$H$6:$H$400) -> 0 | V10: =SUMPRODUCT((Events!$B$6:$B$400<=$A10)*(Events!$C$6:$C$400>=$A10)*(Events!$E$6:$E$400="Subsidy & guarantee")*Events!$H$6:$H$400)+SUMPRODUCT((Events!$B$6:$B$400<=$A10)*(Events!$C$6:$C$400>=$A10)*(Events!$E$6:$E$400="Relief")*Events!$H$6:$H$400) -> 0.1 | W10: =SUMPRODUCT((Events!$B$6:$B$400<=$A10)*(Events!$C$6:$C$400>=$A10)*(Events!$E$6:$E$400="Bank rescue & capital")*Events!$H$6:$H$400) -> 0 | X10: ='Debt & cash'!R9*Paths!Y10 -> 1.0392331 | Y10: =SUM(N10:X10) -> 7.515048 | Z10: =M10-Y10 -> 0.25919762 | AA10: =M10/Economy!O10 -> 0.086902005 | AB10: =Y10/Economy!O10 -> 0.084004644 | AC10: =(N10+O10+P10)/Economy!O10 -> 0.013648572
A11: 1851 | B11: =Economy!O11*Paths!N11*Paths!O11*cust_coll -> 2.5294337 | C11: =(Economy!J11+Economy!L11+Economy!M11+Economy!N11)*Paths!P11*Paths!Q11 -> 3.6468283 | D11: =Resources!P11+Resources!Q11 -> 3.375 | E11: =Paths!S11*(1-canal_opcost)*canal_share -> 0 | F11: =Economy!O11*Paths!R11 -> 0.012400644 | G11: =SUMPRODUCT((Events!$B$6:$B$400<=$A11)*(Events!$C$6:$C$400>=$A11)*(Events!$E$6:$E$400="Receipt")*Events!$H$6:$H$400)+'Land Fund'!O11 -> 0.975 | H11: =Loans!Y11 -> 0 | I11: ='Debt & cash'!S10*fund_yield -> 0 | J11: =Labour!Q11 -> 0 | K11: =Champions!BD11 -> 0 | L11: =Abroad!N11 -> 0.002689612 | M11: =SUM(B11:L11) -> 10.541352 | N11: =(Paths!W11*army_cost+Paths!X11*res_cost)*Economy!H11/1000000 -> 1.6626 | O11: =Navy!Y11 -> 0.21 | P11: =SUMPRODUCT((Events!$B$6:$B$400<=$A11)*(Events!$C$6:$C$400>=$A11)*(Events!$E$6:$E$400="War & operations")*Events!$H$6:$H$400) -> 0 | Q11: =Economy!O11*Paths!T11 -> 2.4429268 | R11: =Economy!O11*Paths!U11 -> 1.7608914 | S11: =Economy!O11*Paths!V11+SUMPRODUCT((Events!$B$6:$B$400<=$A11)*(Events!$C$6:$C$400>=$A11)*(Events!$E$6:$E$400="Programme")*Events!$H$6:$H$400)+SUMPRODUCT((Events!$B$6:$B$400<=$A11)*(Events!$C$6:$C$400>=$A11)*(Events!$E$6:$E$400="Investment")*Events!$H$6:$H$400) -> 0.90922124 | T11: =(People!T11*assist_cost+Labour!AD11*talent_cost+Labour!L11*gw_admin)*Economy!H11/1000000 -> 1.105272 | U11: =SUMPRODUCT((Events!$B$6:$B$400<=$A11)*(Events!$C$6:$C$400>=$A11)*(Events!$E$6:$E$400="Purchase")*Events!$H$6:$H$400) -> 0 | V11: =SUMPRODUCT((Events!$B$6:$B$400<=$A11)*(Events!$C$6:$C$400>=$A11)*(Events!$E$6:$E$400="Subsidy & guarantee")*Events!$H$6:$H$400)+SUMPRODUCT((Events!$B$6:$B$400<=$A11)*(Events!$C$6:$C$400>=$A11)*(Events!$E$6:$E$400="Relief")*Events!$H$6:$H$400) -> 0 | W11: =SUMPRODUCT((Events!$B$6:$B$400<=$A11)*(Events!$C$6:$C$400>=$A11)*(Events!$E$6:$E$400="Bank rescue & capital")*Events!$H$6:$H$400) -> 0 | X11: ='Debt & cash'!R10*Paths!Y11 -> 1.0432265 | Y11: =SUM(N11:X11) -> 9.1341379 | Z11: =M11-Y11 -> 1.4072143 | AA11: =M11/Economy!O11 -> 0.085006492 | AB11: =Y11/Economy!O11 -> 0.073658579 | AC11: =(N11+O11+P11)/Economy!O11 -> 0.015100829
A12: 1852 | B12: =Economy!O12*Paths!N12*Paths!O12*cust_coll -> 4.4153786 | C12: =(Economy!J12+Economy!L12+Economy!M12+Economy!N12)*Paths!P12*Paths!Q12 -> 5.6935889 | D12: =Resources!P12+Resources!Q12 -> 3.645 | E12: =Paths!S12*(1-canal_opcost)*canal_share -> 0 | F12: =Economy!O12*Paths!R12 -> 0.018981456 | G12: =SUMPRODUCT((Events!$B$6:$B$400<=$A12)*(Events!$C$6:$C$400>=$A12)*(Events!$E$6:$E$400="Receipt")*Events!$H$6:$H$400)+'Land Fund'!O12 -> 0.61582704 | H12: =Loans!Y12 -> 0 | I12: ='Debt & cash'!S11*fund_yield -> 0.003000561 | J12: =Labour!Q12 -> 0 | K12: =Champions!BD12 -> 0 | L12: =Abroad!N12 -> 0.0040970009 | M12: =SUM(B12:L12) -> 14.395874 | N12: =(Paths!W12*army_cost+Paths!X12*res_cost)*Economy!H12/1000000 -> 2.205 | O12: =Navy!Y12 -> 0.5504 | P12: =SUMPRODUCT((Events!$B$6:$B$400<=$A12)*(Events!$C$6:$C$400>=$A12)*(Events!$E$6:$E$400="War & operations")*Events!$H$6:$H$400) -> 0 | Q12: =Economy!O12*Paths!T12 -> 2.920224 | R12: =Economy!O12*Paths!U12 -> 2.190168 | S12: =Economy!O12*Paths!V12+SUMPRODUCT((Events!$B$6:$B$400<=$A12)*(Events!$C$6:$C$400>=$A12)*(Events!$E$6:$E$400="Programme")*Events!$H$6:$H$400)+SUMPRODUCT((Events!$B$6:$B$400<=$A12)*(Events!$C$6:$C$400>=$A12)*(Events!$E$6:$E$400="Investment")*Events!$H$6:$H$400) -> 0.58404479 | T12: =(People!T12*assist_cost+Labour!AD12*talent_cost+Labour!L12*gw_admin)*Economy!H12/1000000 -> 3.78 | U12: =SUMPRODUCT((Events!$B$6:$B$400<=$A12)*(Events!$C$6:$C$400>=$A12)*(Events!$E$6:$E$400="Purchase")*Events!$H$6:$H$400) -> 0 | V12: =SUMPRODUCT((Events!$B$6:$B$400<=$A12)*(Events!$C$6:$C$400>=$A12)*(Events!$E$6:$E$400="Subsidy & guarantee")*Events!$H$6:$H$400)+SUMPRODUCT((Events!$B$6:$B$400<=$A12)*(Events!$C$6:$C$400>=$A12)*(Events!$E$6:$E$400="Relief")*Events!$H$6:$H$400) -> 0 | W12: =SUMPRODUCT((Events!$B$6:$B$400<=$A12)*(Events!$C$6:$C$400>=$A12)*(Events!$E$6:$E$400="Bank rescue & capital")*Events!$H$6:$H$400) -> 0 | X12: ='Debt & cash'!R11*Paths!Y12 -> 1.0088819 | Y12: =SUM(N12:X12) -> 13.238719 | Z12: =M12-Y12 -> 1.157155 | AA12: =M12/Economy!O12 -> 0.098594312 | AB12: =Y12/Economy!O12 -> 0.090669201 | AC12: =(N12+O12+P12)/Economy!O12 -> 0.018871155
A13: 1853 | B13: =Economy!O13*Paths!N13*Paths!O13*cust_coll -> 4.7132458 | C13: =(Economy!J13+Economy!L13+Economy!M13+Economy!N13)*Paths!P13*Paths!Q13 -> 7.0069783 | D13: =Resources!P13+Resources!Q13 -> 3.015 | E13: =Paths!S13*(1-canal_opcost)*canal_share -> 0 | F13: =Economy!O13*Paths!R13 -> 0.023522008 | G13: =SUMPRODUCT((Events!$B$6:$B$400<=$A13)*(Events!$C$6:$C$400>=$A13)*(Events!$E$6:$E$400="Receipt")*Events!$H$6:$H$400)+'Land Fund'!O13 -> 0.61989544 | H13: =Loans!Y13 -> 0 | I13: ='Debt & cash'!S12*fund_yield -> 0 | J13: =Labour!Q13 -> 0 | K13: =Champions!BD13 -> 0 | L13: =Abroad!N13 -> 0.0057262252 | M13: =SUM(B13:L13) -> 15.384368 | N13: =(Paths!W13*army_cost+Paths!X13*res_cost)*Economy!H13/1000000 -> 2.6829 | O13: =Navy!Y13 -> 0.3378125 | P13: =SUMPRODUCT((Events!$B$6:$B$400<=$A13)*(Events!$C$6:$C$400>=$A13)*(Events!$E$6:$E$400="War & operations")*Events!$H$6:$H$400) -> 0.3 | Q13: =Economy!O13*Paths!T13 -> 3.1676304 | R13: =Economy!O13*Paths!U13 -> 2.4776515 | S13: =Economy!O13*Paths!V13+SUMPRODUCT((Events!$B$6:$B$400<=$A13)*(Events!$C$6:$C$400>=$A13)*(Events!$E$6:$E$400="Programme")*Events!$H$6:$H$400)+SUMPRODUCT((Events!$B$6:$B$400<=$A13)*(Events!$C$6:$C$400>=$A13)*(Events!$E$6:$E$400="Investment")*Events!$H$6:$H$400) -> 0.70566024 | T13: =(People!T13*assist_cost+Labour!AD13*talent_cost+Labour!L13*gw_admin)*Economy!H13/1000000 -> 2.295216 | U13: =SUMPRODUCT((Events!$B$6:$B$400<=$A13)*(Events!$C$6:$C$400>=$A13)*(Events!$E$6:$E$400="Purchase")*Events!$H$6:$H$400) -> 0 | V13: =SUMPRODUCT((Events!$B$6:$B$400<=$A13)*(Events!$C$6:$C$400>=$A13)*(Events!$E$6:$E$400="Subsidy & guarantee")*Events!$H$6:$H$400)+SUMPRODUCT((Events!$B$6:$B$400<=$A13)*(Events!$C$6:$C$400>=$A13)*(Events!$E$6:$E$400="Relief")*Events!$H$6:$H$400) -> 0 | W13: =SUMPRODUCT((Events!$B$6:$B$400<=$A13)*(Events!$C$6:$C$400>=$A13)*(Events!$E$6:$E$400="Bank rescue & capital")*Events!$H$6:$H$400) -> 0 | X13: ='Debt & cash'!R12*Paths!Y13 -> 0.9956746 | Y13: =SUM(N13:X13) -> 12.962545 | Z13: =M13-Y13 -> 2.4218226 | AA13: =M13/Economy!O13 -> 0.098106216 | AB13: =Y13/Economy!O13 -> 0.082662237 | AC13: =(N13+O13+P13)/Economy!O13 -> 0.021176206
A14: 1854 | B14: =Economy!O14*Paths!N14*Paths!O14*cust_coll -> 5.2151181 | C14: =(Economy!J14+Economy!L14+Economy!M14+Economy!N14)*Paths!P14*Paths!Q14 -> 8.046167 | D14: =Resources!P14+Resources!Q14 -> 3.105 | E14: =Paths!S14*(1-canal_opcost)*canal_share -> 0 | F14: =Economy!O14*Paths!R14 -> 0.029667445 | G14: =SUMPRODUCT((Events!$B$6:$B$400<=$A14)*(Events!$C$6:$C$400>=$A14)*(Events!$E$6:$E$400="Receipt")*Events!$H$6:$H$400)+'Land Fund'!O14 -> 0.62803223 | H14: =Loans!Y14 -> 0 | I14: ='Debt & cash'!S13*fund_yield -> 0.014819794 | J14: =Labour!Q14 -> 0 | K14: =Champions!BD14 -> 0 | L14: =Abroad!N14 -> 0.0074361991 | M14: =SUM(B14:L14) -> 17.046241 | N14: =(Paths!W14*army_cost+Paths!X14*res_cost)*Economy!H14/1000000 -> 3.05065 | O14: =Navy!Y14 -> 0.5570625 | P14: =SUMPRODUCT((Events!$B$6:$B$400<=$A14)*(Events!$C$6:$C$400>=$A14)*(Events!$E$6:$E$400="War & operations")*Events!$H$6:$H$400) -> 0.3 | Q14: =Economy!O14*Paths!T14 -> 3.542642 | R14: =Economy!O14*Paths!U14 -> 2.8794873 | S14: =Economy!O14*Paths!V14+SUMPRODUCT((Events!$B$6:$B$400<=$A14)*(Events!$C$6:$C$400>=$A14)*(Events!$E$6:$E$400="Programme")*Events!$H$6:$H$400)+SUMPRODUCT((Events!$B$6:$B$400<=$A14)*(Events!$C$6:$C$400>=$A14)*(Events!$E$6:$E$400="Investment")*Events!$H$6:$H$400) -> 0.87257192 | T14: =(People!T14*assist_cost+Labour!AD14*talent_cost+Labour!L14*gw_admin)*Economy!H14/1000000 -> 2.004408 | U14: =SUMPRODUCT((Events!$B$6:$B$400<=$A14)*(Events!$C$6:$C$400>=$A14)*(Events!$E$6:$E$400="Purchase")*Events!$H$6:$H$400) -> 0 | V14: =SUMPRODUCT((Events!$B$6:$B$400<=$A14)*(Events!$C$6:$C$400>=$A14)*(Events!$E$6:$E$400="Subsidy & guarantee")*Events!$H$6:$H$400)+SUMPRODUCT((Events!$B$6:$B$400<=$A14)*(Events!$C$6:$C$400>=$A14)*(Events!$E$6:$E$400="Relief")*Events!$H$6:$H$400) -> 0 | W14: =SUMPRODUCT((Events!$B$6:$B$400<=$A14)*(Events!$C$6:$C$400>=$A14)*(Events!$E$6:$E$400="Bank rescue & capital")*Events!$H$6:$H$400) -> 0 | X14: ='Debt & cash'!R13*Paths!Y14 -> 0.88846689 | Y14: =SUM(N14:X14) -> 14.095289 | Z14: =M14-Y14 -> 2.9509521 | AA14: =M14/Economy!O14 -> 0.097678142 | AB14: =Y14/Economy!O14 -> 0.080768635 | AC14: =(N14+O14+P14)/Economy!O14 -> 0.022391922
A15: 1855 | B15: =Economy!O15*Paths!N15*Paths!O15*cust_coll -> 5.3640852 | C15: =(Economy!J15+Economy!L15+Economy!M15+Economy!N15)*Paths!P15*Paths!Q15 -> 10.26737 | D15: =Resources!P15+Resources!Q15 -> 2.475 | E15: =Paths!S15*(1-canal_opcost)*canal_share -> 0 | F15: =Economy!O15*Paths!R15 -> 0.034315697 | G15: =SUMPRODUCT((Events!$B$6:$B$400<=$A15)*(Events!$C$6:$C$400>=$A15)*(Events!$E$6:$E$400="Receipt")*Events!$H$6:$H$400)+'Land Fund'!O15 -> 0.63616903 | H15: =Loans!Y15 -> 0 | I15: ='Debt & cash'!S14*fund_yield -> 0.032814539 | J15: =Labour!Q15 -> 0 | K15: =Champions!BD15 -> 0 | L15: =Abroad!N15 -> 0.0093072858 | M15: =SUM(B15:L15) -> 18.819062 | N15: =(Paths!W15*army_cost+Paths!X15*res_cost)*Economy!H15/1000000 -> 3.4675 | O15: =Navy!Y15 -> 0.877625 | P15: =SUMPRODUCT((Events!$B$6:$B$400<=$A15)*(Events!$C$6:$C$400>=$A15)*(Events!$E$6:$E$400="War & operations")*Events!$H$6:$H$400) -> 0 | Q15: =Economy!O15*Paths!T15 -> 3.7024831 | R15: =Economy!O15*Paths!U15 -> 3.1064736 | S15: =Economy!O15*Paths!V15+SUMPRODUCT((Events!$B$6:$B$400<=$A15)*(Events!$C$6:$C$400>=$A15)*(Events!$E$6:$E$400="Programme")*Events!$H$6:$H$400)+SUMPRODUCT((Events!$B$6:$B$400<=$A15)*(Events!$C$6:$C$400>=$A15)*(Events!$E$6:$E$400="Investment")*Events!$H$6:$H$400) -> 1.3933491 | T15: =(People!T15*assist_cost+Labour!AD15*talent_cost+Labour!L15*gw_admin)*Economy!H15/1000000 -> 1.72368 | U15: =SUMPRODUCT((Events!$B$6:$B$400<=$A15)*(Events!$C$6:$C$400>=$A15)*(Events!$E$6:$E$400="Purchase")*Events!$H$6:$H$400) -> 0 | V15: =SUMPRODUCT((Events!$B$6:$B$400<=$A15)*(Events!$C$6:$C$400>=$A15)*(Events!$E$6:$E$400="Subsidy & guarantee")*Events!$H$6:$H$400)+SUMPRODUCT((Events!$B$6:$B$400<=$A15)*(Events!$C$6:$C$400>=$A15)*(Events!$E$6:$E$400="Relief")*Events!$H$6:$H$400) -> 0 | W15: =SUMPRODUCT((Events!$B$6:$B$400<=$A15)*(Events!$C$6:$C$400>=$A15)*(Events!$E$6:$E$400="Bank rescue & capital")*Events!$H$6:$H$400) -> 0 | X15: ='Debt & cash'!R14*Paths!Y15 -> 0.76261661 | Y15: =SUM(N15:X15) -> 15.033727 | Z15: =M15-Y15 -> 3.7853346 | AA15: =M15/Economy!O15 -> 0.10419785 | AB15: =Y15/Economy!O15 -> 0.083239114 | AC15: =(N15+O15+P15)/Economy!O15 -> 0.024058196
A16: 1856 | B16: =Economy!O16*Paths!N16*Paths!O16*cust_coll -> 6.0617343 | C16: =(Economy!J16+Economy!L16+Economy!M16+Economy!N16)*Paths!P16*Paths!Q16 -> 11.955088 | D16: =Resources!P16+Resources!Q16 -> 2.565 | E16: =Paths!S16*(1-canal_opcost)*canal_share -> 0 | F16: =Economy!O16*Paths!R16 -> 0.043127353 | G16: =SUMPRODUCT((Events!$B$6:$B$400<=$A16)*(Events!$C$6:$C$400>=$A16)*(Events!$E$6:$E$400="Receipt")*Events!$H$6:$H$400)+'Land Fund'!O16 -> 0.63638266 | H16: =Loans!Y16 -> 0 | I16: ='Debt & cash'!S15*fund_yield -> 0.057596147 | J16: =Labour!Q16 -> 0 | K16: =Champions!BD16 -> 0 | L16: =Abroad!N16 -> 0.011195374 | M16: =SUM(B16:L16) -> 21.330124 | N16: =(Paths!W16*army_cost+Paths!X16*res_cost)*Economy!H16/1000000 -> 4.445925 | O16: =Navy!Y16 -> 0.6442875 | P16: =SUMPRODUCT((Events!$B$6:$B$400<=$A16)*(Events!$C$6:$C$400>=$A16)*(Events!$E$6:$E$400="War & operations")*Events!$H$6:$H$400) -> 0 | Q16: =Economy!O16*Paths!T16 -> 4.230588 | R16: =Economy!O16*Paths!U16 -> 3.6966303 | S16: =Economy!O16*Paths!V16+SUMPRODUCT((Events!$B$6:$B$400<=$A16)*(Events!$C$6:$C$400>=$A16)*(Events!$E$6:$E$400="Programme")*Events!$H$6:$H$400)+SUMPRODUCT((Events!$B$6:$B$400<=$A16)*(Events!$C$6:$C$400>=$A16)*(Events!$E$6:$E$400="Investment")*Events!$H$6:$H$400) -> 1.6322101 | T16: =(People!T16*assist_cost+Labour!AD16*talent_cost+Labour!L16*gw_admin)*Economy!H16/1000000 -> 2.5187888 | U16: =SUMPRODUCT((Events!$B$6:$B$400<=$A16)*(Events!$C$6:$C$400>=$A16)*(Events!$E$6:$E$400="Purchase")*Events!$H$6:$H$400) -> 0 | V16: =SUMPRODUCT((Events!$B$6:$B$400<=$A16)*(Events!$C$6:$C$400>=$A16)*(Events!$E$6:$E$400="Subsidy & guarantee")*Events!$H$6:$H$400)+SUMPRODUCT((Events!$B$6:$B$400<=$A16)*(Events!$C$6:$C$400>=$A16)*(Events!$E$6:$E$400="Relief")*Events!$H$6:$H$400) -> 0 | W16: =SUMPRODUCT((Events!$B$6:$B$400<=$A16)*(Events!$C$6:$C$400>=$A16)*(Events!$E$6:$E$400="Bank rescue & capital")*Events!$H$6:$H$400) -> 0 | X16: ='Debt & cash'!R15*Paths!Y16 -> 0.59462681 | Y16: =SUM(N16:X16) -> 17.763056 | Z16: =M16-Y16 -> 3.5670676 | AA16: =M16/Economy!O16 -> 0.10386276 | AB16: =Y16/Economy!O16 -> 0.086493642 | AC16: =(N16+O16+P16)/Economy!O16 -> 0.024785769
A17: 1857 | B17: =Economy!O17*Paths!N17*Paths!O17*cust_coll -> 6.3705292 | C17: =(Economy!J17+Economy!L17+Economy!M17+Economy!N17)*Paths!P17*Paths!Q17 -> 13.510833 | D17: =Resources!P17+Resources!Q17 -> 1.935 | E17: =Paths!S17*(1-canal_opcost)*canal_share -> 0 | F17: =Economy!O17*Paths!R17 -> 0.049933264 | G17: =SUMPRODUCT((Events!$B$6:$B$400<=$A17)*(Events!$C$6:$C$400>=$A17)*(Events!$E$6:$E$400="Receipt")*Events!$H$6:$H$400)+'Land Fund'!O17 -> 0.63896766 | H17: =Loans!Y17 -> 0 | I17: ='Debt & cash'!S16*fund_yield -> 0.07959075 | J17: =Labour!Q17 -> 0 | K17: =Champions!BD17 -> 0 | L17: =Abroad!N17 -> 0.013323933 | M17: =SUM(B17:L17) -> 22.598178 | N17: =(Paths!W17*army_cost+Paths!X17*res_cost)*Economy!H17/1000000 -> 5.4694 | O17: =Navy!Y17 -> 0.87595 | P17: =SUMPRODUCT((Events!$B$6:$B$400<=$A17)*(Events!$C$6:$C$400>=$A17)*(Events!$E$6:$E$400="War & operations")*Events!$H$6:$H$400) -> 0.3 | Q17: =Economy!O17*Paths!T17 -> 4.5157039 | R17: =Economy!O17*Paths!U17 -> 3.9295308 | S17: =Economy!O17*Paths!V17+SUMPRODUCT((Events!$B$6:$B$400<=$A17)*(Events!$C$6:$C$400>=$A17)*(Events!$E$6:$E$400="Programme")*Events!$H$6:$H$400)+SUMPRODUCT((Events!$B$6:$B$400<=$A17)*(Events!$C$6:$C$400>=$A17)*(Events!$E$6:$E$400="Investment")*Events!$H$6:$H$400) -> 1.724317 | T17: =(People!T17*assist_cost+Labour!AD17*talent_cost+Labour!L17*gw_admin)*Economy!H17/1000000 -> 2.6457281 | U17: =SUMPRODUCT((Events!$B$6:$B$400<=$A17)*(Events!$C$6:$C$400>=$A17)*(Events!$E$6:$E$400="Purchase")*Events!$H$6:$H$400) -> 0 | V17: =SUMPRODUCT((Events!$B$6:$B$400<=$A17)*(Events!$C$6:$C$400>=$A17)*(Events!$E$6:$E$400="Subsidy & guarantee")*Events!$H$6:$H$400)+SUMPRODUCT((Events!$B$6:$B$400<=$A17)*(Events!$C$6:$C$400>=$A17)*(Events!$E$6:$E$400="Relief")*Events!$H$6:$H$400) -> 0 | W17: =SUMPRODUCT((Events!$B$6:$B$400<=$A17)*(Events!$C$6:$C$400>=$A17)*(Events!$E$6:$E$400="Bank rescue & capital")*Events!$H$6:$H$400) -> 0 | X17: ='Debt & cash'!R16*Paths!Y17 -> 0.44718087 | Y17: =SUM(N17:X17) -> 19.907811 | Z17: =M17-Y17 -> 2.6903671 | AA17: =M17/Economy!O17 -> 0.10409055 | AB17: =Y17/Economy!O17 -> 0.091698321 | AC17: =(N17+O17+P17)/Economy!O17 -> 0.030609465
A18: 1858 | B18: =Economy!O18*Paths!N18*Paths!O18*cust_coll -> 7.0848918 | C18: =(Economy!J18+Economy!L18+Economy!M18+Economy!N18)*Paths!P18*Paths!Q18 -> 15.177277 | D18: =Resources!P18+Resources!Q18 -> 2.115 | E18: =Paths!S18*(1-canal_opcost)*canal_share -> 0 | F18: =Economy!O18*Paths!R18 -> 0.060741528 | G18: =SUMPRODUCT((Events!$B$6:$B$400<=$A18)*(Events!$C$6:$C$400>=$A18)*(Events!$E$6:$E$400="Receipt")*Events!$H$6:$H$400)+'Land Fund'!O18 -> 0.59525462 | H18: =Loans!Y18 -> 0 | I18: ='Debt & cash'!S17*fund_yield -> 0.097440077 | J18: =Labour!Q18 -> 0 | K18: =Champions!BD18 -> 0 | L18: =Abroad!N18 -> 0.015529429 | M18: =SUM(B18:L18) -> 25.146134 | N18: =(Paths!W18*army_cost+Paths!X18*res_cost)*Economy!H18/1000000 -> 6.392235 | O18: =Navy!Y18 -> 1.1830316 | P18: =SUMPRODUCT((Events!$B$6:$B$400<=$A18)*(Events!$C$6:$C$400>=$A18)*(Events!$E$6:$E$400="War & operations")*Events!$H$6:$H$400) -> 0.3 | Q18: =Economy!O18*Paths!T18 -> 5.0779917 | R18: =Economy!O18*Paths!U18 -> 4.4219832 | S18: =Economy!O18*Paths!V18+SUMPRODUCT((Events!$B$6:$B$400<=$A18)*(Events!$C$6:$C$400>=$A18)*(Events!$E$6:$E$400="Programme")*Events!$H$6:$H$400)+SUMPRODUCT((Events!$B$6:$B$400<=$A18)*(Events!$C$6:$C$400>=$A18)*(Events!$E$6:$E$400="Investment")*Events!$H$6:$H$400) -> 1.9063899 | T18: =(People!T18*assist_cost+Labour!AD18*talent_cost+Labour!L18*gw_admin)*Economy!H18/1000000 -> 2.6987088 | U18: =SUMPRODUCT((Events!$B$6:$B$400<=$A18)*(Events!$C$6:$C$400>=$A18)*(Events!$E$6:$E$400="Purchase")*Events!$H$6:$H$400) -> 0 | V18: =SUMPRODUCT((Events!$B$6:$B$400<=$A18)*(Events!$C$6:$C$400>=$A18)*(Events!$E$6:$E$400="Subsidy & guarantee")*Events!$H$6:$H$400)+SUMPRODUCT((Events!$B$6:$B$400<=$A18)*(Events!$C$6:$C$400>=$A18)*(Events!$E$6:$E$400="Relief")*Events!$H$6:$H$400) -> 0 | W18: =SUMPRODUCT((Events!$B$6:$B$400<=$A18)*(Events!$C$6:$C$400>=$A18)*(Events!$E$6:$E$400="Bank rescue & capital")*Events!$H$6:$H$400) -> 0 | X18: ='Debt & cash'!R17*Paths!Y18 -> 0.32751967 | Y18: =SUM(N18:X18) -> 22.30786 | Z18: =M18-Y18 -> 2.838274 | AA18: =M18/Economy!O18 -> 0.10349647 | AB18: =Y18/Economy!O18 -> 0.091814697 | AC18: =(N18+O18+P18)/Economy!O18 -> 0.032413025
... A92: 1932 | B92: =Economy!O92*Paths!N92*Paths!O92*cust_coll -> 770.03951 | C92: =(Economy!J92+Economy!L92+Economy!M92+Economy!N92)*Paths!P92*Paths!Q92 -> 3719.1902 | D92: =Resources!P92+Resources!Q92 -> 21.40875 | E92: =Paths!S92*(1-canal_opcost)*canal_share -> 13.2 | F92: =Economy!O92*Paths!R92 -> 109.69224 | G92: =SUMPRODUCT((Events!$B$6:$B$400<=$A92)*(Events!$C$6:$C$400>=$A92)*(Events!$E$6:$E$400="Receipt")*Events!$H$6:$H$400)+'Land Fund'!O92 -> 30.490849 | H92: =Loans!Y92 -> 24.330592 | I92: ='Debt & cash'!S91*fund_yield -> 53.017775 | J92: =Labour!Q92 -> 334.03131 | K92: =Champions!BD92 -> 104.66775 | L92: =Abroad!N92 -> 149.97244 | M92: =SUM(B92:L92) -> 5330.0415 | N92: =(Paths!W92*army_cost+Paths!X92*res_cost)*Economy!H92/1000000 -> 44.8644 | O92: =Navy!Y92 -> 163.22577 | P92: =SUMPRODUCT((Events!$B$6:$B$400<=$A92)*(Events!$C$6:$C$400>=$A92)*(Events!$E$6:$E$400="War & operations")*Events!$H$6:$H$400) -> 7.5265789 | Q92: =Economy!O92*Paths!T92 -> 2577.7676 | R92: =Economy!O92*Paths!U92 -> 1425.9991 | S92: =Economy!O92*Paths!V92+SUMPRODUCT((Events!$B$6:$B$400<=$A92)*(Events!$C$6:$C$400>=$A92)*(Events!$E$6:$E$400="Programme")*Events!$H$6:$H$400)+SUMPRODUCT((Events!$B$6:$B$400<=$A92)*(Events!$C$6:$C$400>=$A92)*(Events!$E$6:$E$400="Investment")*Events!$H$6:$H$400) -> 475.84895 | T92: =(People!T92*assist_cost+Labour!AD92*talent_cost+Labour!L92*gw_admin)*Economy!H92/1000000 -> 77.786042 | U92: =SUMPRODUCT((Events!$B$6:$B$400<=$A92)*(Events!$C$6:$C$400>=$A92)*(Events!$E$6:$E$400="Purchase")*Events!$H$6:$H$400) -> 0 | V92: =SUMPRODUCT((Events!$B$6:$B$400<=$A92)*(Events!$C$6:$C$400>=$A92)*(Events!$E$6:$E$400="Subsidy & guarantee")*Events!$H$6:$H$400)+SUMPRODUCT((Events!$B$6:$B$400<=$A92)*(Events!$C$6:$C$400>=$A92)*(Events!$E$6:$E$400="Relief")*Events!$H$6:$H$400) -> 0.55 | W92: =SUMPRODUCT((Events!$B$6:$B$400<=$A92)*(Events!$C$6:$C$400>=$A92)*(Events!$E$6:$E$400="Bank rescue & capital")*Events!$H$6:$H$400) -> 75 | X92: ='Debt & cash'!R91*Paths!Y92 -> 152.80775 | Y92: =SUM(N92:X92) -> 5001.3762 | Z92: =M92-Y92 -> 328.66527 | AA92: =M92/Economy!O92 -> 0.097181743 | AB92: =Y92/Economy!O92 -> 0.091189245 | AC92: =(N92+O92+P92)/Economy!O92 -> 0.0039313037

Sheet Land Fund
A1: Land Fund
A2: CR-033 (draft): the Republic buys Native land by treaty for annuities in goods, sells it to settlers on instalments, takes grant land as the price of fast patents, and keeps a fee on homeland leases. Does it pay for itself? Inputs are on Levers (lfund_*); the farm-land path is our timeline's census.
A3: Years run down the page. Blue = input · black = formula · green = link. $m in period money. Net cash to the Treasury feeds Budget column G. Police and commissioners are the wider policy's cost (A7).
A4: Inputs | B4: Purchases | I4: Receipts | M4: Results
A5: Year | B5: Land in farms, our timeline (acres) | C5: Farm land needing purchase (acres) | D5: Bought from the nations, to date (acres) | E5: Bought this year (acres) | F5: Annuities paid in goods ($m) | G5: Old grants patented this year (acres) | H5: Survey and register ($m) | I5: Sold to settlers, to date (acres) | J5: Instalments received ($m) | K5: Grant land paid in and sold ($m) | L5: Homeland lease fees ($m) | M5: Land Fund net ($m) | N5: Commissioners and mounted police ($m) | O5: Net cash to the Treasury ($m) | P5: Land Fund balance with interest ($m) | Q5: Policy balance with interest, incl. police ($m) | R5: Assisted passage ($m) | S5: Land Fund net / assisted passage, to date | T5: Farm land and buildings, average value, our timeline ($ an acre) | U5: Sale price ($ an acre) | V5: Value of land sold this year ($m) | W5: Value of land sold, to date ($m) | Y5: Summary
A6: 1846 | B6: 3893985 | C6: =MAX(0,B6*lfund_farm_scale-lfund_grants) -> 0 | D6: =IF(AND(lfund_on=1,$A6>=lfund_start),MIN(lfund_area-lfund_home-lfund_grants,INDEX($C$6:$C$92,MIN(87,1+lfund_lead))),0) -> 0 | E6: =D6 -> 0 | F6: =lfund_price/lfund_term*(D6-IF(6-lfund_term<6,0,INDEX($D$6:$D$92,6-5-lfund_term)))/1000000 -> 0 | G6: =IF(AND(lfund_on=1,$A6>=lfund_start+1,$A6<lfund_start+1+lfund_grant_years),lfund_grants/lfund_grant_years,0) -> 0 | H6: =(E6+G6)*lfund_survey/1000000 -> 0 | I6: =IF(AND(lfund_on=1,$A6>=lfund_start),MIN(D6,C6),0) -> 0 | J6: =(W6-IF(6-lfund_inst<6,0,INDEX($W$6:$W$92,6-5-lfund_inst)))/lfund_inst*(1-lfund_default) -> 0 | K6: =G6*lfund_grant_fee*U6/1000000 -> 0 | L6: =IF(AND(lfund_on=1,$A6>=1860),lfund_home*lfund_lease_1932*($A6-1859)/(1932-1859)*lfund_rent*lfund_fee,0)/1000000 -> 0 | M6: =J6+K6+L6-F6-H6 -> 0 | N6: =IF(lfund_on=1,IF(AND($A6>=1852,$A6<=1870),lfund_police,IF(AND($A6>1870,$A6<=1890),lfund_police_late,0))*lfund_police_cost*Economy!H6/INDEX(Economy!$H$6:$H$92,1877-1845),0)/1000000 -> 0 | O6: =M6-N6 -> 0 | P6: =M6 -> 0 | Q6: =O6 -> 0 | R6: =People!T6*assist_cost*Economy!H6/1000000 -> 0.01776 | S6: =0 -> 0 | T6: 0.99 | U6: =MAX(lfund_floor,lfund_share*T6) -> 1.25 | V6: =(I6-0)*U6/1000000 -> 0 | W6: =V6 -> 0 | Y6: Acres bought, 1851-1932 | Z6: =D92 -> 21642581
A7: 1847 | B7: 3893985 | C7: =MAX(0,B7*lfund_farm_scale-lfund_grants) -> 0 | D7: =IF(AND(lfund_on=1,$A7>=lfund_start),MIN(lfund_area-lfund_home-lfund_grants,MAX(D6,INDEX($C$6:$C$92,MIN(87,2+lfund_lead)))),0) -> 0 | E7: =D7-D6 -> 0 | F7: =lfund_price/lfund_term*(D7-IF(7-lfund_term<6,0,INDEX($D$6:$D$92,7-5-lfund_term)))/1000000 -> 0 | G7: =IF(AND(lfund_on=1,$A7>=lfund_start+1,$A7<lfund_start+1+lfund_grant_years),lfund_grants/lfund_grant_years,0) -> 0 | H7: =(E7+G7)*lfund_survey/1000000 -> 0 | I7: =IF(AND(lfund_on=1,$A7>=lfund_start),MIN(D7,MAX(I6,C7)),0) -> 0 | J7: =(W7-IF(7-lfund_inst<6,0,INDEX($W$6:$W$92,7-5-lfund_inst)))/lfund_inst*(1-lfund_default) -> 0 | K7: =G7*lfund_grant_fee*U7/1000000 -> 0 | L7: =IF(AND(lfund_on=1,$A7>=1860),lfund_home*lfund_lease_1932*($A7-1859)/(1932-1859)*lfund_rent*lfund_fee,0)/1000000 -> 0 | M7: =J7+K7+L7-F7-H7 -> 0 | N7: =IF(lfund_on=1,IF(AND($A7>=1852,$A7<=1870),lfund_police,IF(AND($A7>1870,$A7<=1890),lfund_police_late,0))*lfund_police_cost*Economy!H7/INDEX(Economy!$H$6:$H$92,1877-1845),0)/1000000 -> 0 | O7: =M7-N7 -> 0 | P7: =P6*(1+lfund_rate)+M7 -> 0 | Q7: =Q6*(1+lfund_rate)+O7 -> 0 | R7: =People!T7*assist_cost*Economy!H7/1000000 -> 0.02664 | S7: =IF(SUM(R$6:R7)>0,SUM(M$6:M7)/SUM(R$6:R7),0) -> 0 | T7: 0.99 | U7: =MAX(lfund_floor,lfund_share*T7) -> 1.25 | V7: =(I7-I6)*U7/1000000 -> 0 | W7: =W6+V7 -> 0 | Y7: Annuities paid ($m) | Z7: =SUM(F6:F92) -> 2.0997863
A8: 1848 | B8: 3893985 | C8: =MAX(0,B8*lfund_farm_scale-lfund_grants) -> 0 | D8: =IF(AND(lfund_on=1,$A8>=lfund_start),MIN(lfund_area-lfund_home-lfund_grants,MAX(D7,INDEX($C$6:$C$92,MIN(87,3+lfund_lead)))),0) -> 0 | E8: =D8-D7 -> 0 | F8: =lfund_price/lfund_term*(D8-IF(8-lfund_term<6,0,INDEX($D$6:$D$92,8-5-lfund_term)))/1000000 -> 0 | G8: =IF(AND(lfund_on=1,$A8>=lfund_start+1,$A8<lfund_start+1+lfund_grant_years),lfund_grants/lfund_grant_years,0) -> 0 | H8: =(E8+G8)*lfund_survey/1000000 -> 0 | I8: =IF(AND(lfund_on=1,$A8>=lfund_start),MIN(D8,MAX(I7,C8)),0) -> 0 | J8: =(W8-IF(8-lfund_inst<6,0,INDEX($W$6:$W$92,8-5-lfund_inst)))/lfund_inst*(1-lfund_default) -> 0 | K8: =G8*lfund_grant_fee*U8/1000000 -> 0 | L8: =IF(AND(lfund_on=1,$A8>=1860),lfund_home*lfund_lease_1932*($A8-1859)/(1932-1859)*lfund_rent*lfund_fee,0)/1000000 -> 0 | M8: =J8+K8+L8-F8-H8 -> 0 | N8: =IF(lfund_on=1,IF(AND($A8>=1852,$A8<=1870),lfund_police,IF(AND($A8>1870,$A8<=1890),lfund_police_late,0))*lfund_police_cost*Economy!H8/INDEX(Economy!$H$6:$H$92,1877-1845),0)/1000000 -> 0 | O8: =M8-N8 -> 0 | P8: =P7*(1+lfund_rate)+M8 -> 0 | Q8: =Q7*(1+lfund_rate)+O8 -> 0 | R8: =People!T8*assist_cost*Economy!H8/1000000 -> 0.27972 | S8: =IF(SUM(R$6:R8)>0,SUM(M$6:M8)/SUM(R$6:R8),0) -> 0 | T8: 0.99 | U8: =MAX(lfund_floor,lfund_share*T8) -> 1.25 | V8: =(I8-I7)*U8/1000000 -> 0 | W8: =W7+V8 -> 0 | Y8: Instalments and grant land ($m) | Z8: =SUM(J6:K92) -> 100.5164
A9: 1849 | B9: 3893985 | C9: =MAX(0,B9*lfund_farm_scale-lfund_grants) -> 0 | D9: =IF(AND(lfund_on=1,$A9>=lfund_start),MIN(lfund_area-lfund_home-lfund_grants,MAX(D8,INDEX($C$6:$C$92,MIN(87,4+lfund_lead)))),0) -> 0 | E9: =D9-D8 -> 0 | F9: =lfund_price/lfund_term*(D9-IF(9-lfund_term<6,0,INDEX($D$6:$D$92,9-5-lfund_term)))/1000000 -> 0 | G9: =IF(AND(lfund_on=1,$A9>=lfund_start+1,$A9<lfund_start+1+lfund_grant_years),lfund_grants/lfund_grant_years,0) -> 0 | H9: =(E9+G9)*lfund_survey/1000000 -> 0 | I9: =IF(AND(lfund_on=1,$A9>=lfund_start),MIN(D9,MAX(I8,C9)),0) -> 0 | J9: =(W9-IF(9-lfund_inst<6,0,INDEX($W$6:$W$92,9-5-lfund_inst)))/lfund_inst*(1-lfund_default) -> 0 | K9: =G9*lfund_grant_fee*U9/1000000 -> 0 | L9: =IF(AND(lfund_on=1,$A9>=1860),lfund_home*lfund_lease_1932*($A9-1859)/(1932-1859)*lfund_rent*lfund_fee,0)/1000000 -> 0 | M9: =J9+K9+L9-F9-H9 -> 0 | N9: =IF(lfund_on=1,IF(AND($A9>=1852,$A9<=1870),lfund_police,IF(AND($A9>1870,$A9<=1890),lfund_police_late,0))*lfund_police_cost*Economy!H9/INDEX(Economy!$H$6:$H$92,1877-1845),0)/1000000 -> 0 | O9: =M9-N9 -> 0 | P9: =P8*(1+lfund_rate)+M9 -> 0 | Q9: =Q8*(1+lfund_rate)+O9 -> 0 | R9: =People!T9*assist_cost*Economy!H9/1000000 -> 1.7930808 | S9: =IF(SUM(R$6:R9)>0,SUM(M$6:M9)/SUM(R$6:R9),0) -> 0 | T9: 0.99 | U9: =MAX(lfund_floor,lfund_share*T9) -> 1.25 | V9: =(I9-I8)*U9/1000000 -> 0 | W9: =W8+V9 -> 0 | Y9: Average sale price ($ an acre) | Z9: =IF(I92>0,W92*1000000/I92,0) -> 5.4825809
A10: 1850 | B10: 3893985 | C10: =MAX(0,B10*lfund_farm_scale-lfund_grants) -> 0 | D10: =IF(AND(lfund_on=1,$A10>=lfund_start),MIN(lfund_area-lfund_home-lfund_grants,MAX(D9,INDEX($C$6:$C$92,MIN(87,5+lfund_lead)))),0) -> 0 | E10: =D10-D9 -> 0 | F10: =lfund_price/lfund_term*(D10-IF(10-lfund_term<6,0,INDEX($D$6:$D$92,10-5-lfund_term)))/1000000 -> 0 | G10: =IF(AND(lfund_on=1,$A10>=lfund_start+1,$A10<lfund_start+1+lfund_grant_years),lfund_grants/lfund_grant_years,0) -> 0 | H10: =(E10+G10)*lfund_survey/1000000 -> 0 | I10: =IF(AND(lfund_on=1,$A10>=lfund_start),MIN(D10,MAX(I9,C10)),0) -> 0 | J10: =(W10-IF(10-lfund_inst<6,0,INDEX($W$6:$W$92,10-5-lfund_inst)))/lfund_inst*(1-lfund_default) -> 0 | K10: =G10*lfund_grant_fee*U10/1000000 -> 0 | L10: =IF(AND(lfund_on=1,$A10>=1860),lfund_home*lfund_lease_1932*($A10-1859)/(1932-1859)*lfund_rent*lfund_fee,0)/1000000 -> 0 | M10: =J10+K10+L10-F10-H10 -> 0 | N10: =IF(lfund_on=1,IF(AND($A10>=1852,$A10<=1870),lfund_police,IF(AND($A10>1870,$A10<=1890),lfund_police_late,0))*lfund_police_cost*Economy!H10/INDEX(Economy!$H$6:$H$92,1877-1845),0)/1000000 -> 0 | O10: =M10-N10 -> 0 | P10: =P9*(1+lfund_rate)+M10 -> 0 | Q10: =Q9*(1+lfund_rate)+O10 -> 0 | R10: =People!T10*assist_cost*Economy!H10/1000000 -> 1.49688 | S10: =IF(SUM(R$6:R10)>0,SUM(M$6:M10)/SUM(R$6:R10),0) -> 0 | T10: 0.99 | U10: =MAX(lfund_floor,lfund_share*T10) -> 1.25 | V10: =(I10-I9)*U10/1000000 -> 0 | W10: =W9+V10 -> 0 | Y10: Lease fees ($m) | Z10: =SUM(L6:L92) -> 0.4107
A11: 1851 | B11: 4221399 | C11: =MAX(0,B11*lfund_farm_scale-lfund_grants) -> 0 | D11: =IF(AND(lfund_on=1,$A11>=lfund_start),MIN(lfund_area-lfund_home-lfund_grants,MAX(D10,INDEX($C$6:$C$92,MIN(87,6+lfund_lead)))),0) -> 0 | E11: =D11-D10 -> 0 | F11: =lfund_price/lfund_term*(D11-IF(11-lfund_term<6,0,INDEX($D$6:$D$92,11-5-lfund_term)))/1000000 -> 0 | G11: =IF(AND(lfund_on=1,$A11>=lfund_start+1,$A11<lfund_start+1+lfund_grant_years),lfund_grants/lfund_grant_years,0) -> 0 | H11: =(E11+G11)*lfund_survey/1000000 -> 0 | I11: =IF(AND(lfund_on=1,$A11>=lfund_start),MIN(D11,MAX(I10,C11)),0) -> 0 | J11: =(W11-IF(11-lfund_inst<6,0,INDEX($W$6:$W$92,11-5-lfund_inst)))/lfund_inst*(1-lfund_default) -> 0 | K11: =G11*lfund_grant_fee*U11/1000000 -> 0 | L11: =IF(AND(lfund_on=1,$A11>=1860),lfund_home*lfund_lease_1932*($A11-1859)/(1932-1859)*lfund_rent*lfund_fee,0)/1000000 -> 0 | M11: =J11+K11+L11-F11-H11 -> 0 | N11: =IF(lfund_on=1,IF(AND($A11>=1852,$A11<=1870),lfund_police,IF(AND($A11>1870,$A11<=1890),lfund_police_late,0))*lfund_police_cost*Economy!H11/INDEX(Economy!$H$6:$H$92,1877-1845),0)/1000000 -> 0 | O11: =M11-N11 -> 0 | P11: =P10*(1+lfund_rate)+M11 -> 0 | Q11: =Q10*(1+lfund_rate)+O11 -> 0 | R11: =People!T11*assist_cost*Economy!H11/1000000 -> 1.105272 | S11: =IF(SUM(R$6:R11)>0,SUM(M$6:M11)/SUM(R$6:R11),0) -> 0 | T11: 1.18 | U11: =MAX(lfund_floor,lfund_share*T11) -> 1.25 | V11: =(I11-I10)*U11/1000000 -> 0 | W11: =W10+V11 -> 0 | Y11: Survey and register ($m) | Z11: =SUM(H6:H92) -> 0.91327743
A12: 1852 | B12: 4576344 | C12: =MAX(0,B12*lfund_farm_scale-lfund_grants) -> 0 | D12: =IF(AND(lfund_on=1,$A12>=lfund_start),MIN(lfund_area-lfund_home-lfund_grants,MAX(D11,INDEX($C$6:$C$92,MIN(87,7+lfund_lead)))),0) -> 0 | E12: =D12-D11 -> 0 | F12: =lfund_price/lfund_term*(D12-IF(12-lfund_term<6,0,INDEX($D$6:$D$92,12-5-lfund_term)))/1000000 -> 0 | G12: =IF(AND(lfund_on=1,$A12>=lfund_start+1,$A12<lfund_start+1+lfund_grant_years),lfund_grants/lfund_grant_years,0) -> 1466666.7 | H12: =(E12+G12)*lfund_survey/1000000 -> 0.044 | I12: =IF(AND(lfund_on=1,$A12>=lfund_start),MIN(D12,MAX(I11,C12)),0) -> 0 | J12: =(W12-IF(12-lfund_inst<6,0,INDEX($W$6:$W$92,12-5-lfund_inst)))/lfund_inst*(1-lfund_default) -> 0 | K12: =G12*lfund_grant_fee*U12/1000000 -> 0.091666667 | L12: =IF(AND(lfund_on=1,$A12>=1860),lfund_home*lfund_lease_1932*($A12-1859)/(1932-1859)*lfund_rent*lfund_fee,0)/1000000 -> 0 | M12: =J12+K12+L12-F12-H12 -> 0.047666667 | N12: =IF(lfund_on=1,IF(AND($A12>=1852,$A12<=1870),lfund_police,IF(AND($A12>1870,$A12<=1890),lfund_police_late,0))*lfund_police_cost*Economy!H12/INDEX(Economy!$H$6:$H$92,1877-1845),0)/1000000 -> 0.40683962 | O12: =M12-N12 -> -0.35917296 | P12: =P11*(1+lfund_rate)+M12 -> 0.047666667 | Q12: =Q11*(1+lfund_rate)+O12 -> -0.35917296 | R12: =People!T12*assist_cost*Economy!H12/1000000 -> 3.78 | S12: =IF(SUM(R$6:R12)>0,SUM(M$6:M12)/SUM(R$6:R12),0) -> 0.0056082702 | T12: 1.4 | U12: =MAX(lfund_floor,lfund_share*T12) -> 1.25 | V12: =(I12-I11)*U12/1000000 -> 0 | W12: =W11+V12 -> 0 | Y12: Land Fund net, undiscounted ($m) | Z12: =SUM(M6:M92) -> 97.914035
A13: 1853 | B13: 4961132 | C13: =MAX(0,B13*lfund_farm_scale-lfund_grants) -> 0 | D13: =IF(AND(lfund_on=1,$A13>=lfund_start),MIN(lfund_area-lfund_home-lfund_grants,MAX(D12,INDEX($C$6:$C$92,MIN(87,8+lfund_lead)))),0) -> 0 | E13: =D13-D12 -> 0 | F13: =lfund_price/lfund_term*(D13-IF(13-lfund_term<6,0,INDEX($D$6:$D$92,13-5-lfund_term)))/1000000 -> 0 | G13: =IF(AND(lfund_on=1,$A13>=lfund_start+1,$A13<lfund_start+1+lfund_grant_years),lfund_grants/lfund_grant_years,0) -> 1466666.7 | H13: =(E13+G13)*lfund_survey/1000000 -> 0.044 | I13: =IF(AND(lfund_on=1,$A13>=lfund_start),MIN(D13,MAX(I12,C13)),0) -> 0 | J13: =(W13-IF(13-lfund_inst<6,0,INDEX($W$6:$W$92,13-5-lfund_inst)))/lfund_inst*(1-lfund_default) -> 0 | K13: =G13*lfund_grant_fee*U13/1000000 -> 0.091666667 | L13: =IF(AND(lfund_on=1,$A13>=1860),lfund_home*lfund_lease_1932*($A13-1859)/(1932-1859)*lfund_rent*lfund_fee,0)/1000000 -> 0 | M13: =J13+K13+L13-F13-H13 -> 0.047666667 | N13: =IF(lfund_on=1,IF(AND($A13>=1852,$A13<=1870),lfund_police,IF(AND($A13>1870,$A13<=1890),lfund_police_late,0))*lfund_police_cost*Economy!H13/INDEX(Economy!$H$6:$H$92,1877-1845),0)/1000000 -> 0.40277123 | O13: =M13-N13 -> -0.35510456 | P13: =P12*(1+lfund_rate)+M13 -> 0.097716667 | Q13: =Q12*(1+lfund_rate)+O13 -> -0.73223616 | R13: =People!T13*assist_cost*Economy!H13/1000000 -> 2.295216 | S13: =IF(SUM(R$6:R13)>0,SUM(M$6:M13)/SUM(R$6:R13),0) -> 0.0088316018 | T13: 1.66 | U13: =MAX(lfund_floor,lfund_share*T13) -> 1.25 | V13: =(I13-I12)*U13/1000000 -> 0 | W13: =W12+V13 -> 0 | Y13: Police and commissioners ($m) | Z13: =SUM(N6:N92) -> 10.508667
A14: 1854 | B14: 5378274 | C14: =MAX(0,B14*lfund_farm_scale-lfund_grants) -> 0 | D14: =IF(AND(lfund_on=1,$A14>=lfund_start),MIN(lfund_area-lfund_home-lfund_grants,MAX(D13,INDEX($C$6:$C$92,MIN(87,9+lfund_lead)))),0) -> 0 | E14: =D14-D13 -> 0 | F14: =lfund_price/lfund_term*(D14-IF(14-lfund_term<6,0,INDEX($D$6:$D$92,14-5-lfund_term)))/1000000 -> 0 | G14: =IF(AND(lfund_on=1,$A14>=lfund_start+1,$A14<lfund_start+1+lfund_grant_years),lfund_grants/lfund_grant_years,0) -> 1466666.7 | H14: =(E14+G14)*lfund_survey/1000000 -> 0.044 | I14: =IF(AND(lfund_on=1,$A14>=lfund_start),MIN(D14,MAX(I13,C14)),0) -> 0 | J14: =(W14-IF(14-lfund_inst<6,0,INDEX($W$6:$W$92,14-5-lfund_inst)))/lfund_inst*(1-lfund_default) -> 0 | K14: =G14*lfund_grant_fee*U14/1000000 -> 0.091666667 | L14: =IF(AND(lfund_on=1,$A14>=1860),lfund_home*lfund_lease_1932*($A14-1859)/(1932-1859)*lfund_rent*lfund_fee,0)/1000000 -> 0 | M14: =J14+K14+L14-F14-H14 -> 0.047666667 | N14: =IF(lfund_on=1,IF(AND($A14>=1852,$A14<=1870),lfund_police,IF(AND($A14>1870,$A14<=1890),lfund_police_late,0))*lfund_police_cost*Economy!H14/INDEX(Economy!$H$6:$H$92,1877-1845),0)/1000000 -> 0.39463443 | O14: =M14-N14 -> -0.34696777 | P14: =P13*(1+lfund_rate)+M14 -> 0.15026917 | Q14: =Q13*(1+lfund_rate)+O14 -> -1.1158157 | R14: =People!T14*assist_cost*Economy!H14/1000000 -> 2.004408 | S14: =IF(SUM(R$6:R14)>0,SUM(M$6:M14)/SUM(R$6:R14),0) -> 0.011172768 | T14: 1.98 | U14: =MAX(lfund_floor,lfund_share*T14) -> 1.25 | V14: =(I14-I13)*U14/1000000 -> 0 | W14: =W13+V14 -> 0 | Y14: Policy net, undiscounted ($m) | Z14: =SUM(O6:O92) -> 87.405367
A15: 1855 | B15: 5830491 | C15: =MAX(0,B15*lfund_farm_scale-lfund_grants) -> 0 | D15: =IF(AND(lfund_on=1,$A15>=lfund_start),MIN(lfund_area-lfund_home-lfund_grants,MAX(D14,INDEX($C$6:$C$92,MIN(87,10+lfund_lead)))),0) -> 0 | E15: =D15-D14 -> 0 | F15: =lfund_price/lfund_term*(D15-IF(15-lfund_term<6,0,INDEX($D$6:$D$92,15-5-lfund_term)))/1000000 -> 0 | G15: =IF(AND(lfund_on=1,$A15>=lfund_start+1,$A15<lfund_start+1+lfund_grant_years),lfund_grants/lfund_grant_years,0) -> 1466666.7 | H15: =(E15+G15)*lfund_survey/1000000 -> 0.044 | I15: =IF(AND(lfund_on=1,$A15>=lfund_start),MIN(D15,MAX(I14,C15)),0) -> 0 | J15: =(W15-IF(15-lfund_inst<6,0,INDEX($W$6:$W$92,15-5-lfund_inst)))/lfund_inst*(1-lfund_default) -> 0 | K15: =G15*lfund_grant_fee*U15/1000000 -> 0.091666667 | L15: =IF(AND(lfund_on=1,$A15>=1860),lfund_home*lfund_lease_1932*($A15-1859)/(1932-1859)*lfund_rent*lfund_fee,0)/1000000 -> 0 | M15: =J15+K15+L15-F15-H15 -> 0.047666667 | N15: =IF(lfund_on=1,IF(AND($A15>=1852,$A15<=1870),lfund_police,IF(AND($A15>1870,$A15<=1890),lfund_police_late,0))*lfund_police_cost*Economy!H15/INDEX(Economy!$H$6:$H$92,1877-1845),0)/1000000 -> 0.38649764 | O15: =M15-N15 -> -0.33883097 | P15: =P14*(1+lfund_rate)+M15 -> 0.20544929 | Q15: =Q14*(1+lfund_rate)+O15 -> -1.5104375 | R15: =People!T15*assist_cost*Economy!H15/1000000 -> 1.72368 | S15: =IF(SUM(R$6:R15)>0,SUM(M$6:M15)/SUM(R$6:R15),0) -> 0.013128911 | T15: 2.35 | U15: =MAX(lfund_floor,lfund_share*T15) -> 1.25 | V15: =(I15-I14)*U15/1000000 -> 0 | W15: =W14+V15 -> 0 | Y15: Land Fund net, value in 1850 at lfund_rate ($m) | Z15: =NPV(lfund_rate,M11:M92) -> 12.504864
A16: 1856 | B16: 6320731 | C16: =MAX(0,B16*lfund_farm_scale-lfund_grants) -> 0 | D16: =IF(AND(lfund_on=1,$A16>=lfund_start),MIN(lfund_area-lfund_home-lfund_grants,MAX(D15,INDEX($C$6:$C$92,MIN(87,11+lfund_lead)))),0) -> 168256 | E16: =D16-D15 -> 168256 | F16: =lfund_price/lfund_term*(D16-IF(16-lfund_term<6,0,INDEX($D$6:$D$92,16-5-lfund_term)))/1000000 -> 0.00084128 | G16: =IF(AND(lfund_on=1,$A16>=lfund_start+1,$A16<lfund_start+1+lfund_grant_years),lfund_grants/lfund_grant_years,0) -> 1466666.7 | H16: =(E16+G16)*lfund_survey/1000000 -> 0.04904768 | I16: =IF(AND(lfund_on=1,$A16>=lfund_start),MIN(D16,MAX(I15,C16)),0) -> 0 | J16: =(W16-IF(16-lfund_inst<6,0,INDEX($W$6:$W$92,16-5-lfund_inst)))/lfund_inst*(1-lfund_default) -> 0 | K16: =G16*lfund_grant_fee*U16/1000000 -> 0.091666667 | L16: =IF(AND(lfund_on=1,$A16>=1860),lfund_home*lfund_lease_1932*($A16-1859)/(1932-1859)*lfund_rent*lfund_fee,0)/1000000 -> 0 | M16: =J16+K16+L16-F16-H16 -> 0.041777707 | N16: =IF(lfund_on=1,IF(AND($A16>=1852,$A16<=1870),lfund_police,IF(AND($A16>1870,$A16<=1890),lfund_police_late,0))*lfund_police_cost*Economy!H16/INDEX(Economy!$H$6:$H$92,1877-1845),0)/1000000 -> 0.38039505 | O16: =M16-N16 -> -0.33861734 | P16: =P15*(1+lfund_rate)+M16 -> 0.25749946 | Q16: =Q15*(1+lfund_rate)+O16 -> -1.9245767 | R16: =People!T16*assist_cost*Economy!H16/1000000 -> 1.696464 | S16: =IF(SUM(R$6:R16)>0,SUM(M$6:M16)/SUM(R$6:R16),0) -> 0.014331503 | T16: 2.79 | U16: =MAX(lfund_floor,lfund_share*T16) -> 1.25 | V16: =(I16-I15)*U16/1000000 -> 0 | W16: =W15+V16 -> 0 | Y16: Policy net, value in 1850 at lfund_rate ($m) | Z16: =NPV(lfund_rate,O11:O92) -> 7.3302414
A17: 1857 | B17: 6852191 | C17: =MAX(0,B17*lfund_farm_scale-lfund_grants) -> 0 | D17: =IF(AND(lfund_on=1,$A17>=lfund_start),MIN(lfund_area-lfund_home-lfund_grants,MAX(D16,INDEX($C$6:$C$92,MIN(87,12+lfund_lead)))),0) -> 412978 | E17: =D17-D16 -> 244722 | F17: =lfund_price/lfund_term*(D17-IF(17-lfund_term<6,0,INDEX($D$6:$D$92,17-5-lfund_term)))/1000000 -> 0.00206489 | G17: =IF(AND(lfund_on=1,$A17>=lfund_start+1,$A17<lfund_start+1+lfund_grant_years),lfund_grants/lfund_grant_years,0) -> 1466666.7 | H17: =(E17+G17)*lfund_survey/1000000 -> 0.05134166 | I17: =IF(AND(lfund_on=1,$A17>=lfund_start),MIN(D17,MAX(I16,C17)),0) -> 0 | J17: =(W17-IF(17-lfund_inst<6,0,INDEX($W$6:$W$92,17-5-lfund_inst)))/lfund_inst*(1-lfund_default) -> 0 | K17: =G17*lfund_grant_fee*U17/1000000 -> 0.091666667 | L17: =IF(AND(lfund_on=1,$A17>=1860),lfund_home*lfund_lease_1932*($A17-1859)/(1932-1859)*lfund_rent*lfund_fee,0)/1000000 -> 0 | M17: =J17+K17+L17-F17-H17 -> 0.038260117 | N17: =IF(lfund_on=1,IF(AND($A17>=1852,$A17<=1870),lfund_police,IF(AND($A17>1870,$A17<=1890),lfund_police_late,0))*lfund_police_cost*Economy!H17/INDEX(Economy!$H$6:$H$92,1877-1845),0)/1000000 -> 0.37429245 | O17: =M17-N17 -> -0.33603234 | P17: =P16*(1+lfund_rate)+M17 -> 0.30863455 | Q17: =Q16*(1+lfund_rate)+O17 -> -2.3568379 | R17: =People!T17*assist_cost*Economy!H17/1000000 -> 1.669248 | S17: =IF(SUM(R$6:R17)>0,SUM(M$6:M17)/SUM(R$6:R17),0) -> 0.015132989 | T17: 3.32 | U17: =MAX(lfund_floor,lfund_share*T17) -> 1.25 | V17: =(I17-I16)*U17/1000000 -> 0 | W17: =W16+V17 -> 0 | Y17: Lowest Land Fund balance ($m) | Z17: =MIN(P6:P92) -> 0
A18: 1858 | B18: 7428338 | C18: =MAX(0,B18*lfund_farm_scale-lfund_grants) -> 0 | D18: =IF(AND(lfund_on=1,$A18>=lfund_start),MIN(lfund_area-lfund_home-lfund_grants,MAX(D17,INDEX($C$6:$C$92,MIN(87,13+lfund_lead)))),0) -> 664378 | E18: =D18-D17 -> 251400 | F18: =lfund_price/lfund_term*(D18-IF(18-lfund_term<6,0,INDEX($D$6:$D$92,18-5-lfund_term)))/1000000 -> 0.00332189 | G18: =IF(AND(lfund_on=1,$A18>=lfund_start+1,$A18<lfund_start+1+lfund_grant_years),lfund_grants/lfund_grant_years,0) -> 0 | H18: =(E18+G18)*lfund_survey/1000000 -> 0.007542 | I18: =IF(AND(lfund_on=1,$A18>=lfund_start),MIN(D18,MAX(I17,C18)),0) -> 0 | J18: =(W18-IF(18-lfund_inst<6,0,INDEX($W$6:$W$92,18-5-lfund_inst)))/lfund_inst*(1-lfund_default) -> 0 | K18: =G18*lfund_grant_fee*U18/1000000 -> 0 | L18: =IF(AND(lfund_on=1,$A18>=1860),lfund_home*lfund_lease_1932*($A18-1859)/(1932-1859)*lfund_rent*lfund_fee,0)/1000000 -> 0 | M18: =J18+K18+L18-F18-H18 -> -0.01086389 | N18: =IF(lfund_on=1,IF(AND($A18>=1852,$A18<=1870),lfund_police,IF(AND($A18>1870,$A18<=1890),lfund_police_late,0))*lfund_police_cost*Economy!H18/INDEX(Economy!$H$6:$H$92,1877-1845),0)/1000000 -> 0.36888149 | O18: =M18-N18 -> -0.37974538 | P18: =P17*(1+lfund_rate)+M18 -> 0.31320239 | Q18: =Q17*(1+lfund_rate)+O18 -> -2.8544252 | R18: =People!T18*assist_cost*Economy!H18/1000000 -> 1.6451165 | S18: =IF(SUM(R$6:R18)>0,SUM(M$6:M18)/SUM(R$6:R18),0) -> 0.013302316 | T18: 3.95 | U18: =MAX(lfund_floor,lfund_share*T18) -> 1.25 | V18: =(I18-I17)*U18/1000000 -> 0 | W18: =W17+V18 -> 0 | Y18: First year the Land Fund is back in credit, with interest | Z18: =IF(lfund_on=0,"off",IFERROR(INDEX(A6:A92,MATCH(1,INDEX((P6:P92>=0)*(A6:A92>lfund_start+5),0),0)),"never")) -> 1857
A19: 1859 | B19: 8052928 | C19: =MAX(0,B19*lfund_farm_scale-lfund_grants) -> 0 | D19: =IF(AND(lfund_on=1,$A19>=lfund_start),MIN(lfund_area-lfund_home-lfund_grants,MAX(D18,INDEX($C$6:$C$92,MIN(87,14+lfund_lead)))),0) -> 922637 | E19: =D19-D18 -> 258259 | F19: =lfund_price/lfund_term*(D19-IF(19-lfund_term<6,0,INDEX($D$6:$D$92,19-5-lfund_term)))/1000000 -> 0.004613185 | G19: =IF(AND(lfund_on=1,$A19>=lfund_start+1,$A19<lfund_start+1+lfund_grant_years),lfund_grants/lfund_grant_years,0) -> 0 | H19: =(E19+G19)*lfund_survey/1000000 -> 0.00774777 | I19: =IF(AND(lfund_on=1,$A19>=lfund_start),MIN(D19,MAX(I18,C19)),0) -> 0 | J19: =(W19-IF(19-lfund_inst<6,0,INDEX($W$6:$W$92,19-5-lfund_inst)))/lfund_inst*(1-lfund_default) -> 0 | K19: =G19*lfund_grant_fee*U19/1000000 -> 0 | L19: =IF(AND(lfund_on=1,$A19>=1860),lfund_home*lfund_lease_1932*($A19-1859)/(1932-1859)*lfund_rent*lfund_fee,0)/1000000 -> 0 | M19: =J19+K19+L19-F19-H19 -> -0.012360955 | N19: =IF(lfund_on=1,IF(AND($A19>=1852,$A19<=1870),lfund_police,IF(AND($A19>1870,$A19<=1890),lfund_police_late,0))*lfund_police_cost*Economy!H19/INDEX(Economy!$H$6:$H$92,1877-1845),0)/1000000 -> 0.36342983 | O19: =M19-N19 -> -0.37579079 | P19: =P18*(1+lfund_rate)+M19 -> 0.31650155 | Q19: =Q18*(1+lfund_rate)+O19 -> -3.3729372 | R19: =People!T19*assist_cost*Economy!H19/1000000 -> 1.6208035 | S19: =IF(SUM(R$6:R19)>0,SUM(M$6:M19)/SUM(R$6:R19),0) -> 0.011698793 | T19: 4.69 | U19: =MAX(lfund_floor,lfund_share*T19) -> 1.25 | V19: =(I19-I18)*U19/1000000 -> 0 | W19: =W18+V19 -> 0 | Y19: First year the policy is back in credit, with interest | Z19: =IF(lfund_on=0,"off",IFERROR(INDEX(A6:A92,MATCH(1,INDEX((Q6:Q92>=0)*(A6:A92>lfund_start+5),0),0)),"never")) -> 1882
A20: 1860 | B20: 8730035 | C20: =MAX(0,B20*lfund_farm_scale-lfund_grants) -> 0 | D20: =IF(AND(lfund_on=1,$A20>=lfund_start),MIN(lfund_area-lfund_home-lfund_grants,MAX(D19,INDEX($C$6:$C$92,MIN(87,15+lfund_lead)))),0) -> 1187944 | E20: =D20-D19 -> 265307 | F20: =lfund_price/lfund_term*(D20-IF(20-lfund_term<6,0,INDEX($D$6:$D$92,20-5-lfund_term)))/1000000 -> 0.00593972 | G20: =IF(AND(lfund_on=1,$A20>=lfund_start+1,$A20<lfund_start+1+lfund_grant_years),lfund_grants/lfund_grant_years,0) -> 0 | H20: =(E20+G20)*lfund_survey/1000000 -> 0.00795921 | I20: =IF(AND(lfund_on=1,$A20>=lfund_start),MIN(D20,MAX(I19,C20)),0) -> 0 | J20: =(W20-IF(20-lfund_inst<6,0,INDEX($W$6:$W$92,20-5-lfund_inst)))/lfund_inst*(1-lfund_default) -> 0 | K20: =G20*lfund_grant_fee*U20/1000000 -> 0 | L20: =IF(AND(lfund_on=1,$A20>=1860),lfund_home*lfund_lease_1932*($A20-1859)/(1932-1859)*lfund_rent*lfund_fee,0)/1000000 -> 0.00015205479 | M20: =J20+K20+L20-F20-H20 -> -0.013746875 | N20: =IF(lfund_on=1,IF(AND($A20>=1852,$A20<=1870),lfund_police,IF(AND($A20>1870,$A20<=1890),lfund_police_late,0))*lfund_police_cost*Economy!H20/INDEX(Economy!$H$6:$H$92,1877-1845),0)/1000000 -> 0.35801887 | O20: =M20-N20 -> -0.37176574 | P20: =P19*(1+lfund_rate)+M20 -> 0.31857976 | Q20: =Q19*(1+lfund_rate)+O20 -> -3.9133498 | R20: =People!T20*assist_cost*Economy!H20/1000000 -> 1.685376 | S20: =IF(SUM(R$6:R20)>0,SUM(M$6:M20)/SUM(R$6:R20),0) -> 0.010233634 | T20: 5.58 | U20: =MAX(lfund_floor,lfund_share*T20) -> 1.25 | V20: =(I20-I19)*U20/1000000 -> 0 | W20: =W19+V20 -> 0 | Y20: Land Fund net / assisted passage, 1852-1932 | Z20: =S92 -> 0.47405336
A21: 1861 | B21: 8968256 | C21: =MAX(0,B21*lfund_farm_scale-lfund_grants) -> 168256 | D21: =IF(AND(lfund_on=1,$A21>=lfund_start),MIN(lfund_area-lfund_home-lfund_grants,MAX(D20,INDEX($C$6:$C$92,MIN(87,16+lfund_lead)))),0) -> 1460491 | E21: =D21-D20 -> 272547 | F21: =lfund_price/lfund_term*(D21-IF(21-lfund_term<6,0,INDEX($D$6:$D$92,21-5-lfund_term)))/1000000 -> 0.007302455 | G21: =IF(AND(lfund_on=1,$A21>=lfund_start+1,$A21<lfund_start+1+lfund_grant_years),lfund_grants/lfund_grant_years,0) -> 0 | H21: =(E21+G21)*lfund_survey/1000000 -> 0.00817641 | I21: =IF(AND(lfund_on=1,$A21>=lfund_start),MIN(D21,MAX(I20,C21)),0) -> 168256 | J21: =(W21-IF(21-lfund_inst<6,0,INDEX($W$6:$W$92,21-5-lfund_inst)))/lfund_inst*(1-lfund_default) -> 0.0378576 | K21: =G21*lfund_grant_fee*U21/1000000 -> 0 | L21: =IF(AND(lfund_on=1,$A21>=1860),lfund_home*lfund_lease_1932*($A21-1859)/(1932-1859)*lfund_rent*lfund_fee,0)/1000000 -> 0.00030410959 | M21: =J21+K21+L21-F21-H21 -> 0.022682845 | N21: =IF(lfund_on=1,IF(AND($A21>=1852,$A21<=1870),lfund_police,IF(AND($A21>1870,$A21<=1890),lfund_police_late,0))*lfund_police_cost*Economy!H21/INDEX(Economy!$H$6:$H$92,1877-1845),0)/1000000 -> 0.35801887 | O21: =M21-N21 -> -0.33533602 | P21: =P20*(1+lfund_rate)+M21 -> 0.35719159 | Q21: =Q20*(1+lfund_rate)+O21 -> -4.4443533 | R21: =People!T21*assist_cost*Economy!H21/1000000 -> 0.90816 | S21: =IF(SUM(R$6:R21)>0,SUM(M$6:M21)/SUM(R$6:R21),0) -> 0.010797436 | T21: 6.04 | U21: =MAX(lfund_floor,lfund_share*T21) -> 1.25 | V21: =(I21-I20)*U21/1000000 -> 0.21032 | W21: =W20+V21 -> 0.21032 | Y21: Our timeline: California's militia claims, 1850s ($m) | Z21: 1.293
A22: 1862 | B22: 9212978 | C22: =MAX(0,B22*lfund_farm_scale-lfund_grants) -> 412978 | D22: =IF(AND(lfund_on=1,$A22>=lfund_start),MIN(lfund_area-lfund_home-lfund_grants,MAX(D21,INDEX($C$6:$C$92,MIN(87,17+lfund_lead)))),0) -> 1740474 | E22: =D22-D21 -> 279983 | F22: =lfund_price/lfund_term*(D22-IF(22-lfund_term<6,0,INDEX($D$6:$D$92,22-5-lfund_term)))/1000000 -> 0.00870237 | G22: =IF(AND(lfund_on=1,$A22>=lfund_start+1,$A22<lfund_start+1+lfund_grant_years),lfund_grants/lfund_grant_years,0) -> 0 | H22: =(E22+G22)*lfund_survey/1000000 -> 0.00839949 | I22: =IF(AND(lfund_on=1,$A22>=lfund_start),MIN(D22,MAX(I21,C22)),0) -> 412978 | J22: =(W22-IF(22-lfund_inst<6,0,INDEX($W$6:$W$92,22-5-lfund_inst)))/lfund_inst*(1-lfund_default) -> 0.095474948 | K22: =G22*lfund_grant_fee*U22/1000000 -> 0 | L22: =IF(AND(lfund_on=1,$A22>=1860),lfund_home*lfund_lease_1932*($A22-1859)/(1932-1859)*lfund_rent*lfund_fee,0)/1000000 -> 0.00045616438 | M22: =J22+K22+L22-F22-H22 -> 0.078829252 | N22: =IF(lfund_on=1,IF(AND($A22>=1852,$A22<=1870),lfund_police,IF(AND($A22>1870,$A22<=1890),lfund_police_late,0))*lfund_police_cost*Economy!H22/INDEX(Economy!$H$6:$H$92,1877-1845),0)/1000000 -> 0.35801887 | O22: =M22-N22 -> -0.27918962 | P22: =P21*(1+lfund_rate)+M22 -> 0.45388042 | Q22: =Q21*(1+lfund_rate)+O22 -> -4.9457606 | R22: =People!T22*assist_cost*Economy!H22/1000000 -> 0.90816 | S22: =IF(SUM(R$6:R22)>0,SUM(M$6:M22)/SUM(R$6:R22),0) -> 0.013596896 | T22: 6.54 | U22: =MAX(lfund_floor,lfund_share*T22) -> 1.308 | V22: =(I22-I21)*U22/1000000 -> 0.32009638 | W22: =W21+V22 -> 0.53041638
A23: 1863 | B23: 9464378 | C23: =MAX(0,B23*lfund_farm_scale-lfund_grants) -> 664378 | D23: =IF(AND(lfund_on=1,$A23>=lfund_start),MIN(lfund_area-lfund_home-lfund_grants,MAX(D22,INDEX($C$6:$C$92,MIN(87,18+lfund_lead)))),0) -> 2028098 | E23: =D23-D22 -> 287624 | F23: =lfund_price/lfund_term*(D23-IF(23-lfund_term<6,0,INDEX($D$6:$D$92,23-5-lfund_term)))/1000000 -> 0.01014049 | G23: =IF(AND(lfund_on=1,$A23>=lfund_start+1,$A23<lfund_start+1+lfund_grant_years),lfund_grants/lfund_grant_years,0) -> 0 | H23: =(E23+G23)*lfund_survey/1000000 -> 0.00862872 | I23: =IF(AND(lfund_on=1,$A23>=lfund_start),MIN(D23,MAX(I22,C23)),0) -> 664378 | J23: =(W23-IF(23-lfund_inst<6,0,INDEX($W$6:$W$92,23-5-lfund_inst)))/lfund_inst*(1-lfund_default) -> 0.15946128 | K23: =G23*lfund_grant_fee*U23/1000000 -> 0 | L23: =IF(AND(lfund_on=1,$A23>=1860),lfund_home*lfund_lease_1932*($A23-1859)/(1932-1859)*lfund_rent*lfund_fee,0)/1000000 -> 0.00060821918 | M23: =J23+K23+L23-F23-H23 -> 0.14130028 | N23: =IF(lfund_on=1,IF(AND($A23>=1852,$A23<=1870),lfund_police,IF(AND($A23>1870,$A23<=1890),lfund_police_late,0))*lfund_police_cost*Economy!H23/INDEX(Economy!$H$6:$H$92,1877-1845),0)/1000000 -> 0.36749823 | O23: =M23-N23 -> -0.22619795 | P23: =P22*(1+lfund_rate)+M23 -> 0.61787473 | Q23: =Q22*(1+lfund_rate)+O23 -> -5.4192466 | R23: =People!T23*assist_cost*Economy!H23/1000000 -> 0.9322056 | S23: =IF(SUM(R$6:R23)>0,SUM(M$6:M23)/SUM(R$6:R23),0) -> 0.018623636 | T23: 7.07 | U23: =MAX(lfund_floor,lfund_share*T23) -> 1.414 | V23: =(I23-I22)*U23/1000000 -> 0.3554796 | W23: =W22+V23 -> 0.88589598
A24: 1864 | B24: 9722637 | C24: =MAX(0,B24*lfund_farm_scale-lfund_grants) -> 922637 | D24: =IF(AND(lfund_on=1,$A24>=lfund_start),MIN(lfund_area-lfund_home-lfund_grants,MAX(D23,INDEX($C$6:$C$92,MIN(87,19+lfund_lead)))),0) -> 2323570 | E24: =D24-D23 -> 295472 | F24: =lfund_price/lfund_term*(D24-IF(24-lfund_term<6,0,INDEX($D$6:$D$92,24-5-lfund_term)))/1000000 -> 0.01161785 | G24: =IF(AND(lfund_on=1,$A24>=lfund_start+1,$A24<lfund_start+1+lfund_grant_years),lfund_grants/lfund_grant_years,0) -> 0 | H24: =(E24+G24)*lfund_survey/1000000 -> 0.00886416 | I24: =IF(AND(lfund_on=1,$A24>=lfund_start),MIN(D24,MAX(I23,C24)),0) -> 922637 | J24: =(W24-IF(24-lfund_inst<6,0,INDEX($W$6:$W$92,24-5-lfund_inst)))/lfund_inst*(1-lfund_default) -> 0.2305858 | K24: =G24*lfund_grant_fee*U24/1000000 -> 0 | L24: =IF(AND(lfund_on=1,$A24>=1860),lfund_home*lfund_lease_1932*($A24-1859)/(1932-1859)*lfund_rent*lfund_fee,0)/1000000 -> 0.00076027397 | M24: =J24+K24+L24-F24-H24 -> 0.21086407 | N24: =IF(lfund_on=1,IF(AND($A24>=1852,$A24<=1870),lfund_police,IF(AND($A24>1870,$A24<=1890),lfund_police_late,0))*lfund_police_cost*Economy!H24/INDEX(Economy!$H$6:$H$92,1877-1845),0)/1000000 -> 0.37701828 | O24: =M24-N24 -> -0.16615421 | P24: =P23*(1+lfund_rate)+M24 -> 0.85963253 | Q24: =Q23*(1+lfund_rate)+O24 -> -5.8563631 | R24: =People!T24*assist_cost*Economy!H24/1000000 -> 0.9563544 | S24: =IF(SUM(R$6:R24)>0,SUM(M$6:M24)/SUM(R$6:R24),0) -> 0.02589644 | T24: 7.65 | U24: =MAX(lfund_floor,lfund_share*T24) -> 1.53 | V24: =(I24-I23)*U24/1000000 -> 0.39513627 | W24: =W23+V24 -> 1.2810322
A25: 1865 | B25: 9987944 | C25: =MAX(0,B25*lfund_farm_scale-lfund_grants) -> 1187944 | D25: =IF(AND(lfund_on=1,$A25>=lfund_start),MIN(lfund_area-lfund_home-lfund_grants,MAX(D24,INDEX($C$6:$C$92,MIN(87,20+lfund_lead)))),0) -> 2627105 | E25: =D25-D24 -> 303535 | F25: =lfund_price/lfund_term*(D25-IF(25-lfund_term<6,0,INDEX($D$6:$D$92,25-5-lfund_term)))/1000000 -> 0.013135525 | G25: =IF(AND(lfund_on=1,$A25>=lfund_start+1,$A25<lfund_start+1+lfund_grant_years),lfund_grants/lfund_grant_years,0) -> 0 | H25: =(E25+G25)*lfund_survey/1000000 -> 0.00910605 | I25: =IF(AND(lfund_on=1,$A25>=lfund_start),MIN(D25,MAX(I24,C25)),0) -> 1187944 | J25: =(W25-IF(25-lfund_inst<6,0,INDEX($W$6:$W$92,25-5-lfund_inst)))/lfund_inst*(1-lfund_default) -> 0.30966851 | K25: =G25*lfund_grant_fee*U25/1000000 -> 0 | L25: =IF(AND(lfund_on=1,$A25>=1860),lfund_home*lfund_lease_1932*($A25-1859)/(1932-1859)*lfund_rent*lfund_fee,0)/1000000 -> 0.00091232877 | M25: =J25+K25+L25-F25-H25 -> 0.28833927 | N25: =IF(lfund_on=1,IF(AND($A25>=1852,$A25<=1870),lfund_police,IF(AND($A25>1870,$A25<=1890),lfund_police_late,0))*lfund_police_cost*Economy!H25/INDEX(Economy!$H$6:$H$92,1877-1845),0)/1000000 -> 0.38649764 | O25: =M25-N25 -> -0.098158373 | P25: =P24*(1+lfund_rate)+M25 -> 1.1909534 | Q25: =Q24*(1+lfund_rate)+O25 -> -6.2473397 | R25: =People!T25*assist_cost*Economy!H25/1000000 -> 0.9804 | S25: =IF(SUM(R$6:R25)>0,SUM(M$6:M25)/SUM(R$6:R25),0) -> 0.035449607 | T25: 8.28 | U25: =MAX(lfund_floor,lfund_share*T25) -> 1.656 | V25: =(I25-I24)*U25/1000000 -> 0.43934839 | W25: =W24+V25 -> 1.7203806
A26: 1866 | B26: 10260491 | C26: =MAX(0,B26*lfund_farm_scale-lfund_grants) -> 1460491 | D26: =IF(AND(lfund_on=1,$A26>=lfund_start),MIN(lfund_area-lfund_home-lfund_grants,MAX(D25,INDEX($C$6:$C$92,MIN(87,21+lfund_lead)))),0) -> 3061429 | E26: =D26-D25 -> 434324 | F26: =lfund_price/lfund_term*(D26-IF(26-lfund_term<6,0,INDEX($D$6:$D$92,26-5-lfund_term)))/1000000 -> 0.015307145 | G26: =IF(AND(lfund_on=1,$A26>=lfund_start+1,$A26<lfund_start+1+lfund_grant_years),lfund_grants/lfund_grant_years,0) -> 0 | H26: =(E26+G26)*lfund_survey/1000000 -> 0.01302972 | I26: =IF(AND(lfund_on=1,$A26>=lfund_start),MIN(D26,MAX(I25,C26)),0) -> 1460491 | J26: =(W26-IF(26-lfund_inst<6,0,INDEX($W$6:$W$92,26-5-lfund_inst)))/lfund_inst*(1-lfund_default) -> 0.35982179 | K26: =G26*lfund_grant_fee*U26/1000000 -> 0 | L26: =IF(AND(lfund_on=1,$A26>=1860),lfund_home*lfund_lease_1932*($A26-1859)/(1932-1859)*lfund_rent*lfund_fee,0)/1000000 -> 0.0010643836 | M26: =J26+K26+L26-F26-H26 -> 0.33254931 | N26: =IF(lfund_on=1,IF(AND($A26>=1852,$A26<=1870),lfund_police,IF(AND($A26>1870,$A26<=1890),lfund_police_late,0))*lfund_police_cost*Economy!H26/INDEX(Economy!$H$6:$H$92,1877-1845),0)/1000000 -> 0.38649764 | O26: =M26-N26 -> -0.053948331 | P26: =P25*(1+lfund_rate)+M26 -> 1.5830504 | Q26: =Q25*(1+lfund_rate)+O26 -> -6.613655 | R26: =People!T26*assist_cost*Economy!H26/1000000 -> 2.0064 | S26: =IF(SUM(R$6:R26)>0,SUM(M$6:M26)/SUM(R$6:R26),0) -> 0.044302005 | T26: 8.97 | U26: =MAX(lfund_floor,lfund_share*T26) -> 1.794 | V26: =(I26-I25)*U26/1000000 -> 0.48894932 | W26: =W25+V26 -> 2.20933
A27: 1867 | B27: 10540474 | C27: =MAX(0,B27*lfund_farm_scale-lfund_grants) -> 1740474 | D27: =IF(AND(lfund_on=1,$A27>=lfund_start),MIN(lfund_area-lfund_home-lfund_grants,MAX(D26,INDEX($C$6:$C$92,MIN(87,22+lfund_lead)))),0) -> 3512262 | E27: =D27-D26 -> 450833 | F27: =lfund_price/lfund_term*(D27-IF(27-lfund_term<6,0,INDEX($D$6:$D$92,27-5-lfund_term)))/1000000 -> 0.01756131 | G27: =IF(AND(lfund_on=1,$A27>=lfund_start+1,$A27<lfund_start+1+lfund_grant_years),lfund_grants/lfund_grant_years,0) -> 0 | H27: =(E27+G27)*lfund_survey/1000000 -> 0.01352499 | I27: =IF(AND(lfund_on=1,$A27>=lfund_start),MIN(D27,MAX(I26,C27)),0) -> 1740474 | J27: =(W27-IF(27-lfund_inst<6,0,INDEX($W$6:$W$92,27-5-lfund_inst)))/lfund_inst*(1-lfund_default) -> 0.39997451 | K27: =G27*lfund_grant_fee*U27/1000000 -> 0 | L27: =IF(AND(lfund_on=1,$A27>=1860),lfund_home*lfund_lease_1932*($A27-1859)/(1932-1859)*lfund_rent*lfund_fee,0)/1000000 -> 0.0012164384 | M27: =J27+K27+L27-F27-H27 -> 0.37010465 | N27: =IF(lfund_on=1,IF(AND($A27>=1852,$A27<=1870),lfund_police,IF(AND($A27>1870,$A27<=1890),lfund_police_late,0))*lfund_police_cost*Economy!H27/INDEX(Economy!$H$6:$H$92,1877-1845),0)/1000000 -> 0.38649764 | O27: =M27-N27 -> -0.016392995 | P27: =P26*(1+lfund_rate)+M27 -> 2.0323076 | Q27: =Q26*(1+lfund_rate)+O27 -> -6.9607307 | R27: =People!T27*assist_cost*Economy!H27/1000000 -> 2.0064 | S27: =IF(SUM(R$6:R27)>0,SUM(M$6:M27)/SUM(R$6:R27),0) -> 0.053218848 | T27: 9.7 | U27: =MAX(lfund_floor,lfund_share*T27) -> 1.94 | V27: =(I27-I26)*U27/1000000 -> 0.54316702 | W27: =W26+V27 -> 2.752497
A28: 1868 | B28: 10828098 | C28: =MAX(0,B28*lfund_farm_scale-lfund_grants) -> 2028098 | D28: =IF(AND(lfund_on=1,$A28>=lfund_start),MIN(lfund_area-lfund_home-lfund_grants,MAX(D27,INDEX($C$6:$C$92,MIN(87,23+lfund_lead)))),0) -> 3980229 | E28: =D28-D27 -> 467967 | F28: =lfund_price/lfund_term*(D28-IF(28-lfund_term<6,0,INDEX($D$6:$D$92,28-5-lfund_term)))/1000000 -> 0.019901145 | G28: =IF(AND(lfund_on=1,$A28>=lfund_start+1,$A28<lfund_start+1+lfund_grant_years),lfund_grants/lfund_grant_years,0) -> 0 | H28: =(E28+G28)*lfund_survey/1000000 -> 0.01403901 | I28: =IF(AND(lfund_on=1,$A28>=lfund_start),MIN(D28,MAX(I27,C28)),0) -> 2028098 | J28: =(W28-IF(28-lfund_inst<6,0,INDEX($W$6:$W$92,28-5-lfund_inst)))/lfund_inst*(1-lfund_default) -> 0.44471005 | K28: =G28*lfund_grant_fee*U28/1000000 -> 0 | L28: =IF(AND(lfund_on=1,$A28>=1860),lfund_home*lfund_lease_1932*($A28-1859)/(1932-1859)*lfund_rent*lfund_fee,0)/1000000 -> 0.0013684932 | M28: =J28+K28+L28-F28-H28 -> 0.41213839 | N28: =IF(lfund_on=1,IF(AND($A28>=1852,$A28<=1870),lfund_police,IF(AND($A28>1870,$A28<=1890),lfund_police_late,0))*lfund_police_cost*Economy!H28/INDEX(Economy!$H$6:$H$92,1877-1845),0)/1000000 -> 0.38649764 | O28: =M28-N28 -> 0.025640749 | P28: =P27*(1+lfund_rate)+M28 -> 2.5460613 | Q28: =Q27*(1+lfund_rate)+O28 -> -7.2831265 | R28: =People!T28*assist_cost*Economy!H28/1000000 -> 2.166 | S28: =IF(SUM(R$6:R28)>0,SUM(M$6:M28)/SUM(R$6:R28),0) -> 0.06202696 | T28: 10.5 | U28: =MAX(lfund_floor,lfund_share*T28) -> 2.1 | V28: =(I28-I27)*U28/1000000 -> 0.6040104 | W28: =W27+V28 -> 3.3565074
A29: 1869 | B29: 11123570 | C29: =MAX(0,B29*lfund_farm_scale-lfund_grants) -> 2323570 | D29: =IF(AND(lfund_on=1,$A29>=lfund_start),MIN(lfund_area-lfund_home-lfund_grants,MAX(D28,INDEX($C$6:$C$92,MIN(87,24+lfund_lead)))),0) -> 4465984 | E29: =D29-D28 -> 485755 | F29: =lfund_price/lfund_term*(D29-IF(29-lfund_term<6,0,INDEX($D$6:$D$92,29-5-lfund_term)))/1000000 -> 0.02232992 | G29: =IF(AND(lfund_on=1,$A29>=lfund_start+1,$A29<lfund_start+1+lfund_grant_years),lfund_grants/lfund_grant_years,0) -> 0 | H29: =(E29+G29)*lfund_survey/1000000 -> 0.01457265 | I29: =IF(AND(lfund_on=1,$A29>=lfund_start),MIN(D29,MAX(I28,C29)),0) -> 2323570 | J29: =(W29-IF(29-lfund_inst<6,0,INDEX($W$6:$W$92,29-5-lfund_inst)))/lfund_inst*(1-lfund_default) -> 0.49452812 | K29: =G29*lfund_grant_fee*U29/1000000 -> 0 | L29: =IF(AND(lfund_on=1,$A29>=1860),lfund_home*lfund_lease_1932*($A29-1859)/(1932-1859)*lfund_rent*lfund_fee,0)/1000000 -> 0.0015205479 | M29: =J29+K29+L29-F29-H29 -> 0.4591461 | N29: =IF(lfund_on=1,IF(AND($A29>=1852,$A29<=1870),lfund_police,IF(AND($A29>1870,$A29<=1890),lfund_police_late,0))*lfund_police_cost*Economy!H29/INDEX(Economy!$H$6:$H$92,1877-1845),0)/1000000 -> 0.38649764 | O29: =M29-N29 -> 0.072648459 | P29: =P28*(1+lfund_rate)+M29 -> 3.1325105 | Q29: =Q28*(1+lfund_rate)+O29 -> -7.5746344 | R29: =People!T29*assist_cost*Economy!H29/1000000 -> 2.39856 | S29: =IF(SUM(R$6:R29)>0,SUM(M$6:M29)/SUM(R$6:R29),0) -> 0.070623938 | T29: 11.37 | U29: =MAX(lfund_floor,lfund_share*T29) -> 2.274 | V29: =(I29-I28)*U29/1000000 -> 0.67190333 | W29: =W28+V29 -> 4.0284107
A30: 1870 | B30: 11427105 | C30: =MAX(0,B30*lfund_farm_scale-lfund_grants) -> 2627105 | D30: =IF(AND(lfund_on=1,$A30>=lfund_start),MIN(lfund_area-lfund_home-lfund_grants,MAX(D29,INDEX($C$6:$C$92,MIN(87,25+lfund_lead)))),0) -> 4970201 | E30: =D30-D29 -> 504217 | F30: =lfund_price/lfund_term*(D30-IF(30-lfund_term<6,0,INDEX($D$6:$D$92,30-5-lfund_term)))/1000000 -> 0.024851005 | G30: =IF(AND(lfund_on=1,$A30>=lfund_start+1,$A30<lfund_start+1+lfund_grant_years),lfund_grants/lfund_grant_years,0) -> 0 | H30: =(E30+G30)*lfund_survey/1000000 -> 0.01512651 | I30: =IF(AND(lfund_on=1,$A30>=lfund_start),MIN(D30,MAX(I29,C30)),0) -> 2627105 | J30: =(W30-IF(30-lfund_inst<6,0,INDEX($W$6:$W$92,30-5-lfund_inst)))/lfund_inst*(1-lfund_default) -> 0.54985071 | K30: =G30*lfund_grant_fee*U30/1000000 -> 0 | L30: =IF(AND(lfund_on=1,$A30>=1860),lfund_home*lfund_lease_1932*($A30-1859)/(1932-1859)*lfund_rent*lfund_fee,0)/1000000 -> 0.0016726027 | M30: =J30+K30+L30-F30-H30 -> 0.5115458 | N30: =IF(lfund_on=1,IF(AND($A30>=1852,$A30<=1870),lfund_police,IF(AND($A30>1870,$A30<=1890),lfund_police_late,0))*lfund_police_cost*Economy!H30/INDEX(Economy!$H$6:$H$92,1877-1845),0)/1000000 -> 0.38649764 | O30: =M30-N30 -> 0.12504816 | P30: =P29*(1+lfund_rate)+M30 -> 3.8006818 | Q30: =Q29*(1+lfund_rate)+O30 -> -7.8283179 | R30: =People!T30*assist_cost*Economy!H30/1000000 -> 2.4054 | S30: =IF(SUM(R$6:R30)>0,SUM(M$6:M30)/SUM(R$6:R30),0) -> 0.079496629 | T30: 12.3 | U30: =MAX(lfund_floor,lfund_share*T30) -> 2.46 | V30: =(I30-I29)*U30/1000000 -> 0.7466961 | W30: =W29+V30 -> 4.7751068
A31: 1871 | B31: 11861429 | C31: =MAX(0,B31*lfund_farm_scale-lfund_grants) -> 3061429 | D31: =IF(AND(lfund_on=1,$A31>=lfund_start),MIN(lfund_area-lfund_home-lfund_grants,MAX(D30,INDEX($C$6:$C$92,MIN(87,26+lfund_lead)))),0) -> 5493582 | E31: =D31-D30 -> 523381 | F31: =lfund_price/lfund_term*(D31-IF(31-lfund_term<6,0,INDEX($D$6:$D$92,31-5-lfund_term)))/1000000 -> 0.02746791 | G31: =IF(AND(lfund_on=1,$A31>=lfund_start+1,$A31<lfund_start+1+lfund_grant_years),lfund_grants/lfund_grant_years,0) -> 0 | H31: =(E31+G31)*lfund_survey/1000000 -> 0.01570143 | I31: =IF(AND(lfund_on=1,$A31>=lfund_start),MIN(D31,MAX(I30,C31)),0) -> 3061429 | J31: =(W31-IF(31-lfund_inst<6,0,INDEX($W$6:$W$92,31-5-lfund_inst)))/lfund_inst*(1-lfund_default) -> 0.65900556 | K31: =G31*lfund_grant_fee*U31/1000000 -> 0 | L31: =IF(AND(lfund_on=1,$A31>=1860),lfund_home*lfund_lease_1932*($A31-1859)/(1932-1859)*lfund_rent*lfund_fee,0)/1000000 -> 0.0018246575 | M31: =J31+K31+L31-F31-H31 -> 0.61766087 | N31: =IF(lfund_on=1,IF(AND($A31>=1852,$A31<=1870),lfund_police,IF(AND($A31>1870,$A31<=1890),lfund_police_late,0))*lfund_police_cost*Economy!H31/INDEX(Economy!$H$6:$H$92,1877-1845),0)/1000000 -> 0.19040094 | O31: =M31-N31 -> 0.42725993 | P31: =P30*(1+lfund_rate)+M31 -> 4.6083768 | Q31: =Q30*(1+lfund_rate)+O31 -> -7.7924739 | R31: =People!T31*assist_cost*Economy!H31/1000000 -> 2.369952 | S31: =IF(SUM(R$6:R31)>0,SUM(M$6:M31)/SUM(R$6:R31),0) -> 0.089997664 | T31: 12.61 | U31: =MAX(lfund_floor,lfund_share*T31) -> 2.522 | V31: =(I31-I30)*U31/1000000 -> 1.0953651 | W31: =W30+V31 -> 5.8704719
